{
  "cursor": "sha256:bb3e63cce973c1b8ee630334b61208d1bc5e8cecef951189b2f2542a3b755e65",
  "prev_cursor": "sha256:745606160b0358e37d7291d003992b373fcb008b3b916ab1c3f95023f28442b9",
  "changed": true,
  "generated_at": "2026-03-14T17:44:34Z",
  "ttl_sec": 1800,
  "latest_url": "/diff/pypi_recent_updates/latest.json",
  "_protocol": {
    "standard": "ddv1",
    "spec": "/.well-known/diffdelta.json",
    "usage": "cursor SAME=no changes, STOP. counts.items>0→fetch latest_url. Schema guide in spec."
  },
  "counts": {
    "items": 40,
    "updated": 0,
    "removed": 0
  }
}
