{
  "schema_version": "1.2.0",
  "generated_at": "2026-03-11T08:59:15Z",
  "source_id": "pypi_recent_updates",
  "hash": "sha256:93f490e5154e0e3278beb1948a6640ab80b9a54bdddaed0adbeba6ad10e01a8d",
  "prev_hash": "sha256:0b70ad8678668f84350669f011b100e9ed50e18c595d318198bcee5ea3a04dd6",
  "cursor": "sha256:4c3c1b120c985b44e78f3929cf1e6e20516fa3a45a601770cbcf8d67b52735ea",
  "prev_cursor": "sha256:2cf113caaac6e4ecff9b899bb261da770375c2a9575a4ac7f01800e8a1fea7d8",
  "changed": true,
  "ttl_sec": 1800,
  "sources_included": [
    "pypi_recent_updates"
  ],
  "batch_narrative": "pypi_recent_updates: 40 releases (38 stable, 2 pre-release).",
  "buckets": {
    "items": [
      {
        "source": "pypi_recent_updates",
        "id": "bc19dd4d7115521f44c2c483c2deaaec",
        "url": "https://pypi.org/project/specatwrap7/0.2.0/",
        "published_at": "2026-03-11T08:58:58Z",
        "updated_at": "2026-03-11T08:58:58Z",
        "headline": "specatwrap7 0.2.0",
        "content": {
          "excerpt_text": "A simple wrapper",
          "lang": "en"
        },
        "provenance": {
          "fetched_at": "2026-03-11T08:59:15Z",
          "evidence_urls": [
            "https://pypi.org/project/specatwrap7/0.2.0/"
          ],
          "content_hash": "sha256:4e38210a20b608cb7ebaef714116c7cfa2f07af1d91ef1ebfaf153921b1d22fe"
        },
        "signals": {
          "release": {
            "version": "0.2.0",
            "provenance": {
              "method": "title_regex",
              "authority": "PyPI Recent Updates",
              "authority_url": "https://pypi.org",
              "evidence_url": "https://pypi.org/project/specatwrap7/0.2.0/"
            }
          }
        }
      },
      {
        "source": "pypi_recent_updates",
        "id": "7a76e02040507bf4a5b9194c05016c2e",
        "url": "https://pypi.org/project/e-chem/0.0.0/",
        "published_at": "2026-03-11T08:58:39Z",
        "updated_at": "2026-03-11T08:58:39Z",
        "headline": "e-chem 0.0.0",
        "content": {
          "excerpt_text": "echemkit is a lightweight Python library designed for seamless electrochemical data analysis.",
          "lang": "en"
        },
        "provenance": {
          "fetched_at": "2026-03-11T08:59:15Z",
          "evidence_urls": [
            "https://pypi.org/project/e-chem/0.0.0/"
          ],
          "content_hash": "sha256:18f26e84e123672891999905ed7cc39298ff17265a9ae5dc39ae59c33ac1cf5b"
        },
        "signals": {
          "release": {
            "version": "0.0.0",
            "provenance": {
              "method": "title_regex",
              "authority": "PyPI Recent Updates",
              "authority_url": "https://pypi.org",
              "evidence_url": "https://pypi.org/project/e-chem/0.0.0/"
            }
          }
        }
      },
      {
        "source": "pypi_recent_updates",
        "id": "3f2afeb394e0e89b71aaddafb932dfcb",
        "url": "https://pypi.org/project/acroform/0.2.2/",
        "published_at": "2026-03-11T08:58:39Z",
        "updated_at": "2026-03-11T08:58:39Z",
        "headline": "acroform 0.2.2",
        "content": {
          "excerpt_text": "High-level PDF form manipulation library - Python bindings",
          "lang": "en"
        },
        "provenance": {
          "fetched_at": "2026-03-11T08:59:15Z",
          "evidence_urls": [
            "https://pypi.org/project/acroform/0.2.2/"
          ],
          "content_hash": "sha256:51603e7073f648074cae842308a30112a0a5076d7b73382eddc6dc82ae29b37a"
        },
        "signals": {
          "release": {
            "version": "0.2.2",
            "provenance": {
              "method": "title_regex",
              "authority": "PyPI Recent Updates",
              "authority_url": "https://pypi.org",
              "evidence_url": "https://pypi.org/project/acroform/0.2.2/"
            }
          }
        }
      },
      {
        "source": "pypi_recent_updates",
        "id": "9a2decb245574dc6a4e55ec9ac747cd7",
        "url": "https://pypi.org/project/agentseal/0.6.2/",
        "published_at": "2026-03-11T08:58:38Z",
        "updated_at": "2026-03-11T08:58:38Z",
        "headline": "agentseal 0.6.2",
        "content": {
          "excerpt_text": "Security toolkit for AI agents - machine scan for dangerous skills/MCP configs + prompt injection/extraction testing",
          "lang": "en"
        },
        "provenance": {
          "fetched_at": "2026-03-11T08:59:15Z",
          "evidence_urls": [
            "https://pypi.org/project/agentseal/0.6.2/"
          ],
          "content_hash": "sha256:5ad71f440916d55e46e5c842fd44869f64924b4901d6313f56006b3e856b5d84"
        },
        "signals": {
          "release": {
            "version": "0.6.2",
            "provenance": {
              "method": "title_regex",
              "authority": "PyPI Recent Updates",
              "authority_url": "https://pypi.org",
              "evidence_url": "https://pypi.org/project/agentseal/0.6.2/"
            }
          }
        }
      },
      {
        "source": "pypi_recent_updates",
        "id": "c8b772e83586c92952c8c9b7e66c0357",
        "url": "https://pypi.org/project/passagemath-gap/10.8.2/",
        "published_at": "2026-03-11T08:58:33Z",
        "updated_at": "2026-03-11T08:58:33Z",
        "headline": "passagemath-gap 10.8.2",
        "content": {
          "excerpt_text": "passagemath: Computational Group Theory with GAP",
          "lang": "en"
        },
        "provenance": {
          "fetched_at": "2026-03-11T08:59:15Z",
          "evidence_urls": [
            "https://pypi.org/project/passagemath-gap/10.8.2/"
          ],
          "content_hash": "sha256:f935b02a831d1d3c9a76c620444f6353f46d97afdb182c9159acde037245c14e"
        },
        "signals": {
          "release": {
            "version": "10.8.2",
            "provenance": {
              "method": "title_regex",
              "authority": "PyPI Recent Updates",
              "authority_url": "https://pypi.org",
              "evidence_url": "https://pypi.org/project/passagemath-gap/10.8.2/"
            }
          }
        }
      },
      {
        "source": "pypi_recent_updates",
        "id": "0d765ffe33eca11df57594d0568738af",
        "url": "https://pypi.org/project/2u-enterprise-data/10.22.1/",
        "published_at": "2026-03-11T08:58:15Z",
        "updated_at": "2026-03-11T08:58:15Z",
        "headline": "2u-enterprise-data 10.22.1",
        "content": {
          "excerpt_text": "Enterprise Reporting",
          "lang": "en"
        },
        "provenance": {
          "fetched_at": "2026-03-11T08:59:15Z",
          "evidence_urls": [
            "https://pypi.org/project/2u-enterprise-data/10.22.1/"
          ],
          "content_hash": "sha256:a89358033beb7a801ac073612c37adb4eb2aec92527420130a2dadf68018321e"
        },
        "signals": {
          "release": {
            "version": "10.22.1",
            "provenance": {
              "method": "title_regex",
              "authority": "PyPI Recent Updates",
              "authority_url": "https://pypi.org",
              "evidence_url": "https://pypi.org/project/2u-enterprise-data/10.22.1/"
            }
          }
        }
      },
      {
        "source": "pypi_recent_updates",
        "id": "2b44dfdd591d0b97c644ebde3fb14226",
        "url": "https://pypi.org/project/orthoshapelab/0.1.0/",
        "published_at": "2026-03-11T08:58:09Z",
        "updated_at": "2026-03-11T08:58:09Z",
        "headline": "orthoshapelab 0.1.0",
        "content": {
          "excerpt_text": "Interactive PCA viewer for 3D statistical shape models",
          "lang": "en"
        },
        "provenance": {
          "fetched_at": "2026-03-11T08:59:15Z",
          "evidence_urls": [
            "https://pypi.org/project/orthoshapelab/0.1.0/"
          ],
          "content_hash": "sha256:65ae64f5549da9a7a16f6935850a3f906e058d7f7c5c5bc2697b12690aff1511"
        },
        "signals": {
          "release": {
            "version": "0.1.0",
            "provenance": {
              "method": "title_regex",
              "authority": "PyPI Recent Updates",
              "authority_url": "https://pypi.org",
              "evidence_url": "https://pypi.org/project/orthoshapelab/0.1.0/"
            }
          }
        }
      },
      {
        "source": "pypi_recent_updates",
        "id": "9b1ff2d452966e6cd981ee6db31dfe05",
        "url": "https://pypi.org/project/wordlift-sdk/6.12.4/",
        "published_at": "2026-03-11T08:58:09Z",
        "updated_at": "2026-03-11T08:58:09Z",
        "headline": "wordlift-sdk 6.12.4",
        "content": {
          "excerpt_text": "Python toolkit for orchestrating WordLift imports and structured data workflows.",
          "lang": "en"
        },
        "provenance": {
          "fetched_at": "2026-03-11T08:59:15Z",
          "evidence_urls": [
            "https://pypi.org/project/wordlift-sdk/6.12.4/"
          ],
          "content_hash": "sha256:686055b1e42af89c90e5d5d4bbd1b26eb75f7838d3387fb5075ef8f7b57d3bf8"
        },
        "signals": {
          "release": {
            "version": "6.12.4",
            "provenance": {
              "method": "title_regex",
              "authority": "PyPI Recent Updates",
              "authority_url": "https://pypi.org",
              "evidence_url": "https://pypi.org/project/wordlift-sdk/6.12.4/"
            }
          }
        }
      },
      {
        "source": "pypi_recent_updates",
        "id": "96726c6addb6fb1599389114d03474d1",
        "url": "https://pypi.org/project/passagemath-frobby/10.8.2/",
        "published_at": "2026-03-11T08:58:00Z",
        "updated_at": "2026-03-11T08:58:00Z",
        "headline": "passagemath-frobby 10.8.2",
        "content": {
          "excerpt_text": "passagemath: Computations on monomial ideals with Frobby",
          "lang": "en"
        },
        "provenance": {
          "fetched_at": "2026-03-11T08:59:15Z",
          "evidence_urls": [
            "https://pypi.org/project/passagemath-frobby/10.8.2/"
          ],
          "content_hash": "sha256:be01d8a8a8fab2dbe90515e67b7e6a1ccc2dcd0c81a4a951cf6b40a8ca069d05"
        },
        "signals": {
          "release": {
            "version": "10.8.2",
            "provenance": {
              "method": "title_regex",
              "authority": "PyPI Recent Updates",
              "authority_url": "https://pypi.org",
              "evidence_url": "https://pypi.org/project/passagemath-frobby/10.8.2/"
            }
          }
        }
      },
      {
        "source": "pypi_recent_updates",
        "id": "2dc25bbe1e720572cd7d9ae9df4cc429",
        "url": "https://pypi.org/project/fp-convert/0.5.0/",
        "published_at": "2026-03-11T08:57:57Z",
        "updated_at": "2026-03-11T08:57:57Z",
        "headline": "fp-convert 0.5.0",
        "content": {
          "excerpt_text": "A tool to convert Freeplane mindmaps to print-quality PDF documents.",
          "lang": "en"
        },
        "provenance": {
          "fetched_at": "2026-03-11T08:59:15Z",
          "evidence_urls": [
            "https://pypi.org/project/fp-convert/0.5.0/"
          ],
          "content_hash": "sha256:577d57298f4db173ebb926d2833de46d2a930f576bcd7b8ebb5f6135db768ec7"
        },
        "signals": {
          "release": {
            "version": "0.5.0",
            "provenance": {
              "method": "title_regex",
              "authority": "PyPI Recent Updates",
              "authority_url": "https://pypi.org",
              "evidence_url": "https://pypi.org/project/fp-convert/0.5.0/"
            }
          }
        }
      },
      {
        "source": "pypi_recent_updates",
        "id": "a095c39dbfc65922bae3b78f401f3c39",
        "url": "https://pypi.org/project/reyserver/1.1.112/",
        "published_at": "2026-03-11T08:57:55Z",
        "updated_at": "2026-03-11T08:57:55Z",
        "headline": "reyserver 1.1.112",
        "content": {
          "excerpt_text": "Backend server method set.",
          "lang": "en"
        },
        "provenance": {
          "fetched_at": "2026-03-11T08:59:15Z",
          "evidence_urls": [
            "https://pypi.org/project/reyserver/1.1.112/"
          ],
          "content_hash": "sha256:281dbb242a2068260d33de01fd58de7a764a5c328ca02b1e6c68c66315ce320c"
        },
        "signals": {
          "release": {
            "version": "1.1.112",
            "provenance": {
              "method": "title_regex",
              "authority": "PyPI Recent Updates",
              "authority_url": "https://pypi.org",
              "evidence_url": "https://pypi.org/project/reyserver/1.1.112/"
            }
          }
        }
      },
      {
        "source": "pypi_recent_updates",
        "id": "43003bd32d3ead14da27bcbd4364c7cb",
        "url": "https://pypi.org/project/markdown-flow/0.2.55/",
        "published_at": "2026-03-11T08:57:54Z",
        "updated_at": "2026-03-11T08:57:54Z",
        "headline": "markdown-flow 0.2.55",
        "content": {
          "excerpt_text": "An agent library designed to parse and process MarkdownFlow documents",
          "lang": "en"
        },
        "provenance": {
          "fetched_at": "2026-03-11T08:59:15Z",
          "evidence_urls": [
            "https://pypi.org/project/markdown-flow/0.2.55/"
          ],
          "content_hash": "sha256:5615761f2083839a3f3ba33ff0be0df9c3c53ede722c2a5158b43a36bb64962c"
        },
        "signals": {
          "release": {
            "version": "0.2.55",
            "provenance": {
              "method": "title_regex",
              "authority": "PyPI Recent Updates",
              "authority_url": "https://pypi.org",
              "evidence_url": "https://pypi.org/project/markdown-flow/0.2.55/"
            }
          }
        }
      },
      {
        "source": "pypi_recent_updates",
        "id": "14d0642925f921a83eb70a3fd84ab943",
        "url": "https://pypi.org/project/parseltongue-dsl/0.4.0/",
        "published_at": "2026-03-11T08:57:07Z",
        "updated_at": "2026-03-11T08:57:07Z",
        "headline": "parseltongue-dsl 0.4.0",
        "content": {
          "excerpt_text": "Parseltongue: a DSL for systems which refuse to speak falsehood",
          "lang": "en"
        },
        "provenance": {
          "fetched_at": "2026-03-11T08:59:15Z",
          "evidence_urls": [
            "https://pypi.org/project/parseltongue-dsl/0.4.0/"
          ],
          "content_hash": "sha256:901b34a236834bb57c0b28f83ca833dc2affb925bc6afdf25ff37d7818b9329d"
        },
        "signals": {
          "release": {
            "version": "0.4.0",
            "provenance": {
              "method": "title_regex",
              "authority": "PyPI Recent Updates",
              "authority_url": "https://pypi.org",
              "evidence_url": "https://pypi.org/project/parseltongue-dsl/0.4.0/"
            }
          }
        }
      },
      {
        "source": "pypi_recent_updates",
        "id": "2b0c6b99f66608970635fc845621d952",
        "url": "https://pypi.org/project/airena-sdk/0.10.0/",
        "published_at": "2026-03-11T08:57:04Z",
        "updated_at": "2026-03-11T08:57:04Z",
        "headline": "airena-sdk 0.10.0",
        "content": {
          "excerpt_text": "Thin Python SDK for AiRENA bot protocol (openra.v1)",
          "lang": "en"
        },
        "provenance": {
          "fetched_at": "2026-03-11T08:59:15Z",
          "evidence_urls": [
            "https://pypi.org/project/airena-sdk/0.10.0/"
          ],
          "content_hash": "sha256:05b4aff5047d2d0f6cf3bc81b0c8370b2e7af5ddd583eadfcec4f6432be4858d"
        },
        "signals": {
          "release": {
            "version": "0.10.0",
            "provenance": {
              "method": "title_regex",
              "authority": "PyPI Recent Updates",
              "authority_url": "https://pypi.org",
              "evidence_url": "https://pypi.org/project/airena-sdk/0.10.0/"
            }
          }
        }
      },
      {
        "source": "pypi_recent_updates",
        "id": "219327d8cd22abc7ed48ff24d4c16f27",
        "url": "https://pypi.org/project/revit-mcp/1.0.1/",
        "published_at": "2026-03-11T08:56:49Z",
        "updated_at": "2026-03-11T08:56:49Z",
        "headline": "revit-mcp 1.0.1",
        "content": {
          "excerpt_text": "revit integration through the Model Context Protocol",
          "lang": "en"
        },
        "provenance": {
          "fetched_at": "2026-03-11T08:59:15Z",
          "evidence_urls": [
            "https://pypi.org/project/revit-mcp/1.0.1/"
          ],
          "content_hash": "sha256:5996e2efc7559a2b32d44c8fd5cff30326de11365b206819dbee20622a6b0145"
        },
        "signals": {
          "release": {
            "version": "1.0.1",
            "provenance": {
              "method": "title_regex",
              "authority": "PyPI Recent Updates",
              "authority_url": "https://pypi.org",
              "evidence_url": "https://pypi.org/project/revit-mcp/1.0.1/"
            }
          }
        }
      },
      {
        "source": "pypi_recent_updates",
        "id": "b519f2154006622990f7b63365c0962d",
        "url": "https://pypi.org/project/puda-drivers/0.0.37/",
        "published_at": "2026-03-11T08:56:38Z",
        "updated_at": "2026-03-11T08:56:38Z",
        "headline": "puda-drivers 0.0.37",
        "content": {
          "excerpt_text": "Hardware drivers for the PUDA platform.",
          "lang": "en"
        },
        "provenance": {
          "fetched_at": "2026-03-11T08:59:15Z",
          "evidence_urls": [
            "https://pypi.org/project/puda-drivers/0.0.37/"
          ],
          "content_hash": "sha256:0716b4261f7fc9a1417114c3cc4e514e994379f0d9aa50e3fa485c7dc82207d1"
        },
        "signals": {
          "release": {
            "version": "0.0.37",
            "provenance": {
              "method": "title_regex",
              "authority": "PyPI Recent Updates",
              "authority_url": "https://pypi.org",
              "evidence_url": "https://pypi.org/project/puda-drivers/0.0.37/"
            }
          }
        }
      },
      {
        "source": "pypi_recent_updates",
        "id": "95f2873a471fd4f3d3f29f7fd1166872",
        "url": "https://pypi.org/project/openreward/0.1.51/",
        "published_at": "2026-03-11T08:56:34Z",
        "updated_at": "2026-03-11T08:56:34Z",
        "headline": "openreward 0.1.51",
        "content": {
          "excerpt_text": "Python SDK for OpenrReward tracing and logging",
          "lang": "en"
        },
        "provenance": {
          "fetched_at": "2026-03-11T08:59:15Z",
          "evidence_urls": [
            "https://pypi.org/project/openreward/0.1.51/"
          ],
          "content_hash": "sha256:bc931dfdc079e5d4fa2465226254bee1e8fbc66fae49b8b3a9fa1f4235779579"
        },
        "signals": {
          "release": {
            "version": "0.1.51",
            "provenance": {
              "method": "title_regex",
              "authority": "PyPI Recent Updates",
              "authority_url": "https://pypi.org",
              "evidence_url": "https://pypi.org/project/openreward/0.1.51/"
            }
          }
        }
      },
      {
        "source": "pypi_recent_updates",
        "id": "7fad4b458ed0e7b9971af7627a2a8d57",
        "url": "https://pypi.org/project/autolife-planning/0.1.4/",
        "published_at": "2026-03-11T08:56:31Z",
        "updated_at": "2026-03-11T08:56:31Z",
        "headline": "autolife-planning 0.1.4",
        "content": {
          "excerpt_text": "Autolife planning module",
          "lang": "en"
        },
        "provenance": {
          "fetched_at": "2026-03-11T08:59:15Z",
          "evidence_urls": [
            "https://pypi.org/project/autolife-planning/0.1.4/"
          ],
          "content_hash": "sha256:d63f4d9dbeeb8246b4ce2b62ab1dbadf84ec59fa26b12e176dddd45352928788"
        },
        "signals": {
          "release": {
            "version": "0.1.4",
            "provenance": {
              "method": "title_regex",
              "authority": "PyPI Recent Updates",
              "authority_url": "https://pypi.org",
              "evidence_url": "https://pypi.org/project/autolife-planning/0.1.4/"
            }
          }
        }
      },
      {
        "source": "pypi_recent_updates",
        "id": "22a582b8f5e63388dd99af5e6942532d",
        "url": "https://pypi.org/project/autolife-vamp/0.6.4/",
        "published_at": "2026-03-11T08:56:10Z",
        "updated_at": "2026-03-11T08:56:10Z",
        "headline": "autolife-vamp 0.6.4",
        "content": {
          "excerpt_text": "Vector-Accelerated Motion Planner",
          "lang": "en"
        },
        "provenance": {
          "fetched_at": "2026-03-11T08:59:15Z",
          "evidence_urls": [
            "https://pypi.org/project/autolife-vamp/0.6.4/"
          ],
          "content_hash": "sha256:dc6fede32b6bf785a27294ae15a6fb750b24ca6188aa82a6868768b71d156fe6"
        },
        "signals": {
          "release": {
            "version": "0.6.4",
            "provenance": {
              "method": "title_regex",
              "authority": "PyPI Recent Updates",
              "authority_url": "https://pypi.org",
              "evidence_url": "https://pypi.org/project/autolife-vamp/0.6.4/"
            }
          }
        }
      },
      {
        "source": "pypi_recent_updates",
        "id": "4c5f1478e59cfd4655ee8787806f8425",
        "url": "https://pypi.org/project/passagemath-fricas/10.8.2/",
        "published_at": "2026-03-11T08:56:04Z",
        "updated_at": "2026-03-11T08:56:04Z",
        "headline": "passagemath-fricas 10.8.2",
        "content": {
          "excerpt_text": "passagemath: Symbolic computation with the general purpose computer algebra system FriCAS",
          "lang": "en"
        },
        "provenance": {
          "fetched_at": "2026-03-11T08:59:15Z",
          "evidence_urls": [
            "https://pypi.org/project/passagemath-fricas/10.8.2/"
          ],
          "content_hash": "sha256:9c813070935737eb8905eda6923a78ee3fcc877d6278ed879b04f1da5769f3a1"
        },
        "signals": {
          "release": {
            "version": "10.8.2",
            "provenance": {
              "method": "title_regex",
              "authority": "PyPI Recent Updates",
              "authority_url": "https://pypi.org",
              "evidence_url": "https://pypi.org/project/passagemath-fricas/10.8.2/"
            }
          }
        }
      },
      {
        "source": "pypi_recent_updates",
        "id": "26a4628b8123cae18d3b2733004435bf",
        "url": "https://pypi.org/project/specatwrap6/0.2.0/",
        "published_at": "2026-03-11T08:55:53Z",
        "updated_at": "2026-03-11T08:55:53Z",
        "headline": "specatwrap6 0.2.0",
        "content": {
          "excerpt_text": "A simple wrapper",
          "lang": "en"
        },
        "provenance": {
          "fetched_at": "2026-03-11T08:59:15Z",
          "evidence_urls": [
            "https://pypi.org/project/specatwrap6/0.2.0/"
          ],
          "content_hash": "sha256:9abe73af921ef8bdfcc533fcbe8e676707a4e1ea8d0d8c63e2cb93da88b73e62"
        },
        "signals": {
          "release": {
            "version": "0.2.0",
            "provenance": {
              "method": "title_regex",
              "authority": "PyPI Recent Updates",
              "authority_url": "https://pypi.org",
              "evidence_url": "https://pypi.org/project/specatwrap6/0.2.0/"
            }
          }
        }
      },
      {
        "source": "pypi_recent_updates",
        "id": "2136c0078b4dd65b7e505af40a4df3c2",
        "url": "https://pypi.org/project/my-pyrogram/2.0.115/",
        "published_at": "2026-03-11T08:55:46Z",
        "updated_at": "2026-03-11T08:55:46Z",
        "headline": "My-Pyrogram 2.0.115",
        "content": {
          "excerpt_text": "Elegant, modern and asynchronous Telegram MTProto API framework in Python for users and bots",
          "lang": "en"
        },
        "provenance": {
          "fetched_at": "2026-03-11T08:59:15Z",
          "evidence_urls": [
            "https://pypi.org/project/my-pyrogram/2.0.115/"
          ],
          "content_hash": "sha256:4af658c0530b1fd0320d809f9e145e50dcf895ab4e528e634f30011c56475cce"
        },
        "signals": {
          "release": {
            "version": "2.0.115",
            "provenance": {
              "method": "title_regex",
              "authority": "PyPI Recent Updates",
              "authority_url": "https://pypi.org",
              "evidence_url": "https://pypi.org/project/my-pyrogram/2.0.115/"
            }
          }
        }
      },
      {
        "source": "pypi_recent_updates",
        "id": "4f833892cb4356e7d657d879caf4f502",
        "url": "https://pypi.org/project/nvfuser-cu128/0.2.36.dev20260311/",
        "published_at": "2026-03-11T08:55:28Z",
        "updated_at": "2026-03-11T08:55:28Z",
        "headline": "nvfuser-cu128 0.2.36.dev20260311",
        "content": {
          "excerpt_text": "A Fusion Code Generator for NVIDIA GPUs (commonly known as 'nvFuser')",
          "lang": "en"
        },
        "provenance": {
          "fetched_at": "2026-03-11T08:59:15Z",
          "evidence_urls": [
            "https://pypi.org/project/nvfuser-cu128/0.2.36.dev20260311/"
          ],
          "content_hash": "sha256:07f8b939811f4e7582c4b0143b2dd27507e15b846706a04d57966dd7ebe3c0c3"
        },
        "signals": {
          "release": {
            "version": "0.2.36.dev20260311",
            "prerelease": true,
            "provenance": {
              "method": "title_regex",
              "authority": "PyPI Recent Updates",
              "authority_url": "https://pypi.org",
              "evidence_url": "https://pypi.org/project/nvfuser-cu128/0.2.36.dev20260311/"
            }
          }
        }
      },
      {
        "source": "pypi_recent_updates",
        "id": "7069f5fd2b31507896bc388aab41ac10",
        "url": "https://pypi.org/project/ion-csp/2.3.0/",
        "published_at": "2026-03-11T08:55:23Z",
        "updated_at": "2026-03-11T08:55:23Z",
        "headline": "ion-CSP 2.3.0",
        "content": {
          "excerpt_text": "Crystal Structure Design Software Based on Molecular/Ionic Configuration.",
          "lang": "en"
        },
        "provenance": {
          "fetched_at": "2026-03-11T08:59:15Z",
          "evidence_urls": [
            "https://pypi.org/project/ion-csp/2.3.0/"
          ],
          "content_hash": "sha256:d464c436ed4f9f0bec7546f5c79f0cad32ab324e4dba0ba7c21d86ed080f1a60"
        },
        "signals": {
          "release": {
            "version": "2.3.0",
            "provenance": {
              "method": "title_regex",
              "authority": "PyPI Recent Updates",
              "authority_url": "https://pypi.org",
              "evidence_url": "https://pypi.org/project/ion-csp/2.3.0/"
            }
          }
        }
      },
      {
        "source": "pypi_recent_updates",
        "id": "11949b22404b874f714437a25ad6727c",
        "url": "https://pypi.org/project/mnpbem-simulation/0.1.6/",
        "published_at": "2026-03-11T08:55:20Z",
        "updated_at": "2026-03-11T08:55:20Z",
        "headline": "mnpbem-simulation 0.1.6",
        "content": {
          "excerpt_text": "High-level simulation orchestration helpers for MNPBEM workflows.",
          "lang": "en"
        },
        "provenance": {
          "fetched_at": "2026-03-11T08:59:15Z",
          "evidence_urls": [
            "https://pypi.org/project/mnpbem-simulation/0.1.6/"
          ],
          "content_hash": "sha256:8873395001671619cf6590c0978ee487a905e65fe5e81e834a886156f73b58d0"
        },
        "signals": {
          "release": {
            "version": "0.1.6",
            "provenance": {
              "method": "title_regex",
              "authority": "PyPI Recent Updates",
              "authority_url": "https://pypi.org",
              "evidence_url": "https://pypi.org/project/mnpbem-simulation/0.1.6/"
            }
          }
        }
      },
      {
        "source": "pypi_recent_updates",
        "id": "49bf1f134eed6bdbc4c5215d69bfaa71",
        "url": "https://pypi.org/project/dags/0.5.0/",
        "published_at": "2026-03-11T08:55:18Z",
        "updated_at": "2026-03-11T08:55:18Z",
        "headline": "dags 0.5.0",
        "content": {
          "excerpt_text": "Tools to create executable dags from interdependent functions.",
          "lang": "en"
        },
        "provenance": {
          "fetched_at": "2026-03-11T08:59:15Z",
          "evidence_urls": [
            "https://pypi.org/project/dags/0.5.0/"
          ],
          "content_hash": "sha256:f6c70eea8b51e61d96e48836ea21f7a34bdaf157fe8c56175bde4e682cadc079"
        },
        "signals": {
          "release": {
            "version": "0.5.0",
            "provenance": {
              "method": "title_regex",
              "authority": "PyPI Recent Updates",
              "authority_url": "https://pypi.org",
              "evidence_url": "https://pypi.org/project/dags/0.5.0/"
            }
          }
        }
      },
      {
        "source": "pypi_recent_updates",
        "id": "bc86efc5e18a80a7c35049070ce6c3cc",
        "url": "https://pypi.org/project/mnpbem-particles/0.1.5/",
        "published_at": "2026-03-11T08:55:18Z",
        "updated_at": "2026-03-11T08:55:18Z",
        "headline": "mnpbem-particles 0.1.5",
        "content": {
          "excerpt_text": "Particle abstractions for compositional nanostructure modeling.",
          "lang": "en"
        },
        "provenance": {
          "fetched_at": "2026-03-11T08:59:15Z",
          "evidence_urls": [
            "https://pypi.org/project/mnpbem-particles/0.1.5/"
          ],
          "content_hash": "sha256:41661f05fb70a9f10519f25a5c01c29d6f9e83b4ff6db520667be0ea0dccec99"
        },
        "signals": {
          "release": {
            "version": "0.1.5",
            "provenance": {
              "method": "title_regex",
              "authority": "PyPI Recent Updates",
              "authority_url": "https://pypi.org",
              "evidence_url": "https://pypi.org/project/mnpbem-particles/0.1.5/"
            }
          }
        }
      },
      {
        "source": "pypi_recent_updates",
        "id": "5cc2d25fac4f87c5a6f9dca5d3e3dc55",
        "url": "https://pypi.org/project/mnpbem-misc/0.1.6/",
        "published_at": "2026-03-11T08:55:16Z",
        "updated_at": "2026-03-11T08:55:16Z",
        "headline": "mnpbem-misc 0.1.6",
        "content": {
          "excerpt_text": "Shared numerical and vector algebra toolkit for MNPBEM-Python.",
          "lang": "en"
        },
        "provenance": {
          "fetched_at": "2026-03-11T08:59:15Z",
          "evidence_urls": [
            "https://pypi.org/project/mnpbem-misc/0.1.6/"
          ],
          "content_hash": "sha256:1470cc5f39b0bf4c03fde09217624976395a9f7c2c995964b62acfdb38070adb"
        },
        "signals": {
          "release": {
            "version": "0.1.6",
            "provenance": {
              "method": "title_regex",
              "authority": "PyPI Recent Updates",
              "authority_url": "https://pypi.org",
              "evidence_url": "https://pypi.org/project/mnpbem-misc/0.1.6/"
            }
          }
        }
      },
      {
        "source": "pypi_recent_updates",
        "id": "1fae829203b7ac1cfa7412e04f7a3665",
        "url": "https://pypi.org/project/revit-mcp/1.0.0/",
        "published_at": "2026-03-11T08:55:15Z",
        "updated_at": "2026-03-11T08:55:15Z",
        "headline": "revit-mcp 1.0.0",
        "content": {
          "excerpt_text": "revit integration through the Model Context Protocol",
          "lang": "en"
        },
        "provenance": {
          "fetched_at": "2026-03-11T08:59:15Z",
          "evidence_urls": [
            "https://pypi.org/project/revit-mcp/1.0.0/"
          ],
          "content_hash": "sha256:351ee7b7664a2c6ae713ea104dc5da0b60cc40e8884b079202dabcf6684b6ea0"
        },
        "signals": {
          "release": {
            "version": "1.0.0",
            "provenance": {
              "method": "title_regex",
              "authority": "PyPI Recent Updates",
              "authority_url": "https://pypi.org",
              "evidence_url": "https://pypi.org/project/revit-mcp/1.0.0/"
            }
          }
        }
      },
      {
        "source": "pypi_recent_updates",
        "id": "7b07f28f0dbf09d3b5607434a5a570f7",
        "url": "https://pypi.org/project/mnpbem-mie/0.1.5/",
        "published_at": "2026-03-11T08:55:13Z",
        "updated_at": "2026-03-11T08:55:13Z",
        "headline": "mnpbem-mie 0.1.5",
        "content": {
          "excerpt_text": "Mie and Rayleigh scattering approximations for spherical particles.",
          "lang": "en"
        },
        "provenance": {
          "fetched_at": "2026-03-11T08:59:15Z",
          "evidence_urls": [
            "https://pypi.org/project/mnpbem-mie/0.1.5/"
          ],
          "content_hash": "sha256:fa8abac3dc95e6616b2abc5c57d363ab502ae5a7ca8f00591d61124a676c8830"
        },
        "signals": {
          "release": {
            "version": "0.1.5",
            "provenance": {
              "method": "title_regex",
              "authority": "PyPI Recent Updates",
              "authority_url": "https://pypi.org",
              "evidence_url": "https://pypi.org/project/mnpbem-mie/0.1.5/"
            }
          }
        }
      },
      {
        "source": "pypi_recent_updates",
        "id": "06c9b2aada37d1cc2aa3ee09bbbc3091",
        "url": "https://pypi.org/project/mnpbem-mex/0.1.5/",
        "published_at": "2026-03-11T08:55:10Z",
        "updated_at": "2026-03-11T08:55:10Z",
        "headline": "mnpbem-mex 0.1.5",
        "content": {
          "excerpt_text": "Acceleration-facing interfaces corresponding to MNPBEM mex integrations.",
          "lang": "en"
        },
        "provenance": {
          "fetched_at": "2026-03-11T08:59:15Z",
          "evidence_urls": [
            "https://pypi.org/project/mnpbem-mex/0.1.5/"
          ],
          "content_hash": "sha256:62c9e2578f23d920b2e8fa9e6725b75a51729cba5aa8022838796d295eeee6dd"
        },
        "signals": {
          "release": {
            "version": "0.1.5",
            "provenance": {
              "method": "title_regex",
              "authority": "PyPI Recent Updates",
              "authority_url": "https://pypi.org",
              "evidence_url": "https://pypi.org/project/mnpbem-mex/0.1.5/"
            }
          }
        }
      },
      {
        "source": "pypi_recent_updates",
        "id": "4b04a4edbe93ded69753caceb114e145",
        "url": "https://pypi.org/project/mnpbem-mesh2d/0.1.5/",
        "published_at": "2026-03-11T08:55:08Z",
        "updated_at": "2026-03-11T08:55:08Z",
        "headline": "mnpbem-mesh2d 0.1.5",
        "content": {
          "excerpt_text": "2D mesh geometry primitives for computational plasmonics meshes.",
          "lang": "en"
        },
        "provenance": {
          "fetched_at": "2026-03-11T08:59:15Z",
          "evidence_urls": [
            "https://pypi.org/project/mnpbem-mesh2d/0.1.5/"
          ],
          "content_hash": "sha256:61054c4cc3c96653c1b238359324f55d638cbf6149a0a9345fc70b8192212438"
        },
        "signals": {
          "release": {
            "version": "0.1.5",
            "provenance": {
              "method": "title_regex",
              "authority": "PyPI Recent Updates",
              "authority_url": "https://pypi.org",
              "evidence_url": "https://pypi.org/project/mnpbem-mesh2d/0.1.5/"
            }
          }
        }
      },
      {
        "source": "pypi_recent_updates",
        "id": "17fff7126c4e43b53908c8f02e73137c",
        "url": "https://pypi.org/project/nvfuser-cu126/0.2.36.dev20260311/",
        "published_at": "2026-03-11T08:55:08Z",
        "updated_at": "2026-03-11T08:55:08Z",
        "headline": "nvfuser-cu126 0.2.36.dev20260311",
        "content": {
          "excerpt_text": "A Fusion Code Generator for NVIDIA GPUs (commonly known as 'nvFuser')",
          "lang": "en"
        },
        "provenance": {
          "fetched_at": "2026-03-11T08:59:15Z",
          "evidence_urls": [
            "https://pypi.org/project/nvfuser-cu126/0.2.36.dev20260311/"
          ],
          "content_hash": "sha256:cde9a3c7685fc29e677a47efe0b5cdff5e8d2dfec0302d2f49d0c16e800efeac"
        },
        "signals": {
          "release": {
            "version": "0.2.36.dev20260311",
            "prerelease": true,
            "provenance": {
              "method": "title_regex",
              "authority": "PyPI Recent Updates",
              "authority_url": "https://pypi.org",
              "evidence_url": "https://pypi.org/project/nvfuser-cu126/0.2.36.dev20260311/"
            }
          }
        }
      },
      {
        "source": "pypi_recent_updates",
        "id": "6548400a638f3787ccaf60e1491a935b",
        "url": "https://pypi.org/project/mnpbem-material/0.1.9/",
        "published_at": "2026-03-11T08:55:06Z",
        "updated_at": "2026-03-11T08:55:06Z",
        "headline": "mnpbem-material 0.1.9",
        "content": {
          "excerpt_text": "Material dielectric models for plasmonic electrodynamics in MNPBEM-Python.",
          "lang": "en"
        },
        "provenance": {
          "fetched_at": "2026-03-11T08:59:15Z",
          "evidence_urls": [
            "https://pypi.org/project/mnpbem-material/0.1.9/"
          ],
          "content_hash": "sha256:4408d40b4d2c7599792d4750a8d9259511954ef006b1c5b178c39e134996f2fc"
        },
        "signals": {
          "release": {
            "version": "0.1.9",
            "provenance": {
              "method": "title_regex",
              "authority": "PyPI Recent Updates",
              "authority_url": "https://pypi.org",
              "evidence_url": "https://pypi.org/project/mnpbem-material/0.1.9/"
            }
          }
        }
      },
      {
        "source": "pypi_recent_updates",
        "id": "49230f31e4ae8beff3af1d69b071daa3",
        "url": "https://pypi.org/project/mnpbem-help/0.1.5/",
        "published_at": "2026-03-11T08:55:04Z",
        "updated_at": "2026-03-11T08:55:04Z",
        "headline": "mnpbem-help 0.1.5",
        "content": {
          "excerpt_text": "Reference and educational helper interfaces for MNPBEM Python users.",
          "lang": "en"
        },
        "provenance": {
          "fetched_at": "2026-03-11T08:59:15Z",
          "evidence_urls": [
            "https://pypi.org/project/mnpbem-help/0.1.5/"
          ],
          "content_hash": "sha256:d94dd699a79bedf8bdb45aa9de1277fcbf49bb3c3f5203218b7699c8abab630b"
        },
        "signals": {
          "release": {
            "version": "0.1.5",
            "provenance": {
              "method": "title_regex",
              "authority": "PyPI Recent Updates",
              "authority_url": "https://pypi.org",
              "evidence_url": "https://pypi.org/project/mnpbem-help/0.1.5/"
            }
          }
        }
      },
      {
        "source": "pypi_recent_updates",
        "id": "3c64c6b929571f7d96157c09aadba93d",
        "url": "https://pypi.org/project/mnpbem-greenfun/0.1.5/",
        "published_at": "2026-03-11T08:55:01Z",
        "updated_at": "2026-03-11T08:55:01Z",
        "headline": "mnpbem-greenfun 0.1.5",
        "content": {
          "excerpt_text": "Green-function utilities and kernels for electrodynamics simulations.",
          "lang": "en"
        },
        "provenance": {
          "fetched_at": "2026-03-11T08:59:15Z",
          "evidence_urls": [
            "https://pypi.org/project/mnpbem-greenfun/0.1.5/"
          ],
          "content_hash": "sha256:b72806324275894601ea9f5a07a1940c2ab0146c300e48d1257dc10a2294b475"
        },
        "signals": {
          "release": {
            "version": "0.1.5",
            "provenance": {
              "method": "title_regex",
              "authority": "PyPI Recent Updates",
              "authority_url": "https://pypi.org",
              "evidence_url": "https://pypi.org/project/mnpbem-greenfun/0.1.5/"
            }
          }
        }
      },
      {
        "source": "pypi_recent_updates",
        "id": "239c726900a8061f0eac7fa542534f11",
        "url": "https://pypi.org/project/gllm-pipeline-binary/0.4.39.post2/",
        "published_at": "2026-03-11T08:55:00Z",
        "updated_at": "2026-03-11T08:55:00Z",
        "headline": "gllm-pipeline-binary 0.4.39.post2",
        "content": {
          "excerpt_text": "A library containing components related to Gen AI applications pipeline orchestration.",
          "lang": "en"
        },
        "provenance": {
          "fetched_at": "2026-03-11T08:59:15Z",
          "evidence_urls": [
            "https://pypi.org/project/gllm-pipeline-binary/0.4.39.post2/"
          ],
          "content_hash": "sha256:b5ca09fc32088d68ea1d78a6e88574652e9839f0ae7a78e931e3a9fcb6495e80"
        },
        "signals": {
          "release": {
            "version": "0.4.39",
            "provenance": {
              "method": "title_regex",
              "authority": "PyPI Recent Updates",
              "authority_url": "https://pypi.org",
              "evidence_url": "https://pypi.org/project/gllm-pipeline-binary/0.4.39.post2/"
            }
          }
        }
      },
      {
        "source": "pypi_recent_updates",
        "id": "83e58bf8eee7ac41486c9119ff359664",
        "url": "https://pypi.org/project/mnpbem-demo-mnpbem/0.1.6/",
        "published_at": "2026-03-11T08:54:59Z",
        "updated_at": "2026-03-11T08:54:59Z",
        "headline": "mnpbem-demo-mnpbem 0.1.6",
        "content": {
          "excerpt_text": "Extended demonstration layer corresponding to the MATLAB Demo MNPBEM folder.",
          "lang": "en"
        },
        "provenance": {
          "fetched_at": "2026-03-11T08:59:15Z",
          "evidence_urls": [
            "https://pypi.org/project/mnpbem-demo-mnpbem/0.1.6/"
          ],
          "content_hash": "sha256:5d6a93d5113ac5e289d7924bf1d84c25950f940613dd5d9643a013e0b15db630"
        },
        "signals": {
          "release": {
            "version": "0.1.6",
            "provenance": {
              "method": "title_regex",
              "authority": "PyPI Recent Updates",
              "authority_url": "https://pypi.org",
              "evidence_url": "https://pypi.org/project/mnpbem-demo-mnpbem/0.1.6/"
            }
          }
        }
      },
      {
        "source": "pypi_recent_updates",
        "id": "6c3302599b40d269fb720708ed72d1d5",
        "url": "https://pypi.org/project/mnpbem-demo/0.1.5/",
        "published_at": "2026-03-11T08:54:56Z",
        "updated_at": "2026-03-11T08:54:56Z",
        "headline": "mnpbem-demo 0.1.5",
        "content": {
          "excerpt_text": "Reproducible demonstration scaffolding for MNPBEM Python modules.",
          "lang": "en"
        },
        "provenance": {
          "fetched_at": "2026-03-11T08:59:15Z",
          "evidence_urls": [
            "https://pypi.org/project/mnpbem-demo/0.1.5/"
          ],
          "content_hash": "sha256:9567a9d7bf2efb71757c42594278f0b1e6f05d8215f60fff59797f442d42680b"
        },
        "signals": {
          "release": {
            "version": "0.1.5",
            "provenance": {
              "method": "title_regex",
              "authority": "PyPI Recent Updates",
              "authority_url": "https://pypi.org",
              "evidence_url": "https://pypi.org/project/mnpbem-demo/0.1.5/"
            }
          }
        }
      },
      {
        "source": "pypi_recent_updates",
        "id": "dc35325c96b2305dc5c0ad91c23e6459",
        "url": "https://pypi.org/project/mnpbem-bem/0.1.5/",
        "published_at": "2026-03-11T08:54:54Z",
        "updated_at": "2026-03-11T08:54:54Z",
        "headline": "mnpbem-bem 0.1.5",
        "content": {
          "excerpt_text": "Core BEM namespace package and solver-facing compatibility helpers.",
          "lang": "en"
        },
        "provenance": {
          "fetched_at": "2026-03-11T08:59:15Z",
          "evidence_urls": [
            "https://pypi.org/project/mnpbem-bem/0.1.5/"
          ],
          "content_hash": "sha256:d6154edc7e3d08dcbb4f7e0cf1b3408f9af969140a714cfe47b78a64d1e843e2"
        },
        "signals": {
          "release": {
            "version": "0.1.5",
            "provenance": {
              "method": "title_regex",
              "authority": "PyPI Recent Updates",
              "authority_url": "https://pypi.org",
              "evidence_url": "https://pypi.org/project/mnpbem-bem/0.1.5/"
            }
          }
        }
      }
    ],
    "updated": [],
    "removed": []
  },
  "counts": {
    "items": 40,
    "updated": 0,
    "removed": 0
  },
  "integrity_reset": false,
  "archive_url": "/archive/pypi_recent_updates/2026/03/11/20260311T085915Z_93f490e5154e0e32.json",
  "sources_url": "/diff/sources.json"
}
