{
  "schema_version": "1.2.0",
  "generated_at": "2026-02-06T19:28:39Z",
  "source_id": "debian_security",
  "hash": "sha256:49a52f18fb4c8bbcdfbc86fc875d762572eaaa7e4751e39fcdde33c3ec2f4ffc",
  "prev_hash": "sha256:0000000000000000000000000000000000000000000000000000000000000000",
  "cursor": "sha256:58515c9f62f793538b16125a84dafb95630d0d66c6606bff5382ead59ef59501",
  "prev_cursor": "sha256:0000000000000000000000000000000000000000000000000000000000000000",
  "changed": true,
  "ttl_sec": 3600,
  "sources_included": [
    "debian_security"
  ],
  "batch_narrative": "debian_security: 30 changes (30 new).",
  "buckets": {
    "new": [
      {
        "source": "debian_security",
        "id": "https://lists.debian.org/debian-security-announce/2026/msg00031.html",
        "url": "https://lists.debian.org/debian-security-announce/2026/msg00031.html",
        "published_at": "2026-02-06T19:28:39Z",
        "updated_at": "2026-02-05T00:00:00Z",
        "headline": "DSA-6122-1 chromium - security update",
        "content": {
          "excerpt_text": "https://security-tracker.debian.org/tracker/DSA-6122-1",
          "lang": "en"
        },
        "provenance": {
          "fetched_at": "2026-02-06T19:28:39Z",
          "evidence_urls": [
            "https://lists.debian.org/debian-security-announce/2026/msg00031.html"
          ],
          "content_hash": "sha256:ade8ae30ecb281164090054a109eaf5898e038392f79f63f588800d9d2392b0c"
        },
        "source_payload": {
          "html": "<a href=\"https://security-tracker.debian.org/tracker/DSA-6122-1\">https://security-tracker.debian.org/tracker/DSA-6122-1</a>",
          "link": "https://lists.debian.org/debian-security-announce/2026/msg00031.html",
          "published": "",
          "updated": "2026-02-05",
          "updated_parsed": [
            2026,
            2,
            5,
            0,
            0,
            0,
            3,
            36,
            0
          ],
          "guid": "https://lists.debian.org/debian-security-announce/2026/msg00031.html"
        }
      },
      {
        "source": "debian_security",
        "id": "https://lists.debian.org/debian-security-announce/2026/msg00030.html",
        "url": "https://lists.debian.org/debian-security-announce/2026/msg00030.html",
        "published_at": "2026-02-06T19:28:39Z",
        "updated_at": "2026-02-05T00:00:00Z",
        "headline": "DSA-6121-1 tomcat11 - security update",
        "content": {
          "excerpt_text": "https://security-tracker.debian.org/tracker/DSA-6121-1",
          "lang": "en"
        },
        "provenance": {
          "fetched_at": "2026-02-06T19:28:39Z",
          "evidence_urls": [
            "https://lists.debian.org/debian-security-announce/2026/msg00030.html"
          ],
          "content_hash": "sha256:d0ed49fb9389db8412f54fd8837a1f31b27833a3951c9078304f848e7c62188e"
        },
        "source_payload": {
          "html": "<a href=\"https://security-tracker.debian.org/tracker/DSA-6121-1\">https://security-tracker.debian.org/tracker/DSA-6121-1</a>",
          "link": "https://lists.debian.org/debian-security-announce/2026/msg00030.html",
          "published": "",
          "updated": "2026-02-05",
          "updated_parsed": [
            2026,
            2,
            5,
            0,
            0,
            0,
            3,
            36,
            0
          ],
          "guid": "https://lists.debian.org/debian-security-announce/2026/msg00030.html"
        }
      },
      {
        "source": "debian_security",
        "id": "https://lists.debian.org/debian-security-announce/2026/msg00029.html",
        "url": "https://lists.debian.org/debian-security-announce/2026/msg00029.html",
        "published_at": "2026-02-06T19:28:39Z",
        "updated_at": "2026-02-05T00:00:00Z",
        "headline": "DSA-6120-1 tomcat10 - security update",
        "content": {
          "excerpt_text": "https://security-tracker.debian.org/tracker/DSA-6120-1",
          "lang": "en"
        },
        "provenance": {
          "fetched_at": "2026-02-06T19:28:39Z",
          "evidence_urls": [
            "https://lists.debian.org/debian-security-announce/2026/msg00029.html"
          ],
          "content_hash": "sha256:98ca8d28076408b294fb0595ac353a51a22154ca43abe70ef1106300abb84e82"
        },
        "source_payload": {
          "html": "<a href=\"https://security-tracker.debian.org/tracker/DSA-6120-1\">https://security-tracker.debian.org/tracker/DSA-6120-1</a>",
          "link": "https://lists.debian.org/debian-security-announce/2026/msg00029.html",
          "published": "",
          "updated": "2026-02-05",
          "updated_parsed": [
            2026,
            2,
            5,
            0,
            0,
            0,
            3,
            36,
            0
          ],
          "guid": "https://lists.debian.org/debian-security-announce/2026/msg00029.html"
        }
      },
      {
        "source": "debian_security",
        "id": "https://lists.debian.org/debian-security-announce/2026/msg00028.html",
        "url": "https://lists.debian.org/debian-security-announce/2026/msg00028.html",
        "published_at": "2026-02-06T19:28:39Z",
        "updated_at": "2026-02-05T00:00:00Z",
        "headline": "DSA-6119-1 openjdk-25 - security update",
        "content": {
          "excerpt_text": "https://security-tracker.debian.org/tracker/DSA-6119-1",
          "lang": "en"
        },
        "provenance": {
          "fetched_at": "2026-02-06T19:28:39Z",
          "evidence_urls": [
            "https://lists.debian.org/debian-security-announce/2026/msg00028.html"
          ],
          "content_hash": "sha256:dcb2eb9d1ec031176e646c2d31c1ced886825f33ca2d67903a1430d0a9fd4523"
        },
        "source_payload": {
          "html": "<a href=\"https://security-tracker.debian.org/tracker/DSA-6119-1\">https://security-tracker.debian.org/tracker/DSA-6119-1</a>",
          "link": "https://lists.debian.org/debian-security-announce/2026/msg00028.html",
          "published": "",
          "updated": "2026-02-05",
          "updated_parsed": [
            2026,
            2,
            5,
            0,
            0,
            0,
            3,
            36,
            0
          ],
          "guid": "https://lists.debian.org/debian-security-announce/2026/msg00028.html"
        }
      },
      {
        "source": "debian_security",
        "id": "https://lists.debian.org/debian-security-announce/2026/msg00027.html",
        "url": "https://lists.debian.org/debian-security-announce/2026/msg00027.html",
        "published_at": "2026-02-06T19:28:39Z",
        "updated_at": "2026-02-03T00:00:00Z",
        "headline": "DSA-6118-1 thunderbird - security update",
        "content": {
          "excerpt_text": "https://security-tracker.debian.org/tracker/DSA-6118-1",
          "lang": "en"
        },
        "provenance": {
          "fetched_at": "2026-02-06T19:28:39Z",
          "evidence_urls": [
            "https://lists.debian.org/debian-security-announce/2026/msg00027.html"
          ],
          "content_hash": "sha256:1ff00a11046f09654c6a2d5a5075eb52d7dd8720f2831058ee6cc596ad635d17"
        },
        "source_payload": {
          "html": "<a href=\"https://security-tracker.debian.org/tracker/DSA-6118-1\">https://security-tracker.debian.org/tracker/DSA-6118-1</a>",
          "link": "https://lists.debian.org/debian-security-announce/2026/msg00027.html",
          "published": "",
          "updated": "2026-02-03",
          "updated_parsed": [
            2026,
            2,
            3,
            0,
            0,
            0,
            1,
            34,
            0
          ],
          "guid": "https://lists.debian.org/debian-security-announce/2026/msg00027.html"
        }
      },
      {
        "source": "debian_security",
        "id": "https://lists.debian.org/debian-security-announce/2026/msg00026.html",
        "url": "https://lists.debian.org/debian-security-announce/2026/msg00026.html",
        "published_at": "2026-02-06T19:28:39Z",
        "updated_at": "2026-01-31T00:00:00Z",
        "headline": "DSA-6117-1 python-django - security update",
        "content": {
          "excerpt_text": "https://security-tracker.debian.org/tracker/DSA-6117-1",
          "lang": "en"
        },
        "provenance": {
          "fetched_at": "2026-02-06T19:28:39Z",
          "evidence_urls": [
            "https://lists.debian.org/debian-security-announce/2026/msg00026.html"
          ],
          "content_hash": "sha256:cbd5c8b843c020c421a1ea8d7339e044e185a6285cbabf7f6ad1e2315bf84e47"
        },
        "source_payload": {
          "html": "<a href=\"https://security-tracker.debian.org/tracker/DSA-6117-1\">https://security-tracker.debian.org/tracker/DSA-6117-1</a>",
          "link": "https://lists.debian.org/debian-security-announce/2026/msg00026.html",
          "published": "",
          "updated": "2026-01-31",
          "updated_parsed": [
            2026,
            1,
            31,
            0,
            0,
            0,
            5,
            31,
            0
          ],
          "guid": "https://lists.debian.org/debian-security-announce/2026/msg00026.html"
        }
      },
      {
        "source": "debian_security",
        "id": "https://lists.debian.org/debian-security-announce/2026/msg00025.html",
        "url": "https://lists.debian.org/debian-security-announce/2026/msg00025.html",
        "published_at": "2026-02-06T19:28:39Z",
        "updated_at": "2026-01-30T00:00:00Z",
        "headline": "DSA-6116-1 chromium - security update",
        "content": {
          "excerpt_text": "https://security-tracker.debian.org/tracker/DSA-6116-1",
          "lang": "en"
        },
        "provenance": {
          "fetched_at": "2026-02-06T19:28:39Z",
          "evidence_urls": [
            "https://lists.debian.org/debian-security-announce/2026/msg00025.html"
          ],
          "content_hash": "sha256:e1965888b666cf92589d9265a991cead3e679ff82f5b2a3248812dcb5a5c457e"
        },
        "source_payload": {
          "html": "<a href=\"https://security-tracker.debian.org/tracker/DSA-6116-1\">https://security-tracker.debian.org/tracker/DSA-6116-1</a>",
          "link": "https://lists.debian.org/debian-security-announce/2026/msg00025.html",
          "published": "",
          "updated": "2026-01-30",
          "updated_parsed": [
            2026,
            1,
            30,
            0,
            0,
            0,
            4,
            30,
            0
          ],
          "guid": "https://lists.debian.org/debian-security-announce/2026/msg00025.html"
        }
      },
      {
        "source": "debian_security",
        "id": "https://lists.debian.org/debian-security-announce/2026/msg00024.html",
        "url": "https://lists.debian.org/debian-security-announce/2026/msg00024.html",
        "published_at": "2026-02-06T19:28:39Z",
        "updated_at": "2026-01-29T00:00:00Z",
        "headline": "DSA-6115-1 gimp - security update",
        "content": {
          "excerpt_text": "https://security-tracker.debian.org/tracker/DSA-6115-1",
          "lang": "en"
        },
        "provenance": {
          "fetched_at": "2026-02-06T19:28:39Z",
          "evidence_urls": [
            "https://lists.debian.org/debian-security-announce/2026/msg00024.html"
          ],
          "content_hash": "sha256:1033fb2c23a2c3628261452a9d16db233454c269465ead3ea09cddc7dc5affce"
        },
        "source_payload": {
          "html": "<a href=\"https://security-tracker.debian.org/tracker/DSA-6115-1\">https://security-tracker.debian.org/tracker/DSA-6115-1</a>",
          "link": "https://lists.debian.org/debian-security-announce/2026/msg00024.html",
          "published": "",
          "updated": "2026-01-29",
          "updated_parsed": [
            2026,
            1,
            29,
            0,
            0,
            0,
            3,
            29,
            0
          ],
          "guid": "https://lists.debian.org/debian-security-announce/2026/msg00024.html"
        }
      },
      {
        "source": "debian_security",
        "id": "https://lists.debian.org/debian-security-announce/2026/msg00023.html",
        "url": "https://lists.debian.org/debian-security-announce/2026/msg00023.html",
        "published_at": "2026-02-06T19:28:39Z",
        "updated_at": "2026-01-28T00:00:00Z",
        "headline": "DSA-6114-1 pyasn1 - security update",
        "content": {
          "excerpt_text": "https://security-tracker.debian.org/tracker/DSA-6114-1",
          "lang": "en"
        },
        "provenance": {
          "fetched_at": "2026-02-06T19:28:39Z",
          "evidence_urls": [
            "https://lists.debian.org/debian-security-announce/2026/msg00023.html"
          ],
          "content_hash": "sha256:890108985c82e84ab81140f30801e168b352c5c62031e6428e3b20a9d4640cbc"
        },
        "source_payload": {
          "html": "<a href=\"https://security-tracker.debian.org/tracker/DSA-6114-1\">https://security-tracker.debian.org/tracker/DSA-6114-1</a>",
          "link": "https://lists.debian.org/debian-security-announce/2026/msg00023.html",
          "published": "",
          "updated": "2026-01-28",
          "updated_parsed": [
            2026,
            1,
            28,
            0,
            0,
            0,
            2,
            28,
            0
          ],
          "guid": "https://lists.debian.org/debian-security-announce/2026/msg00023.html"
        }
      },
      {
        "source": "debian_security",
        "id": "https://lists.debian.org/debian-security-announce/2026/msg00022.html",
        "url": "https://lists.debian.org/debian-security-announce/2026/msg00022.html",
        "published_at": "2026-02-06T19:28:39Z",
        "updated_at": "2026-01-27T00:00:00Z",
        "headline": "DSA-6113-1 openssl - security update",
        "content": {
          "excerpt_text": "https://security-tracker.debian.org/tracker/DSA-6113-1",
          "lang": "en"
        },
        "provenance": {
          "fetched_at": "2026-02-06T19:28:39Z",
          "evidence_urls": [
            "https://lists.debian.org/debian-security-announce/2026/msg00022.html"
          ],
          "content_hash": "sha256:c5c6f9b0a65bb02f75510e4885d052b20ac2f5163067caa487303444709b3c4e"
        },
        "source_payload": {
          "html": "<a href=\"https://security-tracker.debian.org/tracker/DSA-6113-1\">https://security-tracker.debian.org/tracker/DSA-6113-1</a>",
          "link": "https://lists.debian.org/debian-security-announce/2026/msg00022.html",
          "published": "",
          "updated": "2026-01-27",
          "updated_parsed": [
            2026,
            1,
            27,
            0,
            0,
            0,
            1,
            27,
            0
          ],
          "guid": "https://lists.debian.org/debian-security-announce/2026/msg00022.html"
        }
      },
      {
        "source": "debian_security",
        "id": "https://lists.debian.org/debian-security-announce/2026/msg00021.html",
        "url": "https://lists.debian.org/debian-security-announce/2026/msg00021.html",
        "published_at": "2026-02-06T19:28:39Z",
        "updated_at": "2026-01-27T00:00:00Z",
        "headline": "DSA-6112-1 openjdk-21 - security update",
        "content": {
          "excerpt_text": "https://security-tracker.debian.org/tracker/DSA-6112-1",
          "lang": "en"
        },
        "provenance": {
          "fetched_at": "2026-02-06T19:28:39Z",
          "evidence_urls": [
            "https://lists.debian.org/debian-security-announce/2026/msg00021.html"
          ],
          "content_hash": "sha256:7cfd636f63162357462b92436a59db15aabdf0b06d832b23bc6428c2ee666f26"
        },
        "source_payload": {
          "html": "<a href=\"https://security-tracker.debian.org/tracker/DSA-6112-1\">https://security-tracker.debian.org/tracker/DSA-6112-1</a>",
          "link": "https://lists.debian.org/debian-security-announce/2026/msg00021.html",
          "published": "",
          "updated": "2026-01-27",
          "updated_parsed": [
            2026,
            1,
            27,
            0,
            0,
            0,
            1,
            27,
            0
          ],
          "guid": "https://lists.debian.org/debian-security-announce/2026/msg00021.html"
        }
      },
      {
        "source": "debian_security",
        "id": "https://lists.debian.org/debian-security-announce/2026/msg00020.html",
        "url": "https://lists.debian.org/debian-security-announce/2026/msg00020.html",
        "published_at": "2026-02-06T19:28:39Z",
        "updated_at": "2026-01-26T00:00:00Z",
        "headline": "DSA-6111-1 imagemagick - security update",
        "content": {
          "excerpt_text": "https://security-tracker.debian.org/tracker/DSA-6111-1",
          "lang": "en"
        },
        "provenance": {
          "fetched_at": "2026-02-06T19:28:39Z",
          "evidence_urls": [
            "https://lists.debian.org/debian-security-announce/2026/msg00020.html"
          ],
          "content_hash": "sha256:87c5702216f0dc2ae7d6feacc20f1c7d58664adc0f76c49f6e14f38ace030f7d"
        },
        "source_payload": {
          "html": "<a href=\"https://security-tracker.debian.org/tracker/DSA-6111-1\">https://security-tracker.debian.org/tracker/DSA-6111-1</a>",
          "link": "https://lists.debian.org/debian-security-announce/2026/msg00020.html",
          "published": "",
          "updated": "2026-01-26",
          "updated_parsed": [
            2026,
            1,
            26,
            0,
            0,
            0,
            0,
            26,
            0
          ],
          "guid": "https://lists.debian.org/debian-security-announce/2026/msg00020.html"
        }
      },
      {
        "source": "debian_security",
        "id": "https://lists.debian.org/debian-security-announce/2026/msg00019.html",
        "url": "https://lists.debian.org/debian-security-announce/2026/msg00019.html",
        "published_at": "2026-02-06T19:28:39Z",
        "updated_at": "2026-01-25T00:00:00Z",
        "headline": "DSA-6110-1 openjdk-17 - security update",
        "content": {
          "excerpt_text": "https://security-tracker.debian.org/tracker/DSA-6110-1",
          "lang": "en"
        },
        "provenance": {
          "fetched_at": "2026-02-06T19:28:39Z",
          "evidence_urls": [
            "https://lists.debian.org/debian-security-announce/2026/msg00019.html"
          ],
          "content_hash": "sha256:126fa6e2f5a2a86545e1580fe0e52ad3fc545b434a65f345b78959f1464f9a7c"
        },
        "source_payload": {
          "html": "<a href=\"https://security-tracker.debian.org/tracker/DSA-6110-1\">https://security-tracker.debian.org/tracker/DSA-6110-1</a>",
          "link": "https://lists.debian.org/debian-security-announce/2026/msg00019.html",
          "published": "",
          "updated": "2026-01-25",
          "updated_parsed": [
            2026,
            1,
            25,
            0,
            0,
            0,
            6,
            25,
            0
          ],
          "guid": "https://lists.debian.org/debian-security-announce/2026/msg00019.html"
        }
      },
      {
        "source": "debian_security",
        "id": "https://lists.debian.org/debian-security-announce/2026/msg00018.html",
        "url": "https://lists.debian.org/debian-security-announce/2026/msg00018.html",
        "published_at": "2026-02-06T19:28:39Z",
        "updated_at": "2026-01-23T00:00:00Z",
        "headline": "DSA-6109-1 incus - security update",
        "content": {
          "excerpt_text": "https://security-tracker.debian.org/tracker/DSA-6109-1",
          "lang": "en"
        },
        "provenance": {
          "fetched_at": "2026-02-06T19:28:39Z",
          "evidence_urls": [
            "https://lists.debian.org/debian-security-announce/2026/msg00018.html"
          ],
          "content_hash": "sha256:4a19893ebe2c7c13bf32ceb3944158140dfeb8841e1421001bca09d687ac687c"
        },
        "source_payload": {
          "html": "<a href=\"https://security-tracker.debian.org/tracker/DSA-6109-1\">https://security-tracker.debian.org/tracker/DSA-6109-1</a>",
          "link": "https://lists.debian.org/debian-security-announce/2026/msg00018.html",
          "published": "",
          "updated": "2026-01-23",
          "updated_parsed": [
            2026,
            1,
            23,
            0,
            0,
            0,
            4,
            23,
            0
          ],
          "guid": "https://lists.debian.org/debian-security-announce/2026/msg00018.html"
        }
      },
      {
        "source": "debian_security",
        "id": "https://lists.debian.org/debian-security-announce/2026/msg00016.html",
        "url": "https://lists.debian.org/debian-security-announce/2026/msg00016.html",
        "published_at": "2026-02-06T19:28:39Z",
        "updated_at": "2026-01-22T00:00:00Z",
        "headline": "DSA-6102-2 python-urllib3 - regression update",
        "content": {
          "excerpt_text": "https://security-tracker.debian.org/tracker/DSA-6102-2",
          "lang": "en"
        },
        "provenance": {
          "fetched_at": "2026-02-06T19:28:39Z",
          "evidence_urls": [
            "https://lists.debian.org/debian-security-announce/2026/msg00016.html"
          ],
          "content_hash": "sha256:8a134f061a4e1939290a379f29bb49fdad07f676d96e19049375e5b8ee9c68d8"
        },
        "source_payload": {
          "html": "<a href=\"https://security-tracker.debian.org/tracker/DSA-6102-2\">https://security-tracker.debian.org/tracker/DSA-6102-2</a>",
          "link": "https://lists.debian.org/debian-security-announce/2026/msg00016.html",
          "published": "",
          "updated": "2026-01-22",
          "updated_parsed": [
            2026,
            1,
            22,
            0,
            0,
            0,
            3,
            22,
            0
          ],
          "guid": "https://lists.debian.org/debian-security-announce/2026/msg00016.html"
        }
      },
      {
        "source": "debian_security",
        "id": "https://lists.debian.org/debian-security-announce/2026/msg00017.html",
        "url": "https://lists.debian.org/debian-security-announce/2026/msg00017.html",
        "published_at": "2026-02-06T19:28:39Z",
        "updated_at": "2026-01-22T00:00:00Z",
        "headline": "DSA-6108-1 chromium - security update",
        "content": {
          "excerpt_text": "https://security-tracker.debian.org/tracker/DSA-6108-1",
          "lang": "en"
        },
        "provenance": {
          "fetched_at": "2026-02-06T19:28:39Z",
          "evidence_urls": [
            "https://lists.debian.org/debian-security-announce/2026/msg00017.html"
          ],
          "content_hash": "sha256:c26250be98bb71b238656a293b2522c49fc736d3990ebdce2f324056a0bf31d2"
        },
        "source_payload": {
          "html": "<a href=\"https://security-tracker.debian.org/tracker/DSA-6108-1\">https://security-tracker.debian.org/tracker/DSA-6108-1</a>",
          "link": "https://lists.debian.org/debian-security-announce/2026/msg00017.html",
          "published": "",
          "updated": "2026-01-22",
          "updated_parsed": [
            2026,
            1,
            22,
            0,
            0,
            0,
            3,
            22,
            0
          ],
          "guid": "https://lists.debian.org/debian-security-announce/2026/msg00017.html"
        }
      },
      {
        "source": "debian_security",
        "id": "https://lists.debian.org/debian-security-announce/2026/msg00015.html",
        "url": "https://lists.debian.org/debian-security-announce/2026/msg00015.html",
        "published_at": "2026-02-06T19:28:39Z",
        "updated_at": "2026-01-22T00:00:00Z",
        "headline": "DSA-6107-1 bind9 - security update",
        "content": {
          "excerpt_text": "https://security-tracker.debian.org/tracker/DSA-6107-1",
          "lang": "en"
        },
        "provenance": {
          "fetched_at": "2026-02-06T19:28:39Z",
          "evidence_urls": [
            "https://lists.debian.org/debian-security-announce/2026/msg00015.html"
          ],
          "content_hash": "sha256:4400655fbe471696188544350a466aa7b8bf09c53b62abf9ac9f046f579bec41"
        },
        "source_payload": {
          "html": "<a href=\"https://security-tracker.debian.org/tracker/DSA-6107-1\">https://security-tracker.debian.org/tracker/DSA-6107-1</a>",
          "link": "https://lists.debian.org/debian-security-announce/2026/msg00015.html",
          "published": "",
          "updated": "2026-01-22",
          "updated_parsed": [
            2026,
            1,
            22,
            0,
            0,
            0,
            3,
            22,
            0
          ],
          "guid": "https://lists.debian.org/debian-security-announce/2026/msg00015.html"
        }
      },
      {
        "source": "debian_security",
        "id": "https://lists.debian.org/debian-security-announce/2026/msg00014.html",
        "url": "https://lists.debian.org/debian-security-announce/2026/msg00014.html",
        "published_at": "2026-02-06T19:28:39Z",
        "updated_at": "2026-01-22T00:00:00Z",
        "headline": "DSA-6106-1 inetutils - security update",
        "content": {
          "excerpt_text": "https://security-tracker.debian.org/tracker/DSA-6106-1",
          "lang": "en"
        },
        "provenance": {
          "fetched_at": "2026-02-06T19:28:39Z",
          "evidence_urls": [
            "https://lists.debian.org/debian-security-announce/2026/msg00014.html"
          ],
          "content_hash": "sha256:75b41ccbd19cac6e9c97c60e777099d15c01d5e88ac4693b51a29205867bd850"
        },
        "source_payload": {
          "html": "<a href=\"https://security-tracker.debian.org/tracker/DSA-6106-1\">https://security-tracker.debian.org/tracker/DSA-6106-1</a>",
          "link": "https://lists.debian.org/debian-security-announce/2026/msg00014.html",
          "published": "",
          "updated": "2026-01-22",
          "updated_parsed": [
            2026,
            1,
            22,
            0,
            0,
            0,
            3,
            22,
            0
          ],
          "guid": "https://lists.debian.org/debian-security-announce/2026/msg00014.html"
        }
      },
      {
        "source": "debian_security",
        "id": "https://lists.debian.org/debian-security-announce/2026/msg00013.html",
        "url": "https://lists.debian.org/debian-security-announce/2026/msg00013.html",
        "published_at": "2026-02-06T19:28:39Z",
        "updated_at": "2026-01-21T00:00:00Z",
        "headline": "DSA-6105-1 modsecurity-crs - security update",
        "content": {
          "excerpt_text": "https://security-tracker.debian.org/tracker/DSA-6105-1",
          "lang": "en"
        },
        "provenance": {
          "fetched_at": "2026-02-06T19:28:39Z",
          "evidence_urls": [
            "https://lists.debian.org/debian-security-announce/2026/msg00013.html"
          ],
          "content_hash": "sha256:ce58e7518d337f80ec2710da7f1263823105350ff845cfb5b9f88cb09caa28b3"
        },
        "source_payload": {
          "html": "<a href=\"https://security-tracker.debian.org/tracker/DSA-6105-1\">https://security-tracker.debian.org/tracker/DSA-6105-1</a>",
          "link": "https://lists.debian.org/debian-security-announce/2026/msg00013.html",
          "published": "",
          "updated": "2026-01-21",
          "updated_parsed": [
            2026,
            1,
            21,
            0,
            0,
            0,
            2,
            21,
            0
          ],
          "guid": "https://lists.debian.org/debian-security-announce/2026/msg00013.html"
        }
      },
      {
        "source": "debian_security",
        "id": "https://lists.debian.org/debian-security-announce/2026/msg00012.html",
        "url": "https://lists.debian.org/debian-security-announce/2026/msg00012.html",
        "published_at": "2026-02-06T19:28:39Z",
        "updated_at": "2026-01-20T00:00:00Z",
        "headline": "DSA-6104-1 python-keystonemiddleware - security update",
        "content": {
          "excerpt_text": "https://security-tracker.debian.org/tracker/DSA-6104-1",
          "lang": "en"
        },
        "provenance": {
          "fetched_at": "2026-02-06T19:28:39Z",
          "evidence_urls": [
            "https://lists.debian.org/debian-security-announce/2026/msg00012.html"
          ],
          "content_hash": "sha256:41b81fe16c2e5e58935044fbc1bf9776ab0c4219fdc708279edc32cb7f7d9554"
        },
        "source_payload": {
          "html": "<a href=\"https://security-tracker.debian.org/tracker/DSA-6104-1\">https://security-tracker.debian.org/tracker/DSA-6104-1</a>",
          "link": "https://lists.debian.org/debian-security-announce/2026/msg00012.html",
          "published": "",
          "updated": "2026-01-20",
          "updated_parsed": [
            2026,
            1,
            20,
            0,
            0,
            0,
            1,
            20,
            0
          ],
          "guid": "https://lists.debian.org/debian-security-announce/2026/msg00012.html"
        }
      },
      {
        "source": "debian_security",
        "id": "https://lists.debian.org/debian-security-announce/2026/msg00011.html",
        "url": "https://lists.debian.org/debian-security-announce/2026/msg00011.html",
        "published_at": "2026-02-06T19:28:39Z",
        "updated_at": "2026-01-17T00:00:00Z",
        "headline": "DSA-6103-1 thunderbird - security update",
        "content": {
          "excerpt_text": "https://security-tracker.debian.org/tracker/DSA-6103-1",
          "lang": "en"
        },
        "provenance": {
          "fetched_at": "2026-02-06T19:28:39Z",
          "evidence_urls": [
            "https://lists.debian.org/debian-security-announce/2026/msg00011.html"
          ],
          "content_hash": "sha256:570b0fbaa20520390c2fc761bde7514a5dbdd83c3f373c6a3b972fa4f6cb16e7"
        },
        "source_payload": {
          "html": "<a href=\"https://security-tracker.debian.org/tracker/DSA-6103-1\">https://security-tracker.debian.org/tracker/DSA-6103-1</a>",
          "link": "https://lists.debian.org/debian-security-announce/2026/msg00011.html",
          "published": "",
          "updated": "2026-01-17",
          "updated_parsed": [
            2026,
            1,
            17,
            0,
            0,
            0,
            5,
            17,
            0
          ],
          "guid": "https://lists.debian.org/debian-security-announce/2026/msg00011.html"
        }
      },
      {
        "source": "debian_security",
        "id": "https://lists.debian.org/debian-security-announce/2026/msg00010.html",
        "url": "https://lists.debian.org/debian-security-announce/2026/msg00010.html",
        "published_at": "2026-02-06T19:28:39Z",
        "updated_at": "2026-01-17T00:00:00Z",
        "headline": "DSA-6102-1 python-urllib3 - security update",
        "content": {
          "excerpt_text": "https://security-tracker.debian.org/tracker/DSA-6102-1",
          "lang": "en"
        },
        "provenance": {
          "fetched_at": "2026-02-06T19:28:39Z",
          "evidence_urls": [
            "https://lists.debian.org/debian-security-announce/2026/msg00010.html"
          ],
          "content_hash": "sha256:f444d97239b1208dcf7a69f254ff092b6c747c0132ad6d3bc19b0b5e7f3fc052"
        },
        "source_payload": {
          "html": "<a href=\"https://security-tracker.debian.org/tracker/DSA-6102-1\">https://security-tracker.debian.org/tracker/DSA-6102-1</a>",
          "link": "https://lists.debian.org/debian-security-announce/2026/msg00010.html",
          "published": "",
          "updated": "2026-01-17",
          "updated_parsed": [
            2026,
            1,
            17,
            0,
            0,
            0,
            5,
            17,
            0
          ],
          "guid": "https://lists.debian.org/debian-security-announce/2026/msg00010.html"
        }
      },
      {
        "source": "debian_security",
        "id": "https://lists.debian.org/debian-security-announce/2026/msg00009.html",
        "url": "https://lists.debian.org/debian-security-announce/2026/msg00009.html",
        "published_at": "2026-02-06T19:28:39Z",
        "updated_at": "2026-01-15T00:00:00Z",
        "headline": "DSA-6101-1 firefox-esr - security update",
        "content": {
          "excerpt_text": "https://security-tracker.debian.org/tracker/DSA-6101-1",
          "lang": "en"
        },
        "provenance": {
          "fetched_at": "2026-02-06T19:28:39Z",
          "evidence_urls": [
            "https://lists.debian.org/debian-security-announce/2026/msg00009.html"
          ],
          "content_hash": "sha256:9220a4feaa7ff8c505b9f51d355254f1e3a957704ddbcc1a89fe0e493ba7d458"
        },
        "source_payload": {
          "html": "<a href=\"https://security-tracker.debian.org/tracker/DSA-6101-1\">https://security-tracker.debian.org/tracker/DSA-6101-1</a>",
          "link": "https://lists.debian.org/debian-security-announce/2026/msg00009.html",
          "published": "",
          "updated": "2026-01-15",
          "updated_parsed": [
            2026,
            1,
            15,
            0,
            0,
            0,
            3,
            15,
            0
          ],
          "guid": "https://lists.debian.org/debian-security-announce/2026/msg00009.html"
        }
      },
      {
        "source": "debian_security",
        "id": "https://lists.debian.org/debian-security-announce/2026/msg00008.html",
        "url": "https://lists.debian.org/debian-security-announce/2026/msg00008.html",
        "published_at": "2026-02-06T19:28:39Z",
        "updated_at": "2026-01-14T00:00:00Z",
        "headline": "DSA-6100-1 chromium - security update",
        "content": {
          "excerpt_text": "https://security-tracker.debian.org/tracker/DSA-6100-1",
          "lang": "en"
        },
        "provenance": {
          "fetched_at": "2026-02-06T19:28:39Z",
          "evidence_urls": [
            "https://lists.debian.org/debian-security-announce/2026/msg00008.html"
          ],
          "content_hash": "sha256:95938d84c291590e3bb251e750bf981a2ace4de90c5c34d6651bd7b8a2efd163"
        },
        "source_payload": {
          "html": "<a href=\"https://security-tracker.debian.org/tracker/DSA-6100-1\">https://security-tracker.debian.org/tracker/DSA-6100-1</a>",
          "link": "https://lists.debian.org/debian-security-announce/2026/msg00008.html",
          "published": "",
          "updated": "2026-01-14",
          "updated_parsed": [
            2026,
            1,
            14,
            0,
            0,
            0,
            2,
            14,
            0
          ],
          "guid": "https://lists.debian.org/debian-security-announce/2026/msg00008.html"
        }
      },
      {
        "source": "debian_security",
        "id": "https://lists.debian.org/debian-security-announce/2026/msg00007.html",
        "url": "https://lists.debian.org/debian-security-announce/2026/msg00007.html",
        "published_at": "2026-02-06T19:28:39Z",
        "updated_at": "2026-01-14T00:00:00Z",
        "headline": "DSA-6099-1 python-parsl - security update",
        "content": {
          "excerpt_text": "https://security-tracker.debian.org/tracker/DSA-6099-1",
          "lang": "en"
        },
        "provenance": {
          "fetched_at": "2026-02-06T19:28:39Z",
          "evidence_urls": [
            "https://lists.debian.org/debian-security-announce/2026/msg00007.html"
          ],
          "content_hash": "sha256:77df552b63a22ae5e8d7956fc5d3920aa78405301f8902f347ef477b63fac0c6"
        },
        "source_payload": {
          "html": "<a href=\"https://security-tracker.debian.org/tracker/DSA-6099-1\">https://security-tracker.debian.org/tracker/DSA-6099-1</a>",
          "link": "https://lists.debian.org/debian-security-announce/2026/msg00007.html",
          "published": "",
          "updated": "2026-01-14",
          "updated_parsed": [
            2026,
            1,
            14,
            0,
            0,
            0,
            2,
            14,
            0
          ],
          "guid": "https://lists.debian.org/debian-security-announce/2026/msg00007.html"
        }
      },
      {
        "source": "debian_security",
        "id": "https://lists.debian.org/debian-security-announce/2026/msg00006.html",
        "url": "https://lists.debian.org/debian-security-announce/2026/msg00006.html",
        "published_at": "2026-02-06T19:28:39Z",
        "updated_at": "2026-01-12T00:00:00Z",
        "headline": "DSA-6098-1 net-snmp - security update",
        "content": {
          "excerpt_text": "https://security-tracker.debian.org/tracker/DSA-6098-1",
          "lang": "en"
        },
        "provenance": {
          "fetched_at": "2026-02-06T19:28:39Z",
          "evidence_urls": [
            "https://lists.debian.org/debian-security-announce/2026/msg00006.html"
          ],
          "content_hash": "sha256:28f5bb536f851b02e3e6287c4226e52870e228ddba203890e002ece96a36dc91"
        },
        "source_payload": {
          "html": "<a href=\"https://security-tracker.debian.org/tracker/DSA-6098-1\">https://security-tracker.debian.org/tracker/DSA-6098-1</a>",
          "link": "https://lists.debian.org/debian-security-announce/2026/msg00006.html",
          "published": "",
          "updated": "2026-01-12",
          "updated_parsed": [
            2026,
            1,
            12,
            0,
            0,
            0,
            0,
            12,
            0
          ],
          "guid": "https://lists.debian.org/debian-security-announce/2026/msg00006.html"
        }
      },
      {
        "source": "debian_security",
        "id": "https://lists.debian.org/debian-security-announce/2026/msg00005.html",
        "url": "https://lists.debian.org/debian-security-announce/2026/msg00005.html",
        "published_at": "2026-02-06T19:28:39Z",
        "updated_at": "2026-01-09T00:00:00Z",
        "headline": "DSA-6097-1 chromium - security update",
        "content": {
          "excerpt_text": "https://security-tracker.debian.org/tracker/DSA-6097-1",
          "lang": "en"
        },
        "provenance": {
          "fetched_at": "2026-02-06T19:28:39Z",
          "evidence_urls": [
            "https://lists.debian.org/debian-security-announce/2026/msg00005.html"
          ],
          "content_hash": "sha256:095f778d25d6920bf104abb8cd20b284a6d698af71caea1d426041755502fd16"
        },
        "source_payload": {
          "html": "<a href=\"https://security-tracker.debian.org/tracker/DSA-6097-1\">https://security-tracker.debian.org/tracker/DSA-6097-1</a>",
          "link": "https://lists.debian.org/debian-security-announce/2026/msg00005.html",
          "published": "",
          "updated": "2026-01-09",
          "updated_parsed": [
            2026,
            1,
            9,
            0,
            0,
            0,
            4,
            9,
            0
          ],
          "guid": "https://lists.debian.org/debian-security-announce/2026/msg00005.html"
        }
      },
      {
        "source": "debian_security",
        "id": "https://lists.debian.org/debian-security-announce/2026/msg00004.html",
        "url": "https://lists.debian.org/debian-security-announce/2026/msg00004.html",
        "published_at": "2026-02-06T19:28:39Z",
        "updated_at": "2026-01-08T00:00:00Z",
        "headline": "DSA-6096-1 vlc - security update",
        "content": {
          "excerpt_text": "https://security-tracker.debian.org/tracker/DSA-6096-1",
          "lang": "en"
        },
        "provenance": {
          "fetched_at": "2026-02-06T19:28:39Z",
          "evidence_urls": [
            "https://lists.debian.org/debian-security-announce/2026/msg00004.html"
          ],
          "content_hash": "sha256:348da2c1efa974e7279b0d8dc41e7213da5c85f7e42ad22227d544634c5f88c4"
        },
        "source_payload": {
          "html": "<a href=\"https://security-tracker.debian.org/tracker/DSA-6096-1\">https://security-tracker.debian.org/tracker/DSA-6096-1</a>",
          "link": "https://lists.debian.org/debian-security-announce/2026/msg00004.html",
          "published": "",
          "updated": "2026-01-08",
          "updated_parsed": [
            2026,
            1,
            8,
            0,
            0,
            0,
            3,
            8,
            0
          ],
          "guid": "https://lists.debian.org/debian-security-announce/2026/msg00004.html"
        }
      },
      {
        "source": "debian_security",
        "id": "https://lists.debian.org/debian-security-announce/2026/msg00003.html",
        "url": "https://lists.debian.org/debian-security-announce/2026/msg00003.html",
        "published_at": "2026-02-06T19:28:39Z",
        "updated_at": "2026-01-07T00:00:00Z",
        "headline": "DSA-6095-1 foomuuri - security update",
        "content": {
          "excerpt_text": "https://security-tracker.debian.org/tracker/DSA-6095-1",
          "lang": "en"
        },
        "provenance": {
          "fetched_at": "2026-02-06T19:28:39Z",
          "evidence_urls": [
            "https://lists.debian.org/debian-security-announce/2026/msg00003.html"
          ],
          "content_hash": "sha256:735aa89fe3d002501a4bf760b5ea3c4946269f8c7f099f7eab5156056513034b"
        },
        "source_payload": {
          "html": "<a href=\"https://security-tracker.debian.org/tracker/DSA-6095-1\">https://security-tracker.debian.org/tracker/DSA-6095-1</a>",
          "link": "https://lists.debian.org/debian-security-announce/2026/msg00003.html",
          "published": "",
          "updated": "2026-01-07",
          "updated_parsed": [
            2026,
            1,
            7,
            0,
            0,
            0,
            2,
            7,
            0
          ],
          "guid": "https://lists.debian.org/debian-security-announce/2026/msg00003.html"
        }
      },
      {
        "source": "debian_security",
        "id": "https://lists.debian.org/debian-security-announce/2026/msg00002.html",
        "url": "https://lists.debian.org/debian-security-announce/2026/msg00002.html",
        "published_at": "2026-02-06T19:28:39Z",
        "updated_at": "2026-01-05T00:00:00Z",
        "headline": "DSA-6094-1 libsodium - security update",
        "content": {
          "excerpt_text": "https://security-tracker.debian.org/tracker/DSA-6094-1",
          "lang": "en"
        },
        "provenance": {
          "fetched_at": "2026-02-06T19:28:39Z",
          "evidence_urls": [
            "https://lists.debian.org/debian-security-announce/2026/msg00002.html"
          ],
          "content_hash": "sha256:a755f8bcfd38fbdd1fbc0bc8430a30126ea762008b5806135f1aaf00ff41c54d"
        },
        "source_payload": {
          "html": "<a href=\"https://security-tracker.debian.org/tracker/DSA-6094-1\">https://security-tracker.debian.org/tracker/DSA-6094-1</a>",
          "link": "https://lists.debian.org/debian-security-announce/2026/msg00002.html",
          "published": "",
          "updated": "2026-01-05",
          "updated_parsed": [
            2026,
            1,
            5,
            0,
            0,
            0,
            0,
            5,
            0
          ],
          "guid": "https://lists.debian.org/debian-security-announce/2026/msg00002.html"
        }
      }
    ],
    "updated": [],
    "removed": [],
    "flagged": []
  },
  "counts": {
    "new": 30,
    "updated": 0,
    "removed": 0,
    "flagged": 0
  },
  "integrity_reset": true,
  "integrity_risk": 0.2
}
