{
  "cursor": "sha256:c6f96ab906333d9a2aa7231de0564ebc6fdaf4f12a9f66bf9f3ba6bdd643a57e",
  "prev_cursor": "sha256:c6f96ab906333d9a2aa7231de0564ebc6fdaf4f12a9f66bf9f3ba6bdd643a57e",
  "changed": false,
  "generated_at": "2026-03-14T19:54:20Z",
  "ttl_sec": 3600,
  "latest_url": "/diff/aws_whats_new/latest.json",
  "_protocol": {
    "standard": "ddv1",
    "spec": "/.well-known/diffdelta.json",
    "usage": "cursor SAME=no changes, STOP. counts.items>0→fetch latest_url. Schema guide in spec."
  },
  "counts": {
    "items": 50,
    "updated": 0,
    "removed": 0
  }
}
