{
  "schema_version": "1.2.0",
  "generated_at": "2026-03-11T16:09:52Z",
  "source_id": "pypi_recent_updates",
  "hash": "sha256:af874d9762499abb68bbb37ac715a55573ec064bf8bb6e22353adeafadce2ad7",
  "prev_hash": "sha256:57bc95c79fa0a703d15f0bf7c0d2c33e8c1e13aed014e6f65c1835e241d55766",
  "cursor": "sha256:39b76d62b283a4c03af77d8a1c971c3a3450a3174b5974c077b91831a7af21d9",
  "prev_cursor": "sha256:67ac915280c6fc44ce5ec6a95457d37a72de980d959dfe4f64b15de8174b1fc9",
  "changed": true,
  "ttl_sec": 1800,
  "sources_included": [
    "pypi_recent_updates"
  ],
  "batch_narrative": "pypi_recent_updates: 40 releases (37 stable, 3 pre-release).",
  "buckets": {
    "items": [
      {
        "source": "pypi_recent_updates",
        "id": "b50e4d907aeb43cdb0253eb1d72dfa22",
        "url": "https://pypi.org/project/raytrax/0.2.0/",
        "published_at": "2026-03-11T15:59:30Z",
        "updated_at": "2026-03-11T15:59:30Z",
        "headline": "raytrax 0.2.0",
        "content": {
          "excerpt_text": "An ECRH ray tracer based on JAX",
          "lang": "en"
        },
        "provenance": {
          "fetched_at": "2026-03-11T16:09:52Z",
          "evidence_urls": [
            "https://pypi.org/project/raytrax/0.2.0/"
          ],
          "content_hash": "sha256:3f1620d4812c0c8eb33fc032bcaac14ce45baafe415402599fddf2abc555c1e2"
        },
        "signals": {
          "release": {
            "version": "0.2.0",
            "provenance": {
              "method": "title_regex",
              "authority": "PyPI Recent Updates",
              "authority_url": "https://pypi.org",
              "evidence_url": "https://pypi.org/project/raytrax/0.2.0/"
            }
          }
        },
        "source_payload": {
          "html": "An ECRH ray tracer based on JAX",
          "link": "https://pypi.org/project/raytrax/0.2.0/",
          "published": "Wed, 11 Mar 2026 15:59:30 GMT",
          "published_parsed": [
            2026,
            3,
            11,
            15,
            59,
            30,
            2,
            70,
            0
          ],
          "updated": "Wed, 11 Mar 2026 15:59:30 GMT",
          "updated_parsed": [
            2026,
            3,
            11,
            15,
            59,
            30,
            2,
            70,
            0
          ],
          "guid": ""
        }
      },
      {
        "source": "pypi_recent_updates",
        "id": "90cecdeb66e537ee0bccb90838189293",
        "url": "https://pypi.org/project/aish-cli/0.1.6/",
        "published_at": "2026-03-11T15:59:25Z",
        "updated_at": "2026-03-11T15:59:25Z",
        "headline": "aish-cli 0.1.6",
        "content": {
          "excerpt_text": "AI-powered shell command assistant - convert natural language to safe executable commands",
          "lang": "en"
        },
        "provenance": {
          "fetched_at": "2026-03-11T16:09:52Z",
          "evidence_urls": [
            "https://pypi.org/project/aish-cli/0.1.6/"
          ],
          "content_hash": "sha256:5ac6abc5415c0da67daf29f5012b0e1332bd475450ce284089e1e4417547a48a"
        },
        "signals": {
          "release": {
            "version": "0.1.6",
            "provenance": {
              "method": "title_regex",
              "authority": "PyPI Recent Updates",
              "authority_url": "https://pypi.org",
              "evidence_url": "https://pypi.org/project/aish-cli/0.1.6/"
            }
          }
        },
        "source_payload": {
          "html": "AI-powered shell command assistant - convert natural language to safe executable commands",
          "link": "https://pypi.org/project/aish-cli/0.1.6/",
          "published": "Wed, 11 Mar 2026 15:59:25 GMT",
          "published_parsed": [
            2026,
            3,
            11,
            15,
            59,
            25,
            2,
            70,
            0
          ],
          "updated": "Wed, 11 Mar 2026 15:59:25 GMT",
          "updated_parsed": [
            2026,
            3,
            11,
            15,
            59,
            25,
            2,
            70,
            0
          ],
          "guid": ""
        }
      },
      {
        "source": "pypi_recent_updates",
        "id": "ed53a3570dbd1e035fb38c1362b9c0c6",
        "url": "https://pypi.org/project/airbyte-cdk/7.10.1.post12.dev22961776456/",
        "published_at": "2026-03-11T15:59:25Z",
        "updated_at": "2026-03-11T15:59:25Z",
        "headline": "airbyte-cdk 7.10.1.post12.dev22961776456",
        "content": {
          "excerpt_text": "A framework for writing Airbyte Connectors.",
          "lang": "en"
        },
        "provenance": {
          "fetched_at": "2026-03-11T16:09:52Z",
          "evidence_urls": [
            "https://pypi.org/project/airbyte-cdk/7.10.1.post12.dev22961776456/"
          ],
          "content_hash": "sha256:774f08885473172213f0df8e3c1d892e7d506ce67cd94d8da984a144964f995d"
        },
        "signals": {
          "release": {
            "version": "7.10.1",
            "prerelease": true,
            "provenance": {
              "method": "title_regex",
              "authority": "PyPI Recent Updates",
              "authority_url": "https://pypi.org",
              "evidence_url": "https://pypi.org/project/airbyte-cdk/7.10.1.post12.dev22961776456/"
            }
          }
        },
        "source_payload": {
          "html": "A framework for writing Airbyte Connectors.",
          "link": "https://pypi.org/project/airbyte-cdk/7.10.1.post12.dev22961776456/",
          "published": "Wed, 11 Mar 2026 15:59:25 GMT",
          "published_parsed": [
            2026,
            3,
            11,
            15,
            59,
            25,
            2,
            70,
            0
          ],
          "updated": "Wed, 11 Mar 2026 15:59:25 GMT",
          "updated_parsed": [
            2026,
            3,
            11,
            15,
            59,
            25,
            2,
            70,
            0
          ],
          "guid": ""
        }
      },
      {
        "source": "pypi_recent_updates",
        "id": "72bdb5fa9b189436396723f462296fb9",
        "url": "https://pypi.org/project/zhijiang/0.9.145/",
        "published_at": "2026-03-11T15:59:13Z",
        "updated_at": "2026-03-11T15:59:13Z",
        "headline": "zhijiang 0.9.145",
        "content": {
          "excerpt_text": "published at 2026-03-11",
          "lang": "en"
        },
        "provenance": {
          "fetched_at": "2026-03-11T16:09:52Z",
          "evidence_urls": [
            "https://pypi.org/project/zhijiang/0.9.145/"
          ],
          "content_hash": "sha256:eeded9e5a042c291a3c7815c2c982b88a288c8e8e95caacff1c911a12ee33f1f"
        },
        "signals": {
          "release": {
            "version": "0.9.145",
            "provenance": {
              "method": "title_regex",
              "authority": "PyPI Recent Updates",
              "authority_url": "https://pypi.org",
              "evidence_url": "https://pypi.org/project/zhijiang/0.9.145/"
            }
          }
        },
        "source_payload": {
          "html": "published at 2026-03-11",
          "link": "https://pypi.org/project/zhijiang/0.9.145/",
          "published": "Wed, 11 Mar 2026 15:59:13 GMT",
          "published_parsed": [
            2026,
            3,
            11,
            15,
            59,
            13,
            2,
            70,
            0
          ],
          "updated": "Wed, 11 Mar 2026 15:59:13 GMT",
          "updated_parsed": [
            2026,
            3,
            11,
            15,
            59,
            13,
            2,
            70,
            0
          ],
          "guid": ""
        }
      },
      {
        "source": "pypi_recent_updates",
        "id": "d40b359562c1b07979d9541adbec2ed9",
        "url": "https://pypi.org/project/nattsquare-sdk/1.0.0/",
        "published_at": "2026-03-11T15:58:59Z",
        "updated_at": "2026-03-11T15:58:59Z",
        "headline": "nattsquare-sdk 1.0.0",
        "content": {
          "excerpt_text": "SDK Officiel M2M pour NattSquare (x402 protocol / Agent-to-Agent)",
          "lang": "en"
        },
        "provenance": {
          "fetched_at": "2026-03-11T16:09:52Z",
          "evidence_urls": [
            "https://pypi.org/project/nattsquare-sdk/1.0.0/"
          ],
          "content_hash": "sha256:361cbcd902846dda4de771f7ba6ef7366caf10e8ce4152314779e0c00f9f80a2"
        },
        "signals": {
          "release": {
            "version": "1.0.0",
            "provenance": {
              "method": "title_regex",
              "authority": "PyPI Recent Updates",
              "authority_url": "https://pypi.org",
              "evidence_url": "https://pypi.org/project/nattsquare-sdk/1.0.0/"
            }
          }
        },
        "source_payload": {
          "html": "SDK Officiel M2M pour NattSquare (x402 protocol / Agent-to-Agent)",
          "link": "https://pypi.org/project/nattsquare-sdk/1.0.0/",
          "published": "Wed, 11 Mar 2026 15:58:59 GMT",
          "published_parsed": [
            2026,
            3,
            11,
            15,
            58,
            59,
            2,
            70,
            0
          ],
          "updated": "Wed, 11 Mar 2026 15:58:59 GMT",
          "updated_parsed": [
            2026,
            3,
            11,
            15,
            58,
            59,
            2,
            70,
            0
          ],
          "guid": ""
        }
      },
      {
        "source": "pypi_recent_updates",
        "id": "fe8d42da2ddbbde4441aa0e8c30dc45e",
        "url": "https://pypi.org/project/pulumi-gcp/9.15.0a1773212575/",
        "published_at": "2026-03-11T15:58:49Z",
        "updated_at": "2026-03-11T15:58:49Z",
        "headline": "pulumi-gcp 9.15.0a1773212575",
        "content": {
          "excerpt_text": "A Pulumi package for creating and managing Google Cloud Platform resources.",
          "lang": "en"
        },
        "provenance": {
          "fetched_at": "2026-03-11T16:09:52Z",
          "evidence_urls": [
            "https://pypi.org/project/pulumi-gcp/9.15.0a1773212575/"
          ],
          "content_hash": "sha256:cc88df8da0455fd381ee3b84250076399517711a4ed2783ddff635f308d2b344"
        },
        "signals": {
          "release": {
            "version": "9.15.0",
            "provenance": {
              "method": "title_regex",
              "authority": "PyPI Recent Updates",
              "authority_url": "https://pypi.org",
              "evidence_url": "https://pypi.org/project/pulumi-gcp/9.15.0a1773212575/"
            }
          }
        },
        "source_payload": {
          "html": "A Pulumi package for creating and managing Google Cloud Platform resources.",
          "link": "https://pypi.org/project/pulumi-gcp/9.15.0a1773212575/",
          "published": "Wed, 11 Mar 2026 15:58:49 GMT",
          "published_parsed": [
            2026,
            3,
            11,
            15,
            58,
            49,
            2,
            70,
            0
          ],
          "updated": "Wed, 11 Mar 2026 15:58:49 GMT",
          "updated_parsed": [
            2026,
            3,
            11,
            15,
            58,
            49,
            2,
            70,
            0
          ],
          "guid": ""
        }
      },
      {
        "source": "pypi_recent_updates",
        "id": "d63043e995161c0640172b34dee8eabf",
        "url": "https://pypi.org/project/pulumi-aws/7.22.0a1773213292/",
        "published_at": "2026-03-11T15:58:37Z",
        "updated_at": "2026-03-11T15:58:37Z",
        "headline": "pulumi-aws 7.22.0a1773213292",
        "content": {
          "excerpt_text": "A Pulumi package for creating and managing Amazon Web Services (AWS) cloud resources.",
          "lang": "en"
        },
        "provenance": {
          "fetched_at": "2026-03-11T16:09:52Z",
          "evidence_urls": [
            "https://pypi.org/project/pulumi-aws/7.22.0a1773213292/"
          ],
          "content_hash": "sha256:6541ed11873dfe80a2c3dba6a13d55b8b2bd5e815f928876a8e6a1562750fedd"
        },
        "signals": {
          "release": {
            "version": "7.22.0",
            "provenance": {
              "method": "title_regex",
              "authority": "PyPI Recent Updates",
              "authority_url": "https://pypi.org",
              "evidence_url": "https://pypi.org/project/pulumi-aws/7.22.0a1773213292/"
            }
          }
        },
        "source_payload": {
          "html": "A Pulumi package for creating and managing Amazon Web Services (AWS) cloud resources.",
          "link": "https://pypi.org/project/pulumi-aws/7.22.0a1773213292/",
          "published": "Wed, 11 Mar 2026 15:58:37 GMT",
          "published_parsed": [
            2026,
            3,
            11,
            15,
            58,
            37,
            2,
            70,
            0
          ],
          "updated": "Wed, 11 Mar 2026 15:58:37 GMT",
          "updated_parsed": [
            2026,
            3,
            11,
            15,
            58,
            37,
            2,
            70,
            0
          ],
          "guid": ""
        }
      },
      {
        "source": "pypi_recent_updates",
        "id": "b2420c5b39aa476f625211893ad12e8f",
        "url": "https://pypi.org/project/boxy-agent/0.2.0a1/",
        "published_at": "2026-03-11T15:58:33Z",
        "updated_at": "2026-03-11T15:58:33Z",
        "headline": "boxy-agent 0.2.0a1",
        "content": {
          "excerpt_text": "SDK and CLI for building Boxy agents",
          "lang": "en"
        },
        "provenance": {
          "fetched_at": "2026-03-11T16:09:52Z",
          "evidence_urls": [
            "https://pypi.org/project/boxy-agent/0.2.0a1/"
          ],
          "content_hash": "sha256:903a190b601eeeb63c8477f8d0e298c2d9a319281b11a72a81f06a65199b9fad"
        },
        "signals": {
          "release": {
            "version": "0.2.0",
            "provenance": {
              "method": "title_regex",
              "authority": "PyPI Recent Updates",
              "authority_url": "https://pypi.org",
              "evidence_url": "https://pypi.org/project/boxy-agent/0.2.0a1/"
            }
          }
        },
        "source_payload": {
          "html": "SDK and CLI for building Boxy agents",
          "link": "https://pypi.org/project/boxy-agent/0.2.0a1/",
          "published": "Wed, 11 Mar 2026 15:58:33 GMT",
          "published_parsed": [
            2026,
            3,
            11,
            15,
            58,
            33,
            2,
            70,
            0
          ],
          "updated": "Wed, 11 Mar 2026 15:58:33 GMT",
          "updated_parsed": [
            2026,
            3,
            11,
            15,
            58,
            33,
            2,
            70,
            0
          ],
          "guid": ""
        }
      },
      {
        "source": "pypi_recent_updates",
        "id": "7f229900b755db9fd20473987e1a5250",
        "url": "https://pypi.org/project/pulumi-azure/6.34.0a1773211339/",
        "published_at": "2026-03-11T15:58:28Z",
        "updated_at": "2026-03-11T15:58:28Z",
        "headline": "pulumi-azure 6.34.0a1773211339",
        "content": {
          "excerpt_text": "A Pulumi package for creating and managing Microsoft Azure cloud resources, based on the Terraform azurerm provider. We recommend using the [Azure Native provider](https://github.com/pulumi/pulumi-azure-native) to provision Azure infrastructure. Azure Native provides complete coverage of Azure resources and same-day access to new resources and resource updates.",
          "lang": "en"
        },
        "provenance": {
          "fetched_at": "2026-03-11T16:09:52Z",
          "evidence_urls": [
            "https://pypi.org/project/pulumi-azure/6.34.0a1773211339/"
          ],
          "content_hash": "sha256:dfd4bbed79b74033627ba3c58736f258fa5c6e7ca0f2f4f5dcf2b50c48332b2c"
        },
        "signals": {
          "release": {
            "version": "6.34.0",
            "provenance": {
              "method": "title_regex",
              "authority": "PyPI Recent Updates",
              "authority_url": "https://pypi.org",
              "evidence_url": "https://pypi.org/project/pulumi-azure/6.34.0a1773211339/"
            }
          }
        },
        "source_payload": {
          "html": "A Pulumi package for creating and managing Microsoft Azure cloud resources, based on the Terraform azurerm provider. We recommend using the [Azure Native provider](https://github.com/pulumi/pulumi-azure-native) to provision Azure infrastructure. Azure Native provides complete coverage of Azure resources and same-day access to new resources and resource updates.",
          "link": "https://pypi.org/project/pulumi-azure/6.34.0a1773211339/",
          "published": "Wed, 11 Mar 2026 15:58:28 GMT",
          "published_parsed": [
            2026,
            3,
            11,
            15,
            58,
            28,
            2,
            70,
            0
          ],
          "updated": "Wed, 11 Mar 2026 15:58:28 GMT",
          "updated_parsed": [
            2026,
            3,
            11,
            15,
            58,
            28,
            2,
            70,
            0
          ],
          "guid": ""
        }
      },
      {
        "source": "pypi_recent_updates",
        "id": "f21e9f59980d6c20ebb764d8c71b1a7c",
        "url": "https://pypi.org/project/odoo-addon-l10n-es-atc-mod420/17.0.1.1.3/",
        "published_at": "2026-03-11T15:58:15Z",
        "updated_at": "2026-03-11T15:58:15Z",
        "headline": "odoo-addon-l10n-es-atc-mod420 17.0.1.1.3",
        "content": {
          "excerpt_text": "ATC Modelo 420",
          "lang": "en"
        },
        "provenance": {
          "fetched_at": "2026-03-11T16:09:52Z",
          "evidence_urls": [
            "https://pypi.org/project/odoo-addon-l10n-es-atc-mod420/17.0.1.1.3/"
          ],
          "content_hash": "sha256:e540630a94f3374618c4ab4148fd31b784a7c6e5db5a0bf1eaf9802a9e18f08d"
        },
        "signals": {
          "release": {
            "version": "17.0.1",
            "provenance": {
              "method": "title_regex",
              "authority": "PyPI Recent Updates",
              "authority_url": "https://pypi.org",
              "evidence_url": "https://pypi.org/project/odoo-addon-l10n-es-atc-mod420/17.0.1.1.3/"
            }
          }
        },
        "source_payload": {
          "html": "ATC Modelo 420",
          "link": "https://pypi.org/project/odoo-addon-l10n-es-atc-mod420/17.0.1.1.3/",
          "published": "Wed, 11 Mar 2026 15:58:15 GMT",
          "published_parsed": [
            2026,
            3,
            11,
            15,
            58,
            15,
            2,
            70,
            0
          ],
          "updated": "Wed, 11 Mar 2026 15:58:15 GMT",
          "updated_parsed": [
            2026,
            3,
            11,
            15,
            58,
            15,
            2,
            70,
            0
          ],
          "guid": ""
        }
      },
      {
        "source": "pypi_recent_updates",
        "id": "33ae46ff308aa19dd53011db2e6527d9",
        "url": "https://pypi.org/project/wkls/1.1.0/",
        "published_at": "2026-03-11T15:58:14Z",
        "updated_at": "2026-03-11T15:58:14Z",
        "headline": "wkls 1.1.0",
        "content": {
          "excerpt_text": "Easy access to global administrative boundaries and geometries via Overture Maps data",
          "lang": "en"
        },
        "provenance": {
          "fetched_at": "2026-03-11T16:09:52Z",
          "evidence_urls": [
            "https://pypi.org/project/wkls/1.1.0/"
          ],
          "content_hash": "sha256:1951a6bfd0d1908b3edcef74983bba76aca3705fb40274396a1c3afac83f6aef"
        },
        "signals": {
          "release": {
            "version": "1.1.0",
            "provenance": {
              "method": "title_regex",
              "authority": "PyPI Recent Updates",
              "authority_url": "https://pypi.org",
              "evidence_url": "https://pypi.org/project/wkls/1.1.0/"
            }
          }
        },
        "source_payload": {
          "html": "Easy access to global administrative boundaries and geometries via Overture Maps data",
          "link": "https://pypi.org/project/wkls/1.1.0/",
          "published": "Wed, 11 Mar 2026 15:58:14 GMT",
          "published_parsed": [
            2026,
            3,
            11,
            15,
            58,
            14,
            2,
            70,
            0
          ],
          "updated": "Wed, 11 Mar 2026 15:58:14 GMT",
          "updated_parsed": [
            2026,
            3,
            11,
            15,
            58,
            14,
            2,
            70,
            0
          ],
          "guid": ""
        }
      },
      {
        "source": "pypi_recent_updates",
        "id": "b9d978bc5cd55e46d4c8b7a8b616c6b5",
        "url": "https://pypi.org/project/pulumi-cloudflare/6.14.0a1773210619/",
        "published_at": "2026-03-11T15:58:12Z",
        "updated_at": "2026-03-11T15:58:12Z",
        "headline": "pulumi-cloudflare 6.14.0a1773210619",
        "content": {
          "excerpt_text": "A Pulumi package for creating and managing Cloudflare cloud resources.",
          "lang": "en"
        },
        "provenance": {
          "fetched_at": "2026-03-11T16:09:52Z",
          "evidence_urls": [
            "https://pypi.org/project/pulumi-cloudflare/6.14.0a1773210619/"
          ],
          "content_hash": "sha256:0c1c0472763c608c4a9975b7141c23625c1add3d4911b5e074e426a6ae07239f"
        },
        "signals": {
          "release": {
            "version": "6.14.0",
            "provenance": {
              "method": "title_regex",
              "authority": "PyPI Recent Updates",
              "authority_url": "https://pypi.org",
              "evidence_url": "https://pypi.org/project/pulumi-cloudflare/6.14.0a1773210619/"
            }
          }
        },
        "source_payload": {
          "html": "A Pulumi package for creating and managing Cloudflare cloud resources.",
          "link": "https://pypi.org/project/pulumi-cloudflare/6.14.0a1773210619/",
          "published": "Wed, 11 Mar 2026 15:58:12 GMT",
          "published_parsed": [
            2026,
            3,
            11,
            15,
            58,
            12,
            2,
            70,
            0
          ],
          "updated": "Wed, 11 Mar 2026 15:58:12 GMT",
          "updated_parsed": [
            2026,
            3,
            11,
            15,
            58,
            12,
            2,
            70,
            0
          ],
          "guid": ""
        }
      },
      {
        "source": "pypi_recent_updates",
        "id": "cde3932829d20afe45907aaba34152f2",
        "url": "https://pypi.org/project/aias-common/0.13.1/",
        "published_at": "2026-03-11T15:58:10Z",
        "updated_at": "2026-03-11T15:58:10Z",
        "headline": "aias-common 0.13.1",
        "content": {
          "excerpt_text": "ARLAS AIAS common library",
          "lang": "en"
        },
        "provenance": {
          "fetched_at": "2026-03-11T16:09:52Z",
          "evidence_urls": [
            "https://pypi.org/project/aias-common/0.13.1/"
          ],
          "content_hash": "sha256:969f9e3fee0bcf3cfca4f84dca3f22c6d9a066e7118dd9be00b82d49f94651b6"
        },
        "signals": {
          "release": {
            "version": "0.13.1",
            "provenance": {
              "method": "title_regex",
              "authority": "PyPI Recent Updates",
              "authority_url": "https://pypi.org",
              "evidence_url": "https://pypi.org/project/aias-common/0.13.1/"
            }
          }
        },
        "source_payload": {
          "html": "ARLAS AIAS common library",
          "link": "https://pypi.org/project/aias-common/0.13.1/",
          "published": "Wed, 11 Mar 2026 15:58:10 GMT",
          "published_parsed": [
            2026,
            3,
            11,
            15,
            58,
            10,
            2,
            70,
            0
          ],
          "updated": "Wed, 11 Mar 2026 15:58:10 GMT",
          "updated_parsed": [
            2026,
            3,
            11,
            15,
            58,
            10,
            2,
            70,
            0
          ],
          "guid": ""
        }
      },
      {
        "source": "pypi_recent_updates",
        "id": "af1f7617e85608f9f47bfcbfaf0d3d8f",
        "url": "https://pypi.org/project/smello-server/0.3.4/",
        "published_at": "2026-03-11T15:58:05Z",
        "updated_at": "2026-03-11T15:58:05Z",
        "headline": "smello-server 0.3.4",
        "content": {
          "excerpt_text": "A local web dashboard for inspecting outgoing HTTP requests from your code",
          "lang": "en"
        },
        "provenance": {
          "fetched_at": "2026-03-11T16:09:52Z",
          "evidence_urls": [
            "https://pypi.org/project/smello-server/0.3.4/"
          ],
          "content_hash": "sha256:23927a11126cb4e96559721543a4e7a7f7696ee64a8fbe757491d512c8fb8573"
        },
        "signals": {
          "release": {
            "version": "0.3.4",
            "provenance": {
              "method": "title_regex",
              "authority": "PyPI Recent Updates",
              "authority_url": "https://pypi.org",
              "evidence_url": "https://pypi.org/project/smello-server/0.3.4/"
            }
          }
        },
        "source_payload": {
          "html": "A local web dashboard for inspecting outgoing HTTP requests from your code",
          "link": "https://pypi.org/project/smello-server/0.3.4/",
          "published": "Wed, 11 Mar 2026 15:58:05 GMT",
          "published_parsed": [
            2026,
            3,
            11,
            15,
            58,
            5,
            2,
            70,
            0
          ],
          "updated": "Wed, 11 Mar 2026 15:58:05 GMT",
          "updated_parsed": [
            2026,
            3,
            11,
            15,
            58,
            5,
            2,
            70,
            0
          ],
          "guid": ""
        }
      },
      {
        "source": "pypi_recent_updates",
        "id": "891ada8b1bccc4bbe2780bf8f34e1520",
        "url": "https://pypi.org/project/airsmodel/0.13.1/",
        "published_at": "2026-03-11T15:58:01Z",
        "updated_at": "2026-03-11T15:58:01Z",
        "headline": "airsmodel 0.13.1",
        "content": {
          "excerpt_text": "ARLAS Item Registration Service Model",
          "lang": "en"
        },
        "provenance": {
          "fetched_at": "2026-03-11T16:09:52Z",
          "evidence_urls": [
            "https://pypi.org/project/airsmodel/0.13.1/"
          ],
          "content_hash": "sha256:628d4777e1fc6fdf8b785a4e96c10540dd3ebcf8b7e0afed56551657cbf5da00"
        },
        "signals": {
          "release": {
            "version": "0.13.1",
            "provenance": {
              "method": "title_regex",
              "authority": "PyPI Recent Updates",
              "authority_url": "https://pypi.org",
              "evidence_url": "https://pypi.org/project/airsmodel/0.13.1/"
            }
          }
        },
        "source_payload": {
          "html": "ARLAS Item Registration Service Model",
          "link": "https://pypi.org/project/airsmodel/0.13.1/",
          "published": "Wed, 11 Mar 2026 15:58:01 GMT",
          "published_parsed": [
            2026,
            3,
            11,
            15,
            58,
            1,
            2,
            70,
            0
          ],
          "updated": "Wed, 11 Mar 2026 15:58:01 GMT",
          "updated_parsed": [
            2026,
            3,
            11,
            15,
            58,
            1,
            2,
            70,
            0
          ],
          "guid": ""
        }
      },
      {
        "source": "pypi_recent_updates",
        "id": "da659913437c01f43af386127428241f",
        "url": "https://pypi.org/project/pulumi-vsphere/4.17.0a1773211970/",
        "published_at": "2026-03-11T15:57:48Z",
        "updated_at": "2026-03-11T15:57:48Z",
        "headline": "pulumi-vsphere 4.17.0a1773211970",
        "content": {
          "excerpt_text": "A Pulumi package for creating vsphere resources",
          "lang": "en"
        },
        "provenance": {
          "fetched_at": "2026-03-11T16:09:52Z",
          "evidence_urls": [
            "https://pypi.org/project/pulumi-vsphere/4.17.0a1773211970/"
          ],
          "content_hash": "sha256:50aecf1ca9d350ad7f383e12bc22a6e633dac55f645703827afa12c9b387259b"
        },
        "signals": {
          "release": {
            "version": "4.17.0",
            "provenance": {
              "method": "title_regex",
              "authority": "PyPI Recent Updates",
              "authority_url": "https://pypi.org",
              "evidence_url": "https://pypi.org/project/pulumi-vsphere/4.17.0a1773211970/"
            }
          }
        },
        "source_payload": {
          "html": "A Pulumi package for creating vsphere resources",
          "link": "https://pypi.org/project/pulumi-vsphere/4.17.0a1773211970/",
          "published": "Wed, 11 Mar 2026 15:57:48 GMT",
          "published_parsed": [
            2026,
            3,
            11,
            15,
            57,
            48,
            2,
            70,
            0
          ],
          "updated": "Wed, 11 Mar 2026 15:57:48 GMT",
          "updated_parsed": [
            2026,
            3,
            11,
            15,
            57,
            48,
            2,
            70,
            0
          ],
          "guid": ""
        }
      },
      {
        "source": "pypi_recent_updates",
        "id": "d403bfd8021a90d81c3429f176a5e987",
        "url": "https://pypi.org/project/pulumi-awsx/3.4.0a1773209735/",
        "published_at": "2026-03-11T15:57:47Z",
        "updated_at": "2026-03-11T15:57:47Z",
        "headline": "pulumi-awsx 3.4.0a1773209735",
        "content": {
          "excerpt_text": "Pulumi Amazon Web Services (AWS) AWSX Components.",
          "lang": "en"
        },
        "provenance": {
          "fetched_at": "2026-03-11T16:09:52Z",
          "evidence_urls": [
            "https://pypi.org/project/pulumi-awsx/3.4.0a1773209735/"
          ],
          "content_hash": "sha256:49552998c2d23b90eea537b801e71582b911556d3f9a1589038b4c527bb7f437"
        },
        "signals": {
          "release": {
            "version": "3.4.0",
            "provenance": {
              "method": "title_regex",
              "authority": "PyPI Recent Updates",
              "authority_url": "https://pypi.org",
              "evidence_url": "https://pypi.org/project/pulumi-awsx/3.4.0a1773209735/"
            }
          }
        },
        "source_payload": {
          "html": "Pulumi Amazon Web Services (AWS) AWSX Components.",
          "link": "https://pypi.org/project/pulumi-awsx/3.4.0a1773209735/",
          "published": "Wed, 11 Mar 2026 15:57:47 GMT",
          "published_parsed": [
            2026,
            3,
            11,
            15,
            57,
            47,
            2,
            70,
            0
          ],
          "updated": "Wed, 11 Mar 2026 15:57:47 GMT",
          "updated_parsed": [
            2026,
            3,
            11,
            15,
            57,
            47,
            2,
            70,
            0
          ],
          "guid": ""
        }
      },
      {
        "source": "pypi_recent_updates",
        "id": "215939a785dbcc90b20e69aaf2d32ba8",
        "url": "https://pypi.org/project/ai-stream-proxy-sdk/0.2.2/",
        "published_at": "2026-03-11T15:57:44Z",
        "updated_at": "2026-03-11T15:57:44Z",
        "headline": "ai-stream-proxy-sdk 0.2.2",
        "content": {
          "excerpt_text": "Sync and async Python SDK for the Pantheon stream-proxy service.",
          "lang": "en"
        },
        "provenance": {
          "fetched_at": "2026-03-11T16:09:52Z",
          "evidence_urls": [
            "https://pypi.org/project/ai-stream-proxy-sdk/0.2.2/"
          ],
          "content_hash": "sha256:01fc2680e46ed286242d6f778c3d332788105f7e6e93ea993d964522b4c5b3c3"
        },
        "signals": {
          "release": {
            "version": "0.2.2",
            "provenance": {
              "method": "title_regex",
              "authority": "PyPI Recent Updates",
              "authority_url": "https://pypi.org",
              "evidence_url": "https://pypi.org/project/ai-stream-proxy-sdk/0.2.2/"
            }
          }
        },
        "source_payload": {
          "html": "Sync and async Python SDK for the Pantheon stream-proxy service.",
          "link": "https://pypi.org/project/ai-stream-proxy-sdk/0.2.2/",
          "published": "Wed, 11 Mar 2026 15:57:44 GMT",
          "published_parsed": [
            2026,
            3,
            11,
            15,
            57,
            44,
            2,
            70,
            0
          ],
          "updated": "Wed, 11 Mar 2026 15:57:44 GMT",
          "updated_parsed": [
            2026,
            3,
            11,
            15,
            57,
            44,
            2,
            70,
            0
          ],
          "guid": ""
        }
      },
      {
        "source": "pypi_recent_updates",
        "id": "aaa329f65da47d73f5f942b31c7520c8",
        "url": "https://pypi.org/project/pulumi-github/6.13.0a1773208875/",
        "published_at": "2026-03-11T15:57:42Z",
        "updated_at": "2026-03-11T15:57:42Z",
        "headline": "pulumi-github 6.13.0a1773208875",
        "content": {
          "excerpt_text": "A Pulumi package for creating and managing github cloud resources.",
          "lang": "en"
        },
        "provenance": {
          "fetched_at": "2026-03-11T16:09:52Z",
          "evidence_urls": [
            "https://pypi.org/project/pulumi-github/6.13.0a1773208875/"
          ],
          "content_hash": "sha256:1c11186641dd6c92d939f9135a9d440ca0ab52a303c6a8dcd579ece136db1fa4"
        },
        "signals": {
          "release": {
            "version": "6.13.0",
            "provenance": {
              "method": "title_regex",
              "authority": "PyPI Recent Updates",
              "authority_url": "https://pypi.org",
              "evidence_url": "https://pypi.org/project/pulumi-github/6.13.0a1773208875/"
            }
          }
        },
        "source_payload": {
          "html": "A Pulumi package for creating and managing github cloud resources.",
          "link": "https://pypi.org/project/pulumi-github/6.13.0a1773208875/",
          "published": "Wed, 11 Mar 2026 15:57:42 GMT",
          "published_parsed": [
            2026,
            3,
            11,
            15,
            57,
            42,
            2,
            70,
            0
          ],
          "updated": "Wed, 11 Mar 2026 15:57:42 GMT",
          "updated_parsed": [
            2026,
            3,
            11,
            15,
            57,
            42,
            2,
            70,
            0
          ],
          "guid": ""
        }
      },
      {
        "source": "pypi_recent_updates",
        "id": "45fb719404760a5906a6cb16b8f3d097",
        "url": "https://pypi.org/project/pulumi-terraform/6.1.0a1773211769/",
        "published_at": "2026-03-11T15:57:38Z",
        "updated_at": "2026-03-11T15:57:38Z",
        "headline": "pulumi-terraform 6.1.0a1773211769",
        "content": {
          "excerpt_text": "The Terraform provider for Pulumi lets you consume the outputs contained in Terraform state from your Pulumi programs.",
          "lang": "en"
        },
        "provenance": {
          "fetched_at": "2026-03-11T16:09:52Z",
          "evidence_urls": [
            "https://pypi.org/project/pulumi-terraform/6.1.0a1773211769/"
          ],
          "content_hash": "sha256:cf8768db9f5f7ed3924cd13eb41260e5354903333526f0b90efb49134ea0c091"
        },
        "signals": {
          "release": {
            "version": "6.1.0",
            "provenance": {
              "method": "title_regex",
              "authority": "PyPI Recent Updates",
              "authority_url": "https://pypi.org",
              "evidence_url": "https://pypi.org/project/pulumi-terraform/6.1.0a1773211769/"
            }
          }
        },
        "source_payload": {
          "html": "The Terraform provider for Pulumi lets you consume the outputs contained in Terraform state from your Pulumi programs.",
          "link": "https://pypi.org/project/pulumi-terraform/6.1.0a1773211769/",
          "published": "Wed, 11 Mar 2026 15:57:38 GMT",
          "published_parsed": [
            2026,
            3,
            11,
            15,
            57,
            38,
            2,
            70,
            0
          ],
          "updated": "Wed, 11 Mar 2026 15:57:38 GMT",
          "updated_parsed": [
            2026,
            3,
            11,
            15,
            57,
            38,
            2,
            70,
            0
          ],
          "guid": ""
        }
      },
      {
        "source": "pypi_recent_updates",
        "id": "bbaafda3f5e8978f8767250f34fcf73f",
        "url": "https://pypi.org/project/pulumi-minio/1.0.0a1773209850/",
        "published_at": "2026-03-11T15:57:36Z",
        "updated_at": "2026-03-11T15:57:36Z",
        "headline": "pulumi-minio 1.0.0a1773209850",
        "content": {
          "excerpt_text": "A Pulumi package for creating and managing minio cloud resources.",
          "lang": "en"
        },
        "provenance": {
          "fetched_at": "2026-03-11T16:09:52Z",
          "evidence_urls": [
            "https://pypi.org/project/pulumi-minio/1.0.0a1773209850/"
          ],
          "content_hash": "sha256:f94184b1ee551d83a251cd66fe2931e7d8faa4dfa2fff04123eb0cb5619e4e28"
        },
        "signals": {
          "release": {
            "version": "1.0.0",
            "provenance": {
              "method": "title_regex",
              "authority": "PyPI Recent Updates",
              "authority_url": "https://pypi.org",
              "evidence_url": "https://pypi.org/project/pulumi-minio/1.0.0a1773209850/"
            }
          }
        },
        "source_payload": {
          "html": "A Pulumi package for creating and managing minio cloud resources.",
          "link": "https://pypi.org/project/pulumi-minio/1.0.0a1773209850/",
          "published": "Wed, 11 Mar 2026 15:57:36 GMT",
          "published_parsed": [
            2026,
            3,
            11,
            15,
            57,
            36,
            2,
            70,
            0
          ],
          "updated": "Wed, 11 Mar 2026 15:57:36 GMT",
          "updated_parsed": [
            2026,
            3,
            11,
            15,
            57,
            36,
            2,
            70,
            0
          ],
          "guid": ""
        }
      },
      {
        "source": "pypi_recent_updates",
        "id": "d5dbcc0d2e6a157767ebaac85f8ffcc5",
        "url": "https://pypi.org/project/pulumi-opsgenie/1.4.0a1773210690/",
        "published_at": "2026-03-11T15:57:35Z",
        "updated_at": "2026-03-11T15:57:35Z",
        "headline": "pulumi-opsgenie 1.4.0a1773210690",
        "content": {
          "excerpt_text": "A Pulumi package for creating and managing opsgenie cloud resources.",
          "lang": "en"
        },
        "provenance": {
          "fetched_at": "2026-03-11T16:09:52Z",
          "evidence_urls": [
            "https://pypi.org/project/pulumi-opsgenie/1.4.0a1773210690/"
          ],
          "content_hash": "sha256:0d5063a59f2924f782934626f00c4973f7e9343d2c67da89fcfe2636453a4a91"
        },
        "signals": {
          "release": {
            "version": "1.4.0",
            "provenance": {
              "method": "title_regex",
              "authority": "PyPI Recent Updates",
              "authority_url": "https://pypi.org",
              "evidence_url": "https://pypi.org/project/pulumi-opsgenie/1.4.0a1773210690/"
            }
          }
        },
        "source_payload": {
          "html": "A Pulumi package for creating and managing opsgenie cloud resources.",
          "link": "https://pypi.org/project/pulumi-opsgenie/1.4.0a1773210690/",
          "published": "Wed, 11 Mar 2026 15:57:35 GMT",
          "published_parsed": [
            2026,
            3,
            11,
            15,
            57,
            35,
            2,
            70,
            0
          ],
          "updated": "Wed, 11 Mar 2026 15:57:35 GMT",
          "updated_parsed": [
            2026,
            3,
            11,
            15,
            57,
            35,
            2,
            70,
            0
          ],
          "guid": ""
        }
      },
      {
        "source": "pypi_recent_updates",
        "id": "cb6df66cbc4f8d5c39c39aee0987381c",
        "url": "https://pypi.org/project/pulumi-spotinst/3.129.0a1773211574/",
        "published_at": "2026-03-11T15:57:35Z",
        "updated_at": "2026-03-11T15:57:35Z",
        "headline": "pulumi-spotinst 3.129.0a1773211574",
        "content": {
          "excerpt_text": "A Pulumi package for creating and managing spotinst cloud resources.",
          "lang": "en"
        },
        "provenance": {
          "fetched_at": "2026-03-11T16:09:52Z",
          "evidence_urls": [
            "https://pypi.org/project/pulumi-spotinst/3.129.0a1773211574/"
          ],
          "content_hash": "sha256:ac75abc01a248ddfe3244978a76d2731d17e0705e4753383a6326c391cdd1d15"
        },
        "signals": {
          "release": {
            "version": "3.129.0",
            "provenance": {
              "method": "title_regex",
              "authority": "PyPI Recent Updates",
              "authority_url": "https://pypi.org",
              "evidence_url": "https://pypi.org/project/pulumi-spotinst/3.129.0a1773211574/"
            }
          }
        },
        "source_payload": {
          "html": "A Pulumi package for creating and managing spotinst cloud resources.",
          "link": "https://pypi.org/project/pulumi-spotinst/3.129.0a1773211574/",
          "published": "Wed, 11 Mar 2026 15:57:35 GMT",
          "published_parsed": [
            2026,
            3,
            11,
            15,
            57,
            35,
            2,
            70,
            0
          ],
          "updated": "Wed, 11 Mar 2026 15:57:35 GMT",
          "updated_parsed": [
            2026,
            3,
            11,
            15,
            57,
            35,
            2,
            70,
            0
          ],
          "guid": ""
        }
      },
      {
        "source": "pypi_recent_updates",
        "id": "6813e9c4ef3486386ef4edaf7cc9aebf",
        "url": "https://pypi.org/project/pulumi-docker/4.12.0a1773208743/",
        "published_at": "2026-03-11T15:57:28Z",
        "updated_at": "2026-03-11T15:57:28Z",
        "headline": "pulumi-docker 4.12.0a1773208743",
        "content": {
          "excerpt_text": "A Pulumi package for interacting with Docker in Pulumi programs",
          "lang": "en"
        },
        "provenance": {
          "fetched_at": "2026-03-11T16:09:52Z",
          "evidence_urls": [
            "https://pypi.org/project/pulumi-docker/4.12.0a1773208743/"
          ],
          "content_hash": "sha256:1b23809b2367ce2b5114ed53f7404b312b2c30c2bce0cd7254f90b1e54ddce56"
        },
        "signals": {
          "release": {
            "version": "4.12.0",
            "provenance": {
              "method": "title_regex",
              "authority": "PyPI Recent Updates",
              "authority_url": "https://pypi.org",
              "evidence_url": "https://pypi.org/project/pulumi-docker/4.12.0a1773208743/"
            }
          }
        },
        "source_payload": {
          "html": "A Pulumi package for interacting with Docker in Pulumi programs",
          "link": "https://pypi.org/project/pulumi-docker/4.12.0a1773208743/",
          "published": "Wed, 11 Mar 2026 15:57:28 GMT",
          "published_parsed": [
            2026,
            3,
            11,
            15,
            57,
            28,
            2,
            70,
            0
          ],
          "updated": "Wed, 11 Mar 2026 15:57:28 GMT",
          "updated_parsed": [
            2026,
            3,
            11,
            15,
            57,
            28,
            2,
            70,
            0
          ],
          "guid": ""
        }
      },
      {
        "source": "pypi_recent_updates",
        "id": "038a9a743be1ec6dacbfc5c95072d22e",
        "url": "https://pypi.org/project/pulumi-consul/3.15.0a1773208003/",
        "published_at": "2026-03-11T15:57:27Z",
        "updated_at": "2026-03-11T15:57:27Z",
        "headline": "pulumi-consul 3.15.0a1773208003",
        "content": {
          "excerpt_text": "A Pulumi package for creating and managing consul resources.",
          "lang": "en"
        },
        "provenance": {
          "fetched_at": "2026-03-11T16:09:52Z",
          "evidence_urls": [
            "https://pypi.org/project/pulumi-consul/3.15.0a1773208003/"
          ],
          "content_hash": "sha256:69b1cd4a2aed3d5a92b7dbf8981b28ea99f5a11f8a431e34c8c9e7bc4c8a8baf"
        },
        "signals": {
          "release": {
            "version": "3.15.0",
            "provenance": {
              "method": "title_regex",
              "authority": "PyPI Recent Updates",
              "authority_url": "https://pypi.org",
              "evidence_url": "https://pypi.org/project/pulumi-consul/3.15.0a1773208003/"
            }
          }
        },
        "source_payload": {
          "html": "A Pulumi package for creating and managing consul resources.",
          "link": "https://pypi.org/project/pulumi-consul/3.15.0a1773208003/",
          "published": "Wed, 11 Mar 2026 15:57:27 GMT",
          "published_parsed": [
            2026,
            3,
            11,
            15,
            57,
            27,
            2,
            70,
            0
          ],
          "updated": "Wed, 11 Mar 2026 15:57:27 GMT",
          "updated_parsed": [
            2026,
            3,
            11,
            15,
            57,
            27,
            2,
            70,
            0
          ],
          "guid": ""
        }
      },
      {
        "source": "pypi_recent_updates",
        "id": "9fd6c159754f690936a8cb7c2c08f192",
        "url": "https://pypi.org/project/pulumi-archive/0.4.0a1773206858/",
        "published_at": "2026-03-11T15:57:25Z",
        "updated_at": "2026-03-11T15:57:25Z",
        "headline": "pulumi-archive 0.4.0a1773206858",
        "content": {
          "excerpt_text": "A Pulumi package for creating and managing Archive cloud resources.",
          "lang": "en"
        },
        "provenance": {
          "fetched_at": "2026-03-11T16:09:52Z",
          "evidence_urls": [
            "https://pypi.org/project/pulumi-archive/0.4.0a1773206858/"
          ],
          "content_hash": "sha256:2ebd8b14e2eb72e8a8f1fd487348f098fae9b8ab4bf87b40418bef614bdca3c4"
        },
        "signals": {
          "release": {
            "version": "0.4.0",
            "prerelease": true,
            "provenance": {
              "method": "title_regex",
              "authority": "PyPI Recent Updates",
              "authority_url": "https://pypi.org",
              "evidence_url": "https://pypi.org/project/pulumi-archive/0.4.0a1773206858/"
            }
          }
        },
        "source_payload": {
          "html": "A Pulumi package for creating and managing Archive cloud resources.",
          "link": "https://pypi.org/project/pulumi-archive/0.4.0a1773206858/",
          "published": "Wed, 11 Mar 2026 15:57:25 GMT",
          "published_parsed": [
            2026,
            3,
            11,
            15,
            57,
            25,
            2,
            70,
            0
          ],
          "updated": "Wed, 11 Mar 2026 15:57:25 GMT",
          "updated_parsed": [
            2026,
            3,
            11,
            15,
            57,
            25,
            2,
            70,
            0
          ],
          "guid": ""
        }
      },
      {
        "source": "pypi_recent_updates",
        "id": "d93ef4542705760d4af0813b81d538be",
        "url": "https://pypi.org/project/ragy/0.1.2/",
        "published_at": "2026-03-11T15:57:25Z",
        "updated_at": "2026-03-11T15:57:25Z",
        "headline": "ragy 0.1.2",
        "content": {
          "excerpt_text": "A simple RAG (Retrieval-Augmented Generation) framework for Python.",
          "lang": "en"
        },
        "provenance": {
          "fetched_at": "2026-03-11T16:09:52Z",
          "evidence_urls": [
            "https://pypi.org/project/ragy/0.1.2/"
          ],
          "content_hash": "sha256:a9bea5b11e9a2f2ee9e1258da6c0d2aa87416bb105e0eecec8ed91f58f0e60f9"
        },
        "signals": {
          "release": {
            "version": "0.1.2",
            "provenance": {
              "method": "title_regex",
              "authority": "PyPI Recent Updates",
              "authority_url": "https://pypi.org",
              "evidence_url": "https://pypi.org/project/ragy/0.1.2/"
            }
          }
        },
        "source_payload": {
          "html": "A simple RAG (Retrieval-Augmented Generation) framework for Python.",
          "link": "https://pypi.org/project/ragy/0.1.2/",
          "published": "Wed, 11 Mar 2026 15:57:25 GMT",
          "published_parsed": [
            2026,
            3,
            11,
            15,
            57,
            25,
            2,
            70,
            0
          ],
          "updated": "Wed, 11 Mar 2026 15:57:25 GMT",
          "updated_parsed": [
            2026,
            3,
            11,
            15,
            57,
            25,
            2,
            70,
            0
          ],
          "guid": ""
        }
      },
      {
        "source": "pypi_recent_updates",
        "id": "bb1deaeee1d1f0081ed7ee8c05f5f117",
        "url": "https://pypi.org/project/pulumi-azuread/6.9.0a1773207688/",
        "published_at": "2026-03-11T15:57:21Z",
        "updated_at": "2026-03-11T15:57:21Z",
        "headline": "pulumi-azuread 6.9.0a1773207688",
        "content": {
          "excerpt_text": "A Pulumi package for creating and managing Azure Active Directory (Azure AD) cloud resources.",
          "lang": "en"
        },
        "provenance": {
          "fetched_at": "2026-03-11T16:09:52Z",
          "evidence_urls": [
            "https://pypi.org/project/pulumi-azuread/6.9.0a1773207688/"
          ],
          "content_hash": "sha256:0953ba812e7c73ec9b42ae66fd9b25946acd50325e69970f7501254187afe46f"
        },
        "signals": {
          "release": {
            "version": "6.9.0",
            "provenance": {
              "method": "title_regex",
              "authority": "PyPI Recent Updates",
              "authority_url": "https://pypi.org",
              "evidence_url": "https://pypi.org/project/pulumi-azuread/6.9.0a1773207688/"
            }
          }
        },
        "source_payload": {
          "html": "A Pulumi package for creating and managing Azure Active Directory (Azure AD) cloud resources.",
          "link": "https://pypi.org/project/pulumi-azuread/6.9.0a1773207688/",
          "published": "Wed, 11 Mar 2026 15:57:21 GMT",
          "published_parsed": [
            2026,
            3,
            11,
            15,
            57,
            21,
            2,
            70,
            0
          ],
          "updated": "Wed, 11 Mar 2026 15:57:21 GMT",
          "updated_parsed": [
            2026,
            3,
            11,
            15,
            57,
            21,
            2,
            70,
            0
          ],
          "guid": ""
        }
      },
      {
        "source": "pypi_recent_updates",
        "id": "1e1c9f7d4ae8fed95d9dd7385708327b",
        "url": "https://pypi.org/project/pulumi-fastly/11.4.2a1773201669/",
        "published_at": "2026-03-11T15:57:17Z",
        "updated_at": "2026-03-11T15:57:17Z",
        "headline": "pulumi-fastly 11.4.2a1773201669",
        "content": {
          "excerpt_text": "A Pulumi package for creating and managing fastly cloud resources.",
          "lang": "en"
        },
        "provenance": {
          "fetched_at": "2026-03-11T16:09:52Z",
          "evidence_urls": [
            "https://pypi.org/project/pulumi-fastly/11.4.2a1773201669/"
          ],
          "content_hash": "sha256:a6ad510af2deccd40631a4a667dd5012ff1038f1d103473eada27266f49a9ed1"
        },
        "signals": {
          "release": {
            "version": "11.4.2",
            "provenance": {
              "method": "title_regex",
              "authority": "PyPI Recent Updates",
              "authority_url": "https://pypi.org",
              "evidence_url": "https://pypi.org/project/pulumi-fastly/11.4.2a1773201669/"
            }
          }
        },
        "source_payload": {
          "html": "A Pulumi package for creating and managing fastly cloud resources.",
          "link": "https://pypi.org/project/pulumi-fastly/11.4.2a1773201669/",
          "published": "Wed, 11 Mar 2026 15:57:17 GMT",
          "published_parsed": [
            2026,
            3,
            11,
            15,
            57,
            17,
            2,
            70,
            0
          ],
          "updated": "Wed, 11 Mar 2026 15:57:17 GMT",
          "updated_parsed": [
            2026,
            3,
            11,
            15,
            57,
            17,
            2,
            70,
            0
          ],
          "guid": ""
        }
      },
      {
        "source": "pypi_recent_updates",
        "id": "60f0d3d2c7ca0e2a57b3910e5a03d5f5",
        "url": "https://pypi.org/project/pulumi-digitalocean/4.62.0a1773208580/",
        "published_at": "2026-03-11T15:57:14Z",
        "updated_at": "2026-03-11T15:57:14Z",
        "headline": "pulumi-digitalocean 4.62.0a1773208580",
        "content": {
          "excerpt_text": "A Pulumi package for creating and managing DigitalOcean cloud resources.",
          "lang": "en"
        },
        "provenance": {
          "fetched_at": "2026-03-11T16:09:52Z",
          "evidence_urls": [
            "https://pypi.org/project/pulumi-digitalocean/4.62.0a1773208580/"
          ],
          "content_hash": "sha256:3f6fe0f7d136d976d718fc7761a82348da76cafa59e2e2617af942f10ab0cb50"
        },
        "signals": {
          "release": {
            "version": "4.62.0",
            "provenance": {
              "method": "title_regex",
              "authority": "PyPI Recent Updates",
              "authority_url": "https://pypi.org",
              "evidence_url": "https://pypi.org/project/pulumi-digitalocean/4.62.0a1773208580/"
            }
          }
        },
        "source_payload": {
          "html": "A Pulumi package for creating and managing DigitalOcean cloud resources.",
          "link": "https://pypi.org/project/pulumi-digitalocean/4.62.0a1773208580/",
          "published": "Wed, 11 Mar 2026 15:57:14 GMT",
          "published_parsed": [
            2026,
            3,
            11,
            15,
            57,
            14,
            2,
            70,
            0
          ],
          "updated": "Wed, 11 Mar 2026 15:57:14 GMT",
          "updated_parsed": [
            2026,
            3,
            11,
            15,
            57,
            14,
            2,
            70,
            0
          ],
          "guid": ""
        }
      },
      {
        "source": "pypi_recent_updates",
        "id": "5239c81cb4c3125d1cd204fa9ec30be4",
        "url": "https://pypi.org/project/pulumi-harness/0.12.0a1773209116/",
        "published_at": "2026-03-11T15:57:12Z",
        "updated_at": "2026-03-11T15:57:12Z",
        "headline": "pulumi-harness 0.12.0a1773209116",
        "content": {
          "excerpt_text": "A Pulumi package for creating and managing Harness resources.",
          "lang": "en"
        },
        "provenance": {
          "fetched_at": "2026-03-11T16:09:52Z",
          "evidence_urls": [
            "https://pypi.org/project/pulumi-harness/0.12.0a1773209116/"
          ],
          "content_hash": "sha256:a1c348afce4f29225cbbf4c50905fe981f52a6796bf3e792cdfd32478cc4ba7e"
        },
        "signals": {
          "release": {
            "version": "0.12.0",
            "provenance": {
              "method": "title_regex",
              "authority": "PyPI Recent Updates",
              "authority_url": "https://pypi.org",
              "evidence_url": "https://pypi.org/project/pulumi-harness/0.12.0a1773209116/"
            }
          }
        },
        "source_payload": {
          "html": "A Pulumi package for creating and managing Harness  resources.",
          "link": "https://pypi.org/project/pulumi-harness/0.12.0a1773209116/",
          "published": "Wed, 11 Mar 2026 15:57:12 GMT",
          "published_parsed": [
            2026,
            3,
            11,
            15,
            57,
            12,
            2,
            70,
            0
          ],
          "updated": "Wed, 11 Mar 2026 15:57:12 GMT",
          "updated_parsed": [
            2026,
            3,
            11,
            15,
            57,
            12,
            2,
            70,
            0
          ],
          "guid": ""
        }
      },
      {
        "source": "pypi_recent_updates",
        "id": "f1b9a69fd84ea4d3022a3c170a7cbcdc",
        "url": "https://pypi.org/project/pulumi-mailgun/3.8.0a1773209678/",
        "published_at": "2026-03-11T15:57:09Z",
        "updated_at": "2026-03-11T15:57:09Z",
        "headline": "pulumi-mailgun 3.8.0a1773209678",
        "content": {
          "excerpt_text": "A Pulumi package for creating and managing Mailgun resources.",
          "lang": "en"
        },
        "provenance": {
          "fetched_at": "2026-03-11T16:09:52Z",
          "evidence_urls": [
            "https://pypi.org/project/pulumi-mailgun/3.8.0a1773209678/"
          ],
          "content_hash": "sha256:e920d551506df28564d6591ea9f0135800613874fde2f8f205871608f44ce9b2"
        },
        "signals": {
          "release": {
            "version": "3.8.0",
            "provenance": {
              "method": "title_regex",
              "authority": "PyPI Recent Updates",
              "authority_url": "https://pypi.org",
              "evidence_url": "https://pypi.org/project/pulumi-mailgun/3.8.0a1773209678/"
            }
          }
        },
        "source_payload": {
          "html": "A Pulumi package for creating and managing Mailgun resources.",
          "link": "https://pypi.org/project/pulumi-mailgun/3.8.0a1773209678/",
          "published": "Wed, 11 Mar 2026 15:57:09 GMT",
          "published_parsed": [
            2026,
            3,
            11,
            15,
            57,
            9,
            2,
            70,
            0
          ],
          "updated": "Wed, 11 Mar 2026 15:57:09 GMT",
          "updated_parsed": [
            2026,
            3,
            11,
            15,
            57,
            9,
            2,
            70,
            0
          ],
          "guid": ""
        }
      },
      {
        "source": "pypi_recent_updates",
        "id": "e21ef091e21d12064d14aa97a0edaed2",
        "url": "https://pypi.org/project/pulumi-aiven/6.51.0a1773206706/",
        "published_at": "2026-03-11T15:57:09Z",
        "updated_at": "2026-03-11T15:57:09Z",
        "headline": "pulumi-aiven 6.51.0a1773206706",
        "content": {
          "excerpt_text": "A Pulumi package for creating and managing Aiven cloud resources.",
          "lang": "en"
        },
        "provenance": {
          "fetched_at": "2026-03-11T16:09:52Z",
          "evidence_urls": [
            "https://pypi.org/project/pulumi-aiven/6.51.0a1773206706/"
          ],
          "content_hash": "sha256:e0c981cd5837224391ca3747921c61564e66857dc6b639057dbb1e6b3aade3e5"
        },
        "signals": {
          "release": {
            "version": "6.51.0",
            "provenance": {
              "method": "title_regex",
              "authority": "PyPI Recent Updates",
              "authority_url": "https://pypi.org",
              "evidence_url": "https://pypi.org/project/pulumi-aiven/6.51.0a1773206706/"
            }
          }
        },
        "source_payload": {
          "html": "A Pulumi package for creating and managing Aiven cloud resources.",
          "link": "https://pypi.org/project/pulumi-aiven/6.51.0a1773206706/",
          "published": "Wed, 11 Mar 2026 15:57:09 GMT",
          "published_parsed": [
            2026,
            3,
            11,
            15,
            57,
            9,
            2,
            70,
            0
          ],
          "updated": "Wed, 11 Mar 2026 15:57:09 GMT",
          "updated_parsed": [
            2026,
            3,
            11,
            15,
            57,
            9,
            2,
            70,
            0
          ],
          "guid": ""
        }
      },
      {
        "source": "pypi_recent_updates",
        "id": "6f09df086880686ed4d770be36196393",
        "url": "https://pypi.org/project/pulumi-aws-native/1.58.0a1773208625/",
        "published_at": "2026-03-11T15:57:07Z",
        "updated_at": "2026-03-11T15:57:07Z",
        "headline": "pulumi-aws-native 1.58.0a1773208625",
        "content": {
          "excerpt_text": "A native Pulumi package for creating and managing Amazon Web Services (AWS) resources.",
          "lang": "en"
        },
        "provenance": {
          "fetched_at": "2026-03-11T16:09:52Z",
          "evidence_urls": [
            "https://pypi.org/project/pulumi-aws-native/1.58.0a1773208625/"
          ],
          "content_hash": "sha256:6306280990dde3f289a4da79c761be1d03ba3315d32efc90ffd0e415071b9ecf"
        },
        "signals": {
          "release": {
            "version": "1.58.0",
            "provenance": {
              "method": "title_regex",
              "authority": "PyPI Recent Updates",
              "authority_url": "https://pypi.org",
              "evidence_url": "https://pypi.org/project/pulumi-aws-native/1.58.0a1773208625/"
            }
          }
        },
        "source_payload": {
          "html": "A native Pulumi package for creating and managing Amazon Web Services (AWS) resources.",
          "link": "https://pypi.org/project/pulumi-aws-native/1.58.0a1773208625/",
          "published": "Wed, 11 Mar 2026 15:57:07 GMT",
          "published_parsed": [
            2026,
            3,
            11,
            15,
            57,
            7,
            2,
            70,
            0
          ],
          "updated": "Wed, 11 Mar 2026 15:57:07 GMT",
          "updated_parsed": [
            2026,
            3,
            11,
            15,
            57,
            7,
            2,
            70,
            0
          ],
          "guid": ""
        }
      },
      {
        "source": "pypi_recent_updates",
        "id": "6ab68d023f4f27b55d9fb0bdb19ee166",
        "url": "https://pypi.org/project/base-api-utils/1.1.89/",
        "published_at": "2026-03-11T15:57:07Z",
        "updated_at": "2026-03-11T15:57:07Z",
        "headline": "base-api-utils 1.1.89",
        "content": {
          "excerpt_text": "Django Rest Framework micro services common utilities",
          "lang": "en"
        },
        "provenance": {
          "fetched_at": "2026-03-11T16:09:52Z",
          "evidence_urls": [
            "https://pypi.org/project/base-api-utils/1.1.89/"
          ],
          "content_hash": "sha256:d88b5f70609259aa84930cfab1c8fcfbdd83a4dc4c4f945cc2fa94c78167d835"
        },
        "signals": {
          "release": {
            "version": "1.1.89",
            "provenance": {
              "method": "title_regex",
              "authority": "PyPI Recent Updates",
              "authority_url": "https://pypi.org",
              "evidence_url": "https://pypi.org/project/base-api-utils/1.1.89/"
            }
          }
        },
        "source_payload": {
          "html": "Django Rest Framework micro services common utilities",
          "link": "https://pypi.org/project/base-api-utils/1.1.89/",
          "published": "Wed, 11 Mar 2026 15:57:07 GMT",
          "published_parsed": [
            2026,
            3,
            11,
            15,
            57,
            7,
            2,
            70,
            0
          ],
          "updated": "Wed, 11 Mar 2026 15:57:07 GMT",
          "updated_parsed": [
            2026,
            3,
            11,
            15,
            57,
            7,
            2,
            70,
            0
          ],
          "guid": ""
        }
      },
      {
        "source": "pypi_recent_updates",
        "id": "a398370ed567d13200f56dcaf06a19d0",
        "url": "https://pypi.org/project/airbyte-source-google-ads/4.1.6.dev202603111557/",
        "published_at": "2026-03-11T15:57:07Z",
        "updated_at": "2026-03-11T15:57:07Z",
        "headline": "airbyte-source-google-ads 4.1.6.dev202603111557",
        "content": {
          "excerpt_text": "Source implementation for Google Ads.",
          "lang": "en"
        },
        "provenance": {
          "fetched_at": "2026-03-11T16:09:52Z",
          "evidence_urls": [
            "https://pypi.org/project/airbyte-source-google-ads/4.1.6.dev202603111557/"
          ],
          "content_hash": "sha256:63f6b0e7655f2a92535b10c86968cdb7391ebbb521fe0ad651477c7f557b2b08"
        },
        "signals": {
          "release": {
            "version": "4.1.6.dev202603111557",
            "prerelease": true,
            "provenance": {
              "method": "title_regex",
              "authority": "PyPI Recent Updates",
              "authority_url": "https://pypi.org",
              "evidence_url": "https://pypi.org/project/airbyte-source-google-ads/4.1.6.dev202603111557/"
            }
          }
        },
        "source_payload": {
          "html": "Source implementation for Google Ads.",
          "link": "https://pypi.org/project/airbyte-source-google-ads/4.1.6.dev202603111557/",
          "published": "Wed, 11 Mar 2026 15:57:07 GMT",
          "published_parsed": [
            2026,
            3,
            11,
            15,
            57,
            7,
            2,
            70,
            0
          ],
          "updated": "Wed, 11 Mar 2026 15:57:07 GMT",
          "updated_parsed": [
            2026,
            3,
            11,
            15,
            57,
            7,
            2,
            70,
            0
          ],
          "guid": ""
        }
      },
      {
        "source": "pypi_recent_updates",
        "id": "f2cdc085fe417d82cca00daa01cde22b",
        "url": "https://pypi.org/project/api-zen/0.1.1/",
        "published_at": "2026-03-11T15:57:05Z",
        "updated_at": "2026-03-11T15:57:05Z",
        "headline": "api-zen 0.1.1",
        "content": {
          "excerpt_text": "Uma biblioteca Python moderna, leve e resiliente para simplificar a interação com APIs REST.",
          "lang": "en"
        },
        "provenance": {
          "fetched_at": "2026-03-11T16:09:52Z",
          "evidence_urls": [
            "https://pypi.org/project/api-zen/0.1.1/"
          ],
          "content_hash": "sha256:60f4eeb9beee1018fcd2603ad6f01d3d95faf6f5c6d5528c20d5cdda583ee102"
        },
        "signals": {
          "release": {
            "version": "0.1.1",
            "provenance": {
              "method": "title_regex",
              "authority": "PyPI Recent Updates",
              "authority_url": "https://pypi.org",
              "evidence_url": "https://pypi.org/project/api-zen/0.1.1/"
            }
          }
        },
        "source_payload": {
          "html": "Uma biblioteca Python moderna, leve e resiliente para simplificar a interação com APIs REST.",
          "link": "https://pypi.org/project/api-zen/0.1.1/",
          "published": "Wed, 11 Mar 2026 15:57:05 GMT",
          "published_parsed": [
            2026,
            3,
            11,
            15,
            57,
            5,
            2,
            70,
            0
          ],
          "updated": "Wed, 11 Mar 2026 15:57:05 GMT",
          "updated_parsed": [
            2026,
            3,
            11,
            15,
            57,
            5,
            2,
            70,
            0
          ],
          "guid": ""
        }
      },
      {
        "source": "pypi_recent_updates",
        "id": "2967a330fcf91c67d4f6c51af65e3f1b",
        "url": "https://pypi.org/project/pulumi-command/1.3.0a1773208401/",
        "published_at": "2026-03-11T15:57:04Z",
        "updated_at": "2026-03-11T15:57:04Z",
        "headline": "pulumi-command 1.3.0a1773208401",
        "content": {
          "excerpt_text": "The Pulumi Command Provider enables you to execute commands and scripts either locally or remotely as part of the Pulumi resource model.",
          "lang": "en"
        },
        "provenance": {
          "fetched_at": "2026-03-11T16:09:52Z",
          "evidence_urls": [
            "https://pypi.org/project/pulumi-command/1.3.0a1773208401/"
          ],
          "content_hash": "sha256:cd3217eeb33b77cc55e7aec42c6dd8b085f48e64fdbb530813174a90054788a3"
        },
        "signals": {
          "release": {
            "version": "1.3.0",
            "provenance": {
              "method": "title_regex",
              "authority": "PyPI Recent Updates",
              "authority_url": "https://pypi.org",
              "evidence_url": "https://pypi.org/project/pulumi-command/1.3.0a1773208401/"
            }
          }
        },
        "source_payload": {
          "html": "The Pulumi Command Provider enables you to execute commands and scripts either locally or remotely as part of the Pulumi resource model.",
          "link": "https://pypi.org/project/pulumi-command/1.3.0a1773208401/",
          "published": "Wed, 11 Mar 2026 15:57:04 GMT",
          "published_parsed": [
            2026,
            3,
            11,
            15,
            57,
            4,
            2,
            70,
            0
          ],
          "updated": "Wed, 11 Mar 2026 15:57:04 GMT",
          "updated_parsed": [
            2026,
            3,
            11,
            15,
            57,
            4,
            2,
            70,
            0
          ],
          "guid": ""
        }
      },
      {
        "source": "pypi_recent_updates",
        "id": "ec9a18c6cef47b2fc8417e8224b32fd0",
        "url": "https://pypi.org/project/pulumi-external/0.1.0a1773208507/",
        "published_at": "2026-03-11T15:57:03Z",
        "updated_at": "2026-03-11T15:57:03Z",
        "headline": "pulumi-external 0.1.0a1773208507",
        "content": {
          "excerpt_text": "A Pulumi package for creating and managing External cloud resources.",
          "lang": "en"
        },
        "provenance": {
          "fetched_at": "2026-03-11T16:09:52Z",
          "evidence_urls": [
            "https://pypi.org/project/pulumi-external/0.1.0a1773208507/"
          ],
          "content_hash": "sha256:119fe67c133a216c6be43646967c23adeca01037cfeb6fbb76d2e31b2c0c3f9a"
        },
        "signals": {
          "release": {
            "version": "0.1.0",
            "provenance": {
              "method": "title_regex",
              "authority": "PyPI Recent Updates",
              "authority_url": "https://pypi.org",
              "evidence_url": "https://pypi.org/project/pulumi-external/0.1.0a1773208507/"
            }
          }
        },
        "source_payload": {
          "html": "A Pulumi package for creating and managing External cloud resources.",
          "link": "https://pypi.org/project/pulumi-external/0.1.0a1773208507/",
          "published": "Wed, 11 Mar 2026 15:57:03 GMT",
          "published_parsed": [
            2026,
            3,
            11,
            15,
            57,
            3,
            2,
            70,
            0
          ],
          "updated": "Wed, 11 Mar 2026 15:57:03 GMT",
          "updated_parsed": [
            2026,
            3,
            11,
            15,
            57,
            3,
            2,
            70,
            0
          ],
          "guid": ""
        }
      },
      {
        "source": "pypi_recent_updates",
        "id": "a2abe3a83a71f8417e1d896c34838659",
        "url": "https://pypi.org/project/pulumi-ise/0.4.0a1773209111/",
        "published_at": "2026-03-11T15:57:03Z",
        "updated_at": "2026-03-11T15:57:03Z",
        "headline": "pulumi-ise 0.4.0a1773209111",
        "content": {
          "excerpt_text": "A Pulumi package for managing resources on a Cisco ISE (Identity Service Engine) instance.",
          "lang": "en"
        },
        "provenance": {
          "fetched_at": "2026-03-11T16:09:52Z",
          "evidence_urls": [
            "https://pypi.org/project/pulumi-ise/0.4.0a1773209111/"
          ],
          "content_hash": "sha256:598fda007880885606e4afc2bdd63c7044841b4bed9ca59a05030b11597b1111"
        },
        "signals": {
          "release": {
            "version": "0.4.0",
            "provenance": {
              "method": "title_regex",
              "authority": "PyPI Recent Updates",
              "authority_url": "https://pypi.org",
              "evidence_url": "https://pypi.org/project/pulumi-ise/0.4.0a1773209111/"
            }
          }
        },
        "source_payload": {
          "html": "A Pulumi package for managing resources on a Cisco ISE (Identity Service Engine) instance.",
          "link": "https://pypi.org/project/pulumi-ise/0.4.0a1773209111/",
          "published": "Wed, 11 Mar 2026 15:57:03 GMT",
          "published_parsed": [
            2026,
            3,
            11,
            15,
            57,
            3,
            2,
            70,
            0
          ],
          "updated": "Wed, 11 Mar 2026 15:57:03 GMT",
          "updated_parsed": [
            2026,
            3,
            11,
            15,
            57,
            3,
            2,
            70,
            0
          ],
          "guid": ""
        }
      }
    ],
    "updated": [],
    "removed": []
  },
  "counts": {
    "items": 40,
    "updated": 0,
    "removed": 0
  },
  "integrity_reset": false
}
