{
  "cursor": "sha256:77502fc19c5423f5792b1e4f372c15afdb7544719a1786f8c60bb72345d704ed",
  "prev_cursor": "sha256:bea12a2bd13b39a7d6e6a6c051a0b4028f98b6396fed2e9cc6a73e0f5ec8f1d7",
  "changed": true,
  "generated_at": "2026-03-14T09:23:31Z",
  "ttl_sec": 900,
  "latest_url": "/diff/latest.json",
  "digest_url": "/diff/digest.json",
  "counts": {
    "items": 70,
    "updated": 0,
    "removed": 0
  },
  "sources_checked": 43,
  "sources_ok": 43,
  "all_clear": false,
  "_protocol": {
    "standard": "ddv1",
    "spec": "/.well-known/diffdelta.json",
    "usage": "cursor SAME=no changes, STOP. counts.items>0→fetch latest_url. all_clear=verified silence. Schema guide in spec."
  },
  "freshness": {
    "oldest_data_age_sec": 2746523,
    "mean_data_age_sec": 62460,
    "stale_count": 0,
    "all_fresh": true
  }
}
