{
  "schema_version": "1.2.0",
  "generated_at": "2026-03-15T10:54:41Z",
  "source_id": "pypi_recent_updates",
  "hash": "sha256:ac306440aeba6b62e7bee264d68f449b74d951b21cea9e440242a38df9d3e251",
  "prev_hash": "sha256:03627f5c8ebc36f94de1dacd478247b6b35cc2ebbd668df0a5113589af3b3948",
  "cursor": "sha256:ff3cb7f2febd2502e9694bbf1d21a2c6d9f15a545f85a8a720665e94ccf99951",
  "prev_cursor": "sha256:6873c763806c5860e71796991bc3ae5e5042e6c50e28c0321beba996e31bec30",
  "changed": true,
  "ttl_sec": 1800,
  "sources_included": [
    "pypi_recent_updates"
  ],
  "batch_narrative": "pypi_recent_updates: 40 releases (39 stable, 1 pre-release).",
  "buckets": {
    "items": [
      {
        "source": "pypi_recent_updates",
        "id": "8ebaa0d4378194ee37395ce5f85ad4ef",
        "url": "https://pypi.org/project/pooch-rattler/0.1.0/",
        "published_at": "2026-03-15T10:54:31Z",
        "updated_at": "2026-03-15T10:54:31Z",
        "headline": "pooch-rattler 0.1.0",
        "content": {
          "excerpt_text": "Pooch downloader powered by Rattler",
          "lang": "en"
        },
        "provenance": {
          "fetched_at": "2026-03-15T10:54:41Z",
          "evidence_urls": [
            "https://pypi.org/project/pooch-rattler/0.1.0/"
          ],
          "content_hash": "sha256:8f3a9d56f6c72e75cdea938bf599459fbd48b75cb103fc9ed57a60b39e81cc29"
        },
        "signals": {
          "release": {
            "version": "0.1.0",
            "provenance": {
              "method": "title_regex",
              "authority": "PyPI Recent Updates",
              "authority_url": "https://pypi.org",
              "evidence_url": "https://pypi.org/project/pooch-rattler/0.1.0/"
            }
          }
        },
        "source_payload": {
          "html": "Pooch downloader powered by Rattler",
          "link": "https://pypi.org/project/pooch-rattler/0.1.0/",
          "published": "Sun, 15 Mar 2026 10:54:31 GMT",
          "published_parsed": [
            2026,
            3,
            15,
            10,
            54,
            31,
            6,
            74,
            0
          ],
          "updated": "Sun, 15 Mar 2026 10:54:31 GMT",
          "updated_parsed": [
            2026,
            3,
            15,
            10,
            54,
            31,
            6,
            74,
            0
          ],
          "guid": ""
        }
      },
      {
        "source": "pypi_recent_updates",
        "id": "96cefa0a5266f9a2ea1481529f184868",
        "url": "https://pypi.org/project/lore-sdk/1.0.0/",
        "published_at": "2026-03-15T10:54:11Z",
        "updated_at": "2026-03-15T10:54:11Z",
        "headline": "lore-sdk 1.0.0",
        "content": {
          "excerpt_text": "Cross-agent semantic memory with knowledge graphs, fact extraction, and MCP integration",
          "lang": "en"
        },
        "provenance": {
          "fetched_at": "2026-03-15T10:54:41Z",
          "evidence_urls": [
            "https://pypi.org/project/lore-sdk/1.0.0/"
          ],
          "content_hash": "sha256:fd0a5a8375270852a3d6fcdcbee02a58e98a126cc0e61e005b3c97c0a8d0de27"
        },
        "signals": {
          "release": {
            "version": "1.0.0",
            "provenance": {
              "method": "title_regex",
              "authority": "PyPI Recent Updates",
              "authority_url": "https://pypi.org",
              "evidence_url": "https://pypi.org/project/lore-sdk/1.0.0/"
            }
          }
        },
        "source_payload": {
          "html": "Cross-agent semantic memory with knowledge graphs, fact extraction, and MCP integration",
          "link": "https://pypi.org/project/lore-sdk/1.0.0/",
          "published": "Sun, 15 Mar 2026 10:54:11 GMT",
          "published_parsed": [
            2026,
            3,
            15,
            10,
            54,
            11,
            6,
            74,
            0
          ],
          "updated": "Sun, 15 Mar 2026 10:54:11 GMT",
          "updated_parsed": [
            2026,
            3,
            15,
            10,
            54,
            11,
            6,
            74,
            0
          ],
          "guid": ""
        }
      },
      {
        "source": "pypi_recent_updates",
        "id": "345d0ea9a8e4286ba4691583561f9d3e",
        "url": "https://pypi.org/project/dsxllm/0.1.4/",
        "published_at": "2026-03-15T10:54:04Z",
        "updated_at": "2026-03-15T10:54:04Z",
        "headline": "dsxllm 0.1.4",
        "content": {
          "excerpt_text": "动手学大语言模型依赖库",
          "lang": "en"
        },
        "provenance": {
          "fetched_at": "2026-03-15T10:54:41Z",
          "evidence_urls": [
            "https://pypi.org/project/dsxllm/0.1.4/"
          ],
          "content_hash": "sha256:23aea0a196ba58cc1db6f061ceeda64046cffa004a7c75338cb2884bc7cb22b0"
        },
        "signals": {
          "release": {
            "version": "0.1.4",
            "provenance": {
              "method": "title_regex",
              "authority": "PyPI Recent Updates",
              "authority_url": "https://pypi.org",
              "evidence_url": "https://pypi.org/project/dsxllm/0.1.4/"
            }
          }
        },
        "source_payload": {
          "html": "动手学大语言模型依赖库",
          "link": "https://pypi.org/project/dsxllm/0.1.4/",
          "published": "Sun, 15 Mar 2026 10:54:04 GMT",
          "published_parsed": [
            2026,
            3,
            15,
            10,
            54,
            4,
            6,
            74,
            0
          ],
          "updated": "Sun, 15 Mar 2026 10:54:04 GMT",
          "updated_parsed": [
            2026,
            3,
            15,
            10,
            54,
            4,
            6,
            74,
            0
          ],
          "guid": ""
        }
      },
      {
        "source": "pypi_recent_updates",
        "id": "c0e9c21a308360cb6c5f462bd56cb41c",
        "url": "https://pypi.org/project/largefile/0.2.0/",
        "published_at": "2026-03-15T10:53:44Z",
        "updated_at": "2026-03-15T10:53:44Z",
        "headline": "largefile 0.2.0",
        "content": {
          "excerpt_text": "MCP server for AI assistants to navigate, search, and edit large codebases, logs, and data files with semantic code analysis",
          "lang": "en"
        },
        "provenance": {
          "fetched_at": "2026-03-15T10:54:41Z",
          "evidence_urls": [
            "https://pypi.org/project/largefile/0.2.0/"
          ],
          "content_hash": "sha256:04afeca0614ff60f97f49767638a6ce53d9196ba9edc2d1f9ea34ae17f7ed080"
        },
        "signals": {
          "release": {
            "version": "0.2.0",
            "provenance": {
              "method": "title_regex",
              "authority": "PyPI Recent Updates",
              "authority_url": "https://pypi.org",
              "evidence_url": "https://pypi.org/project/largefile/0.2.0/"
            }
          }
        },
        "source_payload": {
          "html": "MCP server for AI assistants to navigate, search, and edit large codebases, logs, and data files with semantic code analysis",
          "link": "https://pypi.org/project/largefile/0.2.0/",
          "published": "Sun, 15 Mar 2026 10:53:44 GMT",
          "published_parsed": [
            2026,
            3,
            15,
            10,
            53,
            44,
            6,
            74,
            0
          ],
          "updated": "Sun, 15 Mar 2026 10:53:44 GMT",
          "updated_parsed": [
            2026,
            3,
            15,
            10,
            53,
            44,
            6,
            74,
            0
          ],
          "guid": ""
        }
      },
      {
        "source": "pypi_recent_updates",
        "id": "cd98cee6dd29b140b7c9839595de3c02",
        "url": "https://pypi.org/project/indonesia-civic-stack/0.2.0/",
        "published_at": "2026-03-15T10:53:41Z",
        "updated_at": "2026-03-15T10:53:41Z",
        "headline": "indonesia-civic-stack 0.2.0",
        "content": {
          "excerpt_text": "Python SDK + 40 MCP tools for 11 Indonesian government data portals",
          "lang": "en"
        },
        "provenance": {
          "fetched_at": "2026-03-15T10:54:41Z",
          "evidence_urls": [
            "https://pypi.org/project/indonesia-civic-stack/0.2.0/"
          ],
          "content_hash": "sha256:419a1c0a35caffbb0a144b64ca53983381bbcf8eb39455733444db84e096593c"
        },
        "signals": {
          "release": {
            "version": "0.2.0",
            "provenance": {
              "method": "title_regex",
              "authority": "PyPI Recent Updates",
              "authority_url": "https://pypi.org",
              "evidence_url": "https://pypi.org/project/indonesia-civic-stack/0.2.0/"
            }
          }
        },
        "source_payload": {
          "html": "Python SDK + 40 MCP tools for 11 Indonesian government data portals",
          "link": "https://pypi.org/project/indonesia-civic-stack/0.2.0/",
          "published": "Sun, 15 Mar 2026 10:53:41 GMT",
          "published_parsed": [
            2026,
            3,
            15,
            10,
            53,
            41,
            6,
            74,
            0
          ],
          "updated": "Sun, 15 Mar 2026 10:53:41 GMT",
          "updated_parsed": [
            2026,
            3,
            15,
            10,
            53,
            41,
            6,
            74,
            0
          ],
          "guid": ""
        }
      },
      {
        "source": "pypi_recent_updates",
        "id": "c5348b11b53362c89c439ad0f4c9cd3c",
        "url": "https://pypi.org/project/abx-pkg/0.7.0/",
        "published_at": "2026-03-15T10:53:35Z",
        "updated_at": "2026-03-15T10:53:35Z",
        "headline": "abx-pkg 0.7.0",
        "content": {
          "excerpt_text": "System package manager interfaces with Python type hints",
          "lang": "en"
        },
        "provenance": {
          "fetched_at": "2026-03-15T10:54:41Z",
          "evidence_urls": [
            "https://pypi.org/project/abx-pkg/0.7.0/"
          ],
          "content_hash": "sha256:af996b4c73c478a583d9451f41583b8d9d8ddb20e479246864ca1fd0412c10fd"
        },
        "signals": {
          "release": {
            "version": "0.7.0",
            "provenance": {
              "method": "title_regex",
              "authority": "PyPI Recent Updates",
              "authority_url": "https://pypi.org",
              "evidence_url": "https://pypi.org/project/abx-pkg/0.7.0/"
            }
          }
        },
        "source_payload": {
          "html": "System package manager interfaces with Python type hints",
          "link": "https://pypi.org/project/abx-pkg/0.7.0/",
          "published": "Sun, 15 Mar 2026 10:53:35 GMT",
          "published_parsed": [
            2026,
            3,
            15,
            10,
            53,
            35,
            6,
            74,
            0
          ],
          "updated": "Sun, 15 Mar 2026 10:53:35 GMT",
          "updated_parsed": [
            2026,
            3,
            15,
            10,
            53,
            35,
            6,
            74,
            0
          ],
          "guid": ""
        }
      },
      {
        "source": "pypi_recent_updates",
        "id": "dca28de9f5f6559069f66e40112d4adb",
        "url": "https://pypi.org/project/apyds/0.0.20/",
        "published_at": "2026-03-15T10:53:08Z",
        "updated_at": "2026-03-15T10:53:08Z",
        "headline": "apyds 0.0.20",
        "content": {
          "excerpt_text": "A deductive system",
          "lang": "en"
        },
        "provenance": {
          "fetched_at": "2026-03-15T10:54:41Z",
          "evidence_urls": [
            "https://pypi.org/project/apyds/0.0.20/"
          ],
          "content_hash": "sha256:af3d8cab146c94dbfe05b2d520fe4e0f81d8e12487729849752d42f02951e74c"
        },
        "signals": {
          "release": {
            "version": "0.0.20",
            "provenance": {
              "method": "title_regex",
              "authority": "PyPI Recent Updates",
              "authority_url": "https://pypi.org",
              "evidence_url": "https://pypi.org/project/apyds/0.0.20/"
            }
          }
        },
        "source_payload": {
          "html": "A deductive system",
          "link": "https://pypi.org/project/apyds/0.0.20/",
          "published": "Sun, 15 Mar 2026 10:53:08 GMT",
          "published_parsed": [
            2026,
            3,
            15,
            10,
            53,
            8,
            6,
            74,
            0
          ],
          "updated": "Sun, 15 Mar 2026 10:53:08 GMT",
          "updated_parsed": [
            2026,
            3,
            15,
            10,
            53,
            8,
            6,
            74,
            0
          ],
          "guid": ""
        }
      },
      {
        "source": "pypi_recent_updates",
        "id": "65bbfe8dfe6e5b95d8ce9dabc7a81164",
        "url": "https://pypi.org/project/finesse-benchmark/0.17.2/",
        "published_at": "2026-03-15T10:52:57Z",
        "updated_at": "2026-03-15T10:52:57Z",
        "headline": "finesse-benchmark 0.17.2",
        "content": {
          "excerpt_text": "sophisticated evaluation framework designed to assess the performance of long-context embedding models on semantic understanding and information retention",
          "lang": "en"
        },
        "provenance": {
          "fetched_at": "2026-03-15T10:54:41Z",
          "evidence_urls": [
            "https://pypi.org/project/finesse-benchmark/0.17.2/"
          ],
          "content_hash": "sha256:50de7e99bf5651939ad02940403831ed3f6a4870b47c508a839c7f26c1f7e4d8"
        },
        "signals": {
          "release": {
            "version": "0.17.2",
            "provenance": {
              "method": "title_regex",
              "authority": "PyPI Recent Updates",
              "authority_url": "https://pypi.org",
              "evidence_url": "https://pypi.org/project/finesse-benchmark/0.17.2/"
            }
          }
        },
        "source_payload": {
          "html": "sophisticated evaluation framework designed to assess the performance of long-context embedding models on semantic understanding and information retention",
          "link": "https://pypi.org/project/finesse-benchmark/0.17.2/",
          "published": "Sun, 15 Mar 2026 10:52:57 GMT",
          "published_parsed": [
            2026,
            3,
            15,
            10,
            52,
            57,
            6,
            74,
            0
          ],
          "updated": "Sun, 15 Mar 2026 10:52:57 GMT",
          "updated_parsed": [
            2026,
            3,
            15,
            10,
            52,
            57,
            6,
            74,
            0
          ],
          "guid": ""
        }
      },
      {
        "source": "pypi_recent_updates",
        "id": "d3fe8c8afa1c85f93d19ffc070fb0663",
        "url": "https://pypi.org/project/phantom-agent/0.9.90/",
        "published_at": "2026-03-15T10:52:56Z",
        "updated_at": "2026-03-15T10:52:56Z",
        "headline": "phantom-agent 0.9.90",
        "content": {
          "excerpt_text": "Autonomous Offensive Security Intelligence — AI-powered penetration testing",
          "lang": "en"
        },
        "provenance": {
          "fetched_at": "2026-03-15T10:54:41Z",
          "evidence_urls": [
            "https://pypi.org/project/phantom-agent/0.9.90/"
          ],
          "content_hash": "sha256:bfed1bd9a681e0e61b1593fb3063f1a8c0477c137ce14733e9db73ba1f22bb63"
        },
        "signals": {
          "release": {
            "version": "0.9.90",
            "provenance": {
              "method": "title_regex",
              "authority": "PyPI Recent Updates",
              "authority_url": "https://pypi.org",
              "evidence_url": "https://pypi.org/project/phantom-agent/0.9.90/"
            }
          }
        },
        "source_payload": {
          "html": "Autonomous Offensive Security Intelligence — AI-powered penetration testing",
          "link": "https://pypi.org/project/phantom-agent/0.9.90/",
          "published": "Sun, 15 Mar 2026 10:52:56 GMT",
          "published_parsed": [
            2026,
            3,
            15,
            10,
            52,
            56,
            6,
            74,
            0
          ],
          "updated": "Sun, 15 Mar 2026 10:52:56 GMT",
          "updated_parsed": [
            2026,
            3,
            15,
            10,
            52,
            56,
            6,
            74,
            0
          ],
          "guid": ""
        }
      },
      {
        "source": "pypi_recent_updates",
        "id": "c4313a79cf4e3e7bc806c7a0a36c6779",
        "url": "https://pypi.org/project/prfs/0.1.0/",
        "published_at": "2026-03-15T10:52:41Z",
        "updated_at": "2026-03-15T10:52:41Z",
        "headline": "prfs 0.1.0",
        "content": {
          "excerpt_text": "Inline PR comments as local files",
          "lang": "en"
        },
        "provenance": {
          "fetched_at": "2026-03-15T10:54:41Z",
          "evidence_urls": [
            "https://pypi.org/project/prfs/0.1.0/"
          ],
          "content_hash": "sha256:1163c5828715b55ecaed2f965fe401ef07a65fb7786864acad6b7cabba15dfe2"
        },
        "signals": {
          "release": {
            "version": "0.1.0",
            "provenance": {
              "method": "title_regex",
              "authority": "PyPI Recent Updates",
              "authority_url": "https://pypi.org",
              "evidence_url": "https://pypi.org/project/prfs/0.1.0/"
            }
          }
        },
        "source_payload": {
          "html": "Inline PR comments as local files",
          "link": "https://pypi.org/project/prfs/0.1.0/",
          "published": "Sun, 15 Mar 2026 10:52:41 GMT",
          "published_parsed": [
            2026,
            3,
            15,
            10,
            52,
            41,
            6,
            74,
            0
          ],
          "updated": "Sun, 15 Mar 2026 10:52:41 GMT",
          "updated_parsed": [
            2026,
            3,
            15,
            10,
            52,
            41,
            6,
            74,
            0
          ],
          "guid": ""
        }
      },
      {
        "source": "pypi_recent_updates",
        "id": "f80c3c14672291bf9aec3611712e27be",
        "url": "https://pypi.org/project/tiktok-live-api/1.1.0/",
        "published_at": "2026-03-15T10:52:26Z",
        "updated_at": "2026-03-15T10:52:26Z",
        "headline": "tiktok-live-api 1.1.0",
        "content": {
          "excerpt_text": "Unofficial TikTok LIVE API Client — Real-time chat, gifts, viewers, battles, and live captions from any TikTok livestream via the TikTool managed API.",
          "lang": "en"
        },
        "provenance": {
          "fetched_at": "2026-03-15T10:54:41Z",
          "evidence_urls": [
            "https://pypi.org/project/tiktok-live-api/1.1.0/"
          ],
          "content_hash": "sha256:c85dfd608210e50a5e5ca1be34a222b06e8214ce0864ee95aeb8d5282b7c94cf"
        },
        "signals": {
          "release": {
            "version": "1.1.0",
            "provenance": {
              "method": "title_regex",
              "authority": "PyPI Recent Updates",
              "authority_url": "https://pypi.org",
              "evidence_url": "https://pypi.org/project/tiktok-live-api/1.1.0/"
            }
          }
        },
        "source_payload": {
          "html": "Unofficial TikTok LIVE API Client — Real-time chat, gifts, viewers, battles, and live captions from any TikTok livestream via the TikTool managed API.",
          "link": "https://pypi.org/project/tiktok-live-api/1.1.0/",
          "published": "Sun, 15 Mar 2026 10:52:26 GMT",
          "published_parsed": [
            2026,
            3,
            15,
            10,
            52,
            26,
            6,
            74,
            0
          ],
          "updated": "Sun, 15 Mar 2026 10:52:26 GMT",
          "updated_parsed": [
            2026,
            3,
            15,
            10,
            52,
            26,
            6,
            74,
            0
          ],
          "guid": ""
        }
      },
      {
        "source": "pypi_recent_updates",
        "id": "a1cab42883b6a33aa47e10d5268673d0",
        "url": "https://pypi.org/project/phoenix-pubsub/0.5.1/",
        "published_at": "2026-03-15T10:52:17Z",
        "updated_at": "2026-03-15T10:52:17Z",
        "headline": "phoenix-pubsub 0.5.1",
        "content": {
          "excerpt_text": "A topic-based publish-subscribe system for asyncio applications, inspired by Phoenix's PubSub",
          "lang": "en"
        },
        "provenance": {
          "fetched_at": "2026-03-15T10:54:41Z",
          "evidence_urls": [
            "https://pypi.org/project/phoenix-pubsub/0.5.1/"
          ],
          "content_hash": "sha256:413e38afe5de0b3968b6e9a711da3260cdd6b21ad8ceb83bcd0438f4e064dd93"
        },
        "signals": {
          "release": {
            "version": "0.5.1",
            "provenance": {
              "method": "title_regex",
              "authority": "PyPI Recent Updates",
              "authority_url": "https://pypi.org",
              "evidence_url": "https://pypi.org/project/phoenix-pubsub/0.5.1/"
            }
          }
        },
        "source_payload": {
          "html": "A topic-based publish-subscribe system for asyncio applications, inspired by Phoenix's PubSub",
          "link": "https://pypi.org/project/phoenix-pubsub/0.5.1/",
          "published": "Sun, 15 Mar 2026 10:52:17 GMT",
          "published_parsed": [
            2026,
            3,
            15,
            10,
            52,
            17,
            6,
            74,
            0
          ],
          "updated": "Sun, 15 Mar 2026 10:52:17 GMT",
          "updated_parsed": [
            2026,
            3,
            15,
            10,
            52,
            17,
            6,
            74,
            0
          ],
          "guid": ""
        }
      },
      {
        "source": "pypi_recent_updates",
        "id": "260bd843359ec3ea35caf539f7517eda",
        "url": "https://pypi.org/project/unisights/0.0.1b15/",
        "published_at": "2026-03-15T10:52:15Z",
        "updated_at": "2026-03-15T10:52:15Z",
        "headline": "unisights 0.0.1b15",
        "content": {
          "excerpt_text": "Unisights Python SDK provides a lightweight event collection endpoint for Python web frameworks.",
          "lang": "en"
        },
        "provenance": {
          "fetched_at": "2026-03-15T10:54:41Z",
          "evidence_urls": [
            "https://pypi.org/project/unisights/0.0.1b15/"
          ],
          "content_hash": "sha256:fe33b9702f62fc6f5209b4ee68cec6840e82642311e5c4bb6e2f0a7113331419"
        },
        "signals": {
          "release": {
            "version": "0.0.1",
            "provenance": {
              "method": "title_regex",
              "authority": "PyPI Recent Updates",
              "authority_url": "https://pypi.org",
              "evidence_url": "https://pypi.org/project/unisights/0.0.1b15/"
            }
          }
        },
        "source_payload": {
          "html": "Unisights Python SDK provides a lightweight event collection endpoint for Python web frameworks.",
          "link": "https://pypi.org/project/unisights/0.0.1b15/",
          "published": "Sun, 15 Mar 2026 10:52:15 GMT",
          "published_parsed": [
            2026,
            3,
            15,
            10,
            52,
            15,
            6,
            74,
            0
          ],
          "updated": "Sun, 15 Mar 2026 10:52:15 GMT",
          "updated_parsed": [
            2026,
            3,
            15,
            10,
            52,
            15,
            6,
            74,
            0
          ],
          "guid": ""
        }
      },
      {
        "source": "pypi_recent_updates",
        "id": "564774ebc38bca6055fea64e7682a15e",
        "url": "https://pypi.org/project/md-server/0.2.0/",
        "published_at": "2026-03-15T10:52:00Z",
        "updated_at": "2026-03-15T10:52:00Z",
        "headline": "md-server 0.2.0",
        "content": {
          "excerpt_text": "HTTP API and MCP server for converting documents, web pages, and media to markdown",
          "lang": "en"
        },
        "provenance": {
          "fetched_at": "2026-03-15T10:54:41Z",
          "evidence_urls": [
            "https://pypi.org/project/md-server/0.2.0/"
          ],
          "content_hash": "sha256:370cc082d0f5b1cba52ae665703abb63511bc6b4377e863ca27d3971ad61b627"
        },
        "signals": {
          "release": {
            "version": "0.2.0",
            "provenance": {
              "method": "title_regex",
              "authority": "PyPI Recent Updates",
              "authority_url": "https://pypi.org",
              "evidence_url": "https://pypi.org/project/md-server/0.2.0/"
            }
          }
        },
        "source_payload": {
          "html": "HTTP API and MCP server for converting documents, web pages, and media to markdown",
          "link": "https://pypi.org/project/md-server/0.2.0/",
          "published": "Sun, 15 Mar 2026 10:52:00 GMT",
          "published_parsed": [
            2026,
            3,
            15,
            10,
            52,
            0,
            6,
            74,
            0
          ],
          "updated": "Sun, 15 Mar 2026 10:52:00 GMT",
          "updated_parsed": [
            2026,
            3,
            15,
            10,
            52,
            0,
            6,
            74,
            0
          ],
          "guid": ""
        }
      },
      {
        "source": "pypi_recent_updates",
        "id": "657df0e4d45a365a98c4fbfb0ff0a698",
        "url": "https://pypi.org/project/openmedaxis/0.0.1/",
        "published_at": "2026-03-15T10:51:16Z",
        "updated_at": "2026-03-15T10:51:16Z",
        "headline": "openmedaxis 0.0.1",
        "content": {
          "excerpt_text": "Open framework for generative medical imaging research",
          "lang": "en"
        },
        "provenance": {
          "fetched_at": "2026-03-15T10:54:41Z",
          "evidence_urls": [
            "https://pypi.org/project/openmedaxis/0.0.1/"
          ],
          "content_hash": "sha256:df41b1b932ebc0a98ce711f9274b317db0fdcd8d97474d9f00a72bdc7ca78977"
        },
        "signals": {
          "release": {
            "version": "0.0.1",
            "provenance": {
              "method": "title_regex",
              "authority": "PyPI Recent Updates",
              "authority_url": "https://pypi.org",
              "evidence_url": "https://pypi.org/project/openmedaxis/0.0.1/"
            }
          }
        },
        "source_payload": {
          "html": "Open framework for generative medical imaging research",
          "link": "https://pypi.org/project/openmedaxis/0.0.1/",
          "published": "Sun, 15 Mar 2026 10:51:16 GMT",
          "published_parsed": [
            2026,
            3,
            15,
            10,
            51,
            16,
            6,
            74,
            0
          ],
          "updated": "Sun, 15 Mar 2026 10:51:16 GMT",
          "updated_parsed": [
            2026,
            3,
            15,
            10,
            51,
            16,
            6,
            74,
            0
          ],
          "guid": ""
        }
      },
      {
        "source": "pypi_recent_updates",
        "id": "b536df4fc87234d02d96e700eaa93071",
        "url": "https://pypi.org/project/waifuboard/0.2.1/",
        "published_at": "2026-03-15T10:51:10Z",
        "updated_at": "2026-03-15T10:51:10Z",
        "headline": "waifuboard 0.2.1",
        "content": {
          "excerpt_text": "Asynchronous API for downloading images, tags, and metadata from image board sites (e.g., Danbooru, Safebooru, Yandere). Ignore the downloaded files.",
          "lang": "en"
        },
        "provenance": {
          "fetched_at": "2026-03-15T10:54:41Z",
          "evidence_urls": [
            "https://pypi.org/project/waifuboard/0.2.1/"
          ],
          "content_hash": "sha256:173126f6c7dda99bd08ab98e7c1eab8e744ec3faa8e02f7db541e0e1704a52c0"
        },
        "signals": {
          "release": {
            "version": "0.2.1",
            "provenance": {
              "method": "title_regex",
              "authority": "PyPI Recent Updates",
              "authority_url": "https://pypi.org",
              "evidence_url": "https://pypi.org/project/waifuboard/0.2.1/"
            }
          }
        },
        "source_payload": {
          "html": "Asynchronous API for downloading images, tags, and metadata from image board sites (e.g., Danbooru, Safebooru, Yandere). Ignore the downloaded files.",
          "link": "https://pypi.org/project/waifuboard/0.2.1/",
          "published": "Sun, 15 Mar 2026 10:51:10 GMT",
          "published_parsed": [
            2026,
            3,
            15,
            10,
            51,
            10,
            6,
            74,
            0
          ],
          "updated": "Sun, 15 Mar 2026 10:51:10 GMT",
          "updated_parsed": [
            2026,
            3,
            15,
            10,
            51,
            10,
            6,
            74,
            0
          ],
          "guid": ""
        }
      },
      {
        "source": "pypi_recent_updates",
        "id": "8443f2e3732f946035d115cf5a8725ef",
        "url": "https://pypi.org/project/diffchunk/0.1.9/",
        "published_at": "2026-03-15T10:50:46Z",
        "updated_at": "2026-03-15T10:50:46Z",
        "headline": "diffchunk 0.1.9",
        "content": {
          "excerpt_text": "MCP server for navigating large diff files with intelligent chunking",
          "lang": "en"
        },
        "provenance": {
          "fetched_at": "2026-03-15T10:54:41Z",
          "evidence_urls": [
            "https://pypi.org/project/diffchunk/0.1.9/"
          ],
          "content_hash": "sha256:7f524cb910e75a574a7c019339c91fd8cd4317a80a304fb721b18ffa97dd234c"
        },
        "signals": {
          "release": {
            "version": "0.1.9",
            "provenance": {
              "method": "title_regex",
              "authority": "PyPI Recent Updates",
              "authority_url": "https://pypi.org",
              "evidence_url": "https://pypi.org/project/diffchunk/0.1.9/"
            }
          }
        },
        "source_payload": {
          "html": "MCP server for navigating large diff files with intelligent chunking",
          "link": "https://pypi.org/project/diffchunk/0.1.9/",
          "published": "Sun, 15 Mar 2026 10:50:46 GMT",
          "published_parsed": [
            2026,
            3,
            15,
            10,
            50,
            46,
            6,
            74,
            0
          ],
          "updated": "Sun, 15 Mar 2026 10:50:46 GMT",
          "updated_parsed": [
            2026,
            3,
            15,
            10,
            50,
            46,
            6,
            74,
            0
          ],
          "guid": ""
        }
      },
      {
        "source": "pypi_recent_updates",
        "id": "144a85af8b1d83ea6521ec9f86b10d4d",
        "url": "https://pypi.org/project/dsxllm/0.1.3.1/",
        "published_at": "2026-03-15T10:50:32Z",
        "updated_at": "2026-03-15T10:50:32Z",
        "headline": "dsxllm 0.1.3.1",
        "content": {
          "excerpt_text": "动手学大语言模型依赖库",
          "lang": "en"
        },
        "provenance": {
          "fetched_at": "2026-03-15T10:54:41Z",
          "evidence_urls": [
            "https://pypi.org/project/dsxllm/0.1.3.1/"
          ],
          "content_hash": "sha256:463b0b4446a57f1588ec9e32bdb6f3beb4fa6cadd3465b44b718391c8fff1a0b"
        },
        "signals": {
          "release": {
            "version": "0.1.3",
            "provenance": {
              "method": "title_regex",
              "authority": "PyPI Recent Updates",
              "authority_url": "https://pypi.org",
              "evidence_url": "https://pypi.org/project/dsxllm/0.1.3.1/"
            }
          }
        },
        "source_payload": {
          "html": "动手学大语言模型依赖库",
          "link": "https://pypi.org/project/dsxllm/0.1.3.1/",
          "published": "Sun, 15 Mar 2026 10:50:32 GMT",
          "published_parsed": [
            2026,
            3,
            15,
            10,
            50,
            32,
            6,
            74,
            0
          ],
          "updated": "Sun, 15 Mar 2026 10:50:32 GMT",
          "updated_parsed": [
            2026,
            3,
            15,
            10,
            50,
            32,
            6,
            74,
            0
          ],
          "guid": ""
        }
      },
      {
        "source": "pypi_recent_updates",
        "id": "0ee41a4a547b5e7c3113d7ef31f2e6ad",
        "url": "https://pypi.org/project/ztml/0.1.1/",
        "published_at": "2026-03-15T10:50:31Z",
        "updated_at": "2026-03-15T10:50:31Z",
        "headline": "ztml 0.1.1",
        "content": {
          "excerpt_text": "Rust-backed framework for building websites in pure Python",
          "lang": "en"
        },
        "provenance": {
          "fetched_at": "2026-03-15T10:54:41Z",
          "evidence_urls": [
            "https://pypi.org/project/ztml/0.1.1/"
          ],
          "content_hash": "sha256:7ab424b3684f422cbaba56c5febc2ef8ee484b1192dde72a3eb2c99c63229410"
        },
        "signals": {
          "release": {
            "version": "0.1.1",
            "provenance": {
              "method": "title_regex",
              "authority": "PyPI Recent Updates",
              "authority_url": "https://pypi.org",
              "evidence_url": "https://pypi.org/project/ztml/0.1.1/"
            }
          }
        },
        "source_payload": {
          "html": "Rust-backed framework for building websites in pure Python",
          "link": "https://pypi.org/project/ztml/0.1.1/",
          "published": "Sun, 15 Mar 2026 10:50:31 GMT",
          "published_parsed": [
            2026,
            3,
            15,
            10,
            50,
            31,
            6,
            74,
            0
          ],
          "updated": "Sun, 15 Mar 2026 10:50:31 GMT",
          "updated_parsed": [
            2026,
            3,
            15,
            10,
            50,
            31,
            6,
            74,
            0
          ],
          "guid": ""
        }
      },
      {
        "source": "pypi_recent_updates",
        "id": "9ffe3eb260997239fe5a611c4c5e65c2",
        "url": "https://pypi.org/project/aipaygen-mcp/1.8.2/",
        "published_at": "2026-03-15T10:50:21Z",
        "updated_at": "2026-03-15T10:50:21Z",
        "headline": "aipaygen-mcp 1.8.2",
        "content": {
          "excerpt_text": "MCP server for AiPayGen — 229 AI tools with pay-per-call USDC payments, free tier, and in-chat purchasing",
          "lang": "en"
        },
        "provenance": {
          "fetched_at": "2026-03-15T10:54:41Z",
          "evidence_urls": [
            "https://pypi.org/project/aipaygen-mcp/1.8.2/"
          ],
          "content_hash": "sha256:9d97333bc9e082ed61d532c0baed69c68ec3e53ecba29e7239f26220ff319066"
        },
        "signals": {
          "release": {
            "version": "1.8.2",
            "provenance": {
              "method": "title_regex",
              "authority": "PyPI Recent Updates",
              "authority_url": "https://pypi.org",
              "evidence_url": "https://pypi.org/project/aipaygen-mcp/1.8.2/"
            }
          }
        },
        "source_payload": {
          "html": "MCP server for AiPayGen — 229 AI tools with pay-per-call USDC payments, free tier, and in-chat purchasing",
          "link": "https://pypi.org/project/aipaygen-mcp/1.8.2/",
          "published": "Sun, 15 Mar 2026 10:50:21 GMT",
          "published_parsed": [
            2026,
            3,
            15,
            10,
            50,
            21,
            6,
            74,
            0
          ],
          "updated": "Sun, 15 Mar 2026 10:50:21 GMT",
          "updated_parsed": [
            2026,
            3,
            15,
            10,
            50,
            21,
            6,
            74,
            0
          ],
          "guid": ""
        }
      },
      {
        "source": "pypi_recent_updates",
        "id": "4eb0afe439d61da6afaacdfe8f008d5c",
        "url": "https://pypi.org/project/maxwailab/1.0.3/",
        "published_at": "2026-03-15T10:50:11Z",
        "updated_at": "2026-03-15T10:50:11Z",
        "headline": "maxwailab 1.0.3",
        "content": {
          "excerpt_text": "Bootstrap-based model stability and supervised binning toolkit",
          "lang": "en"
        },
        "provenance": {
          "fetched_at": "2026-03-15T10:54:41Z",
          "evidence_urls": [
            "https://pypi.org/project/maxwailab/1.0.3/"
          ],
          "content_hash": "sha256:58a58137d1461b979b93b2b3a3e49cf78710fcf2738ff38da25e87622b964ba9"
        },
        "signals": {
          "release": {
            "version": "1.0.3",
            "provenance": {
              "method": "title_regex",
              "authority": "PyPI Recent Updates",
              "authority_url": "https://pypi.org",
              "evidence_url": "https://pypi.org/project/maxwailab/1.0.3/"
            }
          }
        },
        "source_payload": {
          "html": "Bootstrap-based model stability and supervised binning toolkit",
          "link": "https://pypi.org/project/maxwailab/1.0.3/",
          "published": "Sun, 15 Mar 2026 10:50:11 GMT",
          "published_parsed": [
            2026,
            3,
            15,
            10,
            50,
            11,
            6,
            74,
            0
          ],
          "updated": "Sun, 15 Mar 2026 10:50:11 GMT",
          "updated_parsed": [
            2026,
            3,
            15,
            10,
            50,
            11,
            6,
            74,
            0
          ],
          "guid": ""
        }
      },
      {
        "source": "pypi_recent_updates",
        "id": "c53ea2a04837a360f4e55b47cbc82968",
        "url": "https://pypi.org/project/nblite/1.2.1/",
        "published_at": "2026-03-15T10:50:05Z",
        "updated_at": "2026-03-15T10:50:05Z",
        "headline": "nblite 1.2.1",
        "content": {
          "excerpt_text": "Notebook-driven Python package development tool",
          "lang": "en"
        },
        "provenance": {
          "fetched_at": "2026-03-15T10:54:41Z",
          "evidence_urls": [
            "https://pypi.org/project/nblite/1.2.1/"
          ],
          "content_hash": "sha256:4b32131bfc3acd25cc6cdccddb8de80fa94bbe636ca1f1f6ebfea2944db36afc"
        },
        "signals": {
          "release": {
            "version": "1.2.1",
            "provenance": {
              "method": "title_regex",
              "authority": "PyPI Recent Updates",
              "authority_url": "https://pypi.org",
              "evidence_url": "https://pypi.org/project/nblite/1.2.1/"
            }
          }
        },
        "source_payload": {
          "html": "Notebook-driven Python package development tool",
          "link": "https://pypi.org/project/nblite/1.2.1/",
          "published": "Sun, 15 Mar 2026 10:50:05 GMT",
          "published_parsed": [
            2026,
            3,
            15,
            10,
            50,
            5,
            6,
            74,
            0
          ],
          "updated": "Sun, 15 Mar 2026 10:50:05 GMT",
          "updated_parsed": [
            2026,
            3,
            15,
            10,
            50,
            5,
            6,
            74,
            0
          ],
          "guid": ""
        }
      },
      {
        "source": "pypi_recent_updates",
        "id": "6f00dc8a629374dccbc8d81ac74c4bd1",
        "url": "https://pypi.org/project/cpsat-utils/0.2.1/",
        "published_at": "2026-03-15T10:49:55Z",
        "updated_at": "2026-03-15T10:49:55Z",
        "headline": "cpsat-utils 0.2.1",
        "content": {
          "excerpt_text": "A Python package of utilities for Google's ortools CP-SAT solver.",
          "lang": "en"
        },
        "provenance": {
          "fetched_at": "2026-03-15T10:54:41Z",
          "evidence_urls": [
            "https://pypi.org/project/cpsat-utils/0.2.1/"
          ],
          "content_hash": "sha256:1efe95e0f69e6eac8cab48b7093b23021976722a9b78253d9809c72312643102"
        },
        "signals": {
          "release": {
            "version": "0.2.1",
            "provenance": {
              "method": "title_regex",
              "authority": "PyPI Recent Updates",
              "authority_url": "https://pypi.org",
              "evidence_url": "https://pypi.org/project/cpsat-utils/0.2.1/"
            }
          }
        },
        "source_payload": {
          "html": "A Python package of utilities for Google's ortools CP-SAT solver.",
          "link": "https://pypi.org/project/cpsat-utils/0.2.1/",
          "published": "Sun, 15 Mar 2026 10:49:55 GMT",
          "published_parsed": [
            2026,
            3,
            15,
            10,
            49,
            55,
            6,
            74,
            0
          ],
          "updated": "Sun, 15 Mar 2026 10:49:55 GMT",
          "updated_parsed": [
            2026,
            3,
            15,
            10,
            49,
            55,
            6,
            74,
            0
          ],
          "guid": ""
        }
      },
      {
        "source": "pypi_recent_updates",
        "id": "2b2dad72bafaabbb2e8745efbc4d95b9",
        "url": "https://pypi.org/project/ct-toolkit/0.2.0/",
        "published_at": "2026-03-15T10:49:42Z",
        "updated_at": "2026-03-15T10:49:42Z",
        "headline": "ct-toolkit 0.2.0",
        "content": {
          "excerpt_text": "Computational Theseus Toolkit — Identity Continuity Guardrails for Agentic Systems",
          "lang": "en"
        },
        "provenance": {
          "fetched_at": "2026-03-15T10:54:41Z",
          "evidence_urls": [
            "https://pypi.org/project/ct-toolkit/0.2.0/"
          ],
          "content_hash": "sha256:03ca7e80b37a4042a465a65e1a3505d1e96b8740f52af0b3586cd74595c13d1c"
        },
        "signals": {
          "release": {
            "version": "0.2.0",
            "provenance": {
              "method": "title_regex",
              "authority": "PyPI Recent Updates",
              "authority_url": "https://pypi.org",
              "evidence_url": "https://pypi.org/project/ct-toolkit/0.2.0/"
            }
          }
        },
        "source_payload": {
          "html": "Computational Theseus Toolkit — Identity Continuity Guardrails for Agentic Systems",
          "link": "https://pypi.org/project/ct-toolkit/0.2.0/",
          "published": "Sun, 15 Mar 2026 10:49:42 GMT",
          "published_parsed": [
            2026,
            3,
            15,
            10,
            49,
            42,
            6,
            74,
            0
          ],
          "updated": "Sun, 15 Mar 2026 10:49:42 GMT",
          "updated_parsed": [
            2026,
            3,
            15,
            10,
            49,
            42,
            6,
            74,
            0
          ],
          "guid": ""
        }
      },
      {
        "source": "pypi_recent_updates",
        "id": "d313fa7ac0e481c1aab3305967d15344",
        "url": "https://pypi.org/project/mipiti-verify/0.3.3/",
        "published_at": "2026-03-15T10:49:24Z",
        "updated_at": "2026-03-15T10:49:24Z",
        "headline": "mipiti-verify 0.3.3",
        "content": {
          "excerpt_text": "Turnkey CI verification for Mipiti threat model assertions",
          "lang": "en"
        },
        "provenance": {
          "fetched_at": "2026-03-15T10:54:41Z",
          "evidence_urls": [
            "https://pypi.org/project/mipiti-verify/0.3.3/"
          ],
          "content_hash": "sha256:350a2e005dba9e338aa187173345827edb9e4d5b6b895b7e84813c406c0787f1"
        },
        "signals": {
          "release": {
            "version": "0.3.3",
            "provenance": {
              "method": "title_regex",
              "authority": "PyPI Recent Updates",
              "authority_url": "https://pypi.org",
              "evidence_url": "https://pypi.org/project/mipiti-verify/0.3.3/"
            }
          }
        },
        "source_payload": {
          "html": "Turnkey CI verification for Mipiti threat model assertions",
          "link": "https://pypi.org/project/mipiti-verify/0.3.3/",
          "published": "Sun, 15 Mar 2026 10:49:24 GMT",
          "published_parsed": [
            2026,
            3,
            15,
            10,
            49,
            24,
            6,
            74,
            0
          ],
          "updated": "Sun, 15 Mar 2026 10:49:24 GMT",
          "updated_parsed": [
            2026,
            3,
            15,
            10,
            49,
            24,
            6,
            74,
            0
          ],
          "guid": ""
        }
      },
      {
        "source": "pypi_recent_updates",
        "id": "1027e6f7bd0395d29f4a44bc97bb02ef",
        "url": "https://pypi.org/project/letta-nightly/0.16.6.dev20260315104849/",
        "published_at": "2026-03-15T10:48:55Z",
        "updated_at": "2026-03-15T10:48:55Z",
        "headline": "letta-nightly 0.16.6.dev20260315104849",
        "content": {
          "excerpt_text": "Create LLM agents with long-term memory and custom tools",
          "lang": "en"
        },
        "provenance": {
          "fetched_at": "2026-03-15T10:54:41Z",
          "evidence_urls": [
            "https://pypi.org/project/letta-nightly/0.16.6.dev20260315104849/"
          ],
          "content_hash": "sha256:ac451036564fd0a2d36601af328040042960d27178d4e72c6bc85b14a0e811f3"
        },
        "signals": {
          "release": {
            "version": "0.16.6.dev20260315104849",
            "prerelease": true,
            "provenance": {
              "method": "title_regex",
              "authority": "PyPI Recent Updates",
              "authority_url": "https://pypi.org",
              "evidence_url": "https://pypi.org/project/letta-nightly/0.16.6.dev20260315104849/"
            }
          }
        },
        "source_payload": {
          "html": "Create LLM agents with long-term memory and custom tools",
          "link": "https://pypi.org/project/letta-nightly/0.16.6.dev20260315104849/",
          "published": "Sun, 15 Mar 2026 10:48:55 GMT",
          "published_parsed": [
            2026,
            3,
            15,
            10,
            48,
            55,
            6,
            74,
            0
          ],
          "updated": "Sun, 15 Mar 2026 10:48:55 GMT",
          "updated_parsed": [
            2026,
            3,
            15,
            10,
            48,
            55,
            6,
            74,
            0
          ],
          "guid": ""
        }
      },
      {
        "source": "pypi_recent_updates",
        "id": "99e4c3b68c2af8e28325175434ca0cb1",
        "url": "https://pypi.org/project/nikame/0.7.5/",
        "published_at": "2026-03-15T10:48:50Z",
        "updated_at": "2026-03-15T10:48:50Z",
        "headline": "nikame 0.7.5",
        "content": {
          "excerpt_text": "NIKAME: High-fidelity AI & Cloud Infrastructure Scaffolding Framework (Matrix Engine)",
          "lang": "en"
        },
        "provenance": {
          "fetched_at": "2026-03-15T10:54:41Z",
          "evidence_urls": [
            "https://pypi.org/project/nikame/0.7.5/"
          ],
          "content_hash": "sha256:ff2b9707787f703709e34820073d9ae2bf703d4089346900453dc27a19c41d54"
        },
        "signals": {
          "release": {
            "version": "0.7.5",
            "provenance": {
              "method": "title_regex",
              "authority": "PyPI Recent Updates",
              "authority_url": "https://pypi.org",
              "evidence_url": "https://pypi.org/project/nikame/0.7.5/"
            }
          }
        },
        "source_payload": {
          "html": "NIKAME: High-fidelity AI & Cloud Infrastructure Scaffolding Framework (Matrix Engine)",
          "link": "https://pypi.org/project/nikame/0.7.5/",
          "published": "Sun, 15 Mar 2026 10:48:50 GMT",
          "published_parsed": [
            2026,
            3,
            15,
            10,
            48,
            50,
            6,
            74,
            0
          ],
          "updated": "Sun, 15 Mar 2026 10:48:50 GMT",
          "updated_parsed": [
            2026,
            3,
            15,
            10,
            48,
            50,
            6,
            74,
            0
          ],
          "guid": ""
        }
      },
      {
        "source": "pypi_recent_updates",
        "id": "e25ca40cafe0dc4e8ef63a48181ff5f6",
        "url": "https://pypi.org/project/quidclaw/0.1.0/",
        "published_at": "2026-03-15T10:48:46Z",
        "updated_at": "2026-03-15T10:48:46Z",
        "headline": "quidclaw 0.1.0",
        "content": {
          "excerpt_text": "MCP-based personal finance AI Agent powered by Beancount",
          "lang": "en"
        },
        "provenance": {
          "fetched_at": "2026-03-15T10:54:41Z",
          "evidence_urls": [
            "https://pypi.org/project/quidclaw/0.1.0/"
          ],
          "content_hash": "sha256:5a7870ca945b6f24969e8ed968397864b6d7d75317ab35ca9e9af889ffb52c9f"
        },
        "signals": {
          "release": {
            "version": "0.1.0",
            "provenance": {
              "method": "title_regex",
              "authority": "PyPI Recent Updates",
              "authority_url": "https://pypi.org",
              "evidence_url": "https://pypi.org/project/quidclaw/0.1.0/"
            }
          }
        },
        "source_payload": {
          "html": "MCP-based personal finance AI Agent powered by Beancount",
          "link": "https://pypi.org/project/quidclaw/0.1.0/",
          "published": "Sun, 15 Mar 2026 10:48:46 GMT",
          "published_parsed": [
            2026,
            3,
            15,
            10,
            48,
            46,
            6,
            74,
            0
          ],
          "updated": "Sun, 15 Mar 2026 10:48:46 GMT",
          "updated_parsed": [
            2026,
            3,
            15,
            10,
            48,
            46,
            6,
            74,
            0
          ],
          "guid": ""
        }
      },
      {
        "source": "pypi_recent_updates",
        "id": "550a8e6852794142be129fcb7d0af4ba",
        "url": "https://pypi.org/project/ssblast/0.1.1/",
        "published_at": "2026-03-15T10:48:42Z",
        "updated_at": "2026-03-15T10:48:42Z",
        "headline": "ssblast 0.1.1",
        "content": {
          "excerpt_text": "FP8 per-tile scaled linear solver for consumer NVIDIA GPUs",
          "lang": "en"
        },
        "provenance": {
          "fetched_at": "2026-03-15T10:54:41Z",
          "evidence_urls": [
            "https://pypi.org/project/ssblast/0.1.1/"
          ],
          "content_hash": "sha256:54191d03eb858b5f2537bf94c4731b374286612f5a735fcafb2703e7e03795ec"
        },
        "signals": {
          "release": {
            "version": "0.1.1",
            "provenance": {
              "method": "title_regex",
              "authority": "PyPI Recent Updates",
              "authority_url": "https://pypi.org",
              "evidence_url": "https://pypi.org/project/ssblast/0.1.1/"
            }
          }
        },
        "source_payload": {
          "html": "FP8 per-tile scaled linear solver for consumer NVIDIA GPUs",
          "link": "https://pypi.org/project/ssblast/0.1.1/",
          "published": "Sun, 15 Mar 2026 10:48:42 GMT",
          "published_parsed": [
            2026,
            3,
            15,
            10,
            48,
            42,
            6,
            74,
            0
          ],
          "updated": "Sun, 15 Mar 2026 10:48:42 GMT",
          "updated_parsed": [
            2026,
            3,
            15,
            10,
            48,
            42,
            6,
            74,
            0
          ],
          "guid": ""
        }
      },
      {
        "source": "pypi_recent_updates",
        "id": "729dc5a1a84c5baac20f4f8392e9ce99",
        "url": "https://pypi.org/project/revkeen/1.20260315.63/",
        "published_at": "2026-03-15T10:48:25Z",
        "updated_at": "2026-03-15T10:48:25Z",
        "headline": "revkeen 1.20260315.63",
        "content": {
          "excerpt_text": "RevKeen Python SDK - Stripe-like billing infrastructure for your SaaS",
          "lang": "en"
        },
        "provenance": {
          "fetched_at": "2026-03-15T10:54:41Z",
          "evidence_urls": [
            "https://pypi.org/project/revkeen/1.20260315.63/"
          ],
          "content_hash": "sha256:b19e4a6853e25464ec504e9487362344c0ef93e9c92193d75ab472b01b64c2df"
        },
        "signals": {
          "release": {
            "version": "1.20260315.63",
            "provenance": {
              "method": "title_regex",
              "authority": "PyPI Recent Updates",
              "authority_url": "https://pypi.org",
              "evidence_url": "https://pypi.org/project/revkeen/1.20260315.63/"
            }
          }
        },
        "source_payload": {
          "html": "RevKeen Python SDK - Stripe-like billing infrastructure for your SaaS",
          "link": "https://pypi.org/project/revkeen/1.20260315.63/",
          "published": "Sun, 15 Mar 2026 10:48:25 GMT",
          "published_parsed": [
            2026,
            3,
            15,
            10,
            48,
            25,
            6,
            74,
            0
          ],
          "updated": "Sun, 15 Mar 2026 10:48:25 GMT",
          "updated_parsed": [
            2026,
            3,
            15,
            10,
            48,
            25,
            6,
            74,
            0
          ],
          "guid": ""
        }
      },
      {
        "source": "pypi_recent_updates",
        "id": "b2727bb0031a2bb75d28a5d5101fc803",
        "url": "https://pypi.org/project/sparqlmojo/0.14.2/",
        "published_at": "2026-03-15T10:48:19Z",
        "updated_at": "2026-03-15T10:48:19Z",
        "headline": "SPARQLMojo 0.14.2",
        "content": {
          "excerpt_text": "An SQLAlchemy-like ORM for SPARQL endpoints.",
          "lang": "en"
        },
        "provenance": {
          "fetched_at": "2026-03-15T10:54:41Z",
          "evidence_urls": [
            "https://pypi.org/project/sparqlmojo/0.14.2/"
          ],
          "content_hash": "sha256:2f897e1141a44e893d170646a9619ad1bd5101d615ed9d9706f547bbad412cf2"
        },
        "signals": {
          "release": {
            "version": "0.14.2",
            "provenance": {
              "method": "title_regex",
              "authority": "PyPI Recent Updates",
              "authority_url": "https://pypi.org",
              "evidence_url": "https://pypi.org/project/sparqlmojo/0.14.2/"
            }
          }
        },
        "source_payload": {
          "html": "An SQLAlchemy-like ORM for SPARQL endpoints.",
          "link": "https://pypi.org/project/sparqlmojo/0.14.2/",
          "published": "Sun, 15 Mar 2026 10:48:19 GMT",
          "published_parsed": [
            2026,
            3,
            15,
            10,
            48,
            19,
            6,
            74,
            0
          ],
          "updated": "Sun, 15 Mar 2026 10:48:19 GMT",
          "updated_parsed": [
            2026,
            3,
            15,
            10,
            48,
            19,
            6,
            74,
            0
          ],
          "guid": ""
        }
      },
      {
        "source": "pypi_recent_updates",
        "id": "4b94eb0f40dc3dc66809b89137d59b40",
        "url": "https://pypi.org/project/xpander-sdk/2.0.257/",
        "published_at": "2026-03-15T10:47:57Z",
        "updated_at": "2026-03-15T10:47:57Z",
        "headline": "xpander-sdk 2.0.257",
        "content": {
          "excerpt_text": "xpander.ai Backend-as-a-service for AI Agents - SDK",
          "lang": "en"
        },
        "provenance": {
          "fetched_at": "2026-03-15T10:54:41Z",
          "evidence_urls": [
            "https://pypi.org/project/xpander-sdk/2.0.257/"
          ],
          "content_hash": "sha256:1be21f693e5d26ac48d141c9c5848d7758bec5b933a96590b41df386e5d7587d"
        },
        "signals": {
          "release": {
            "version": "2.0.257",
            "provenance": {
              "method": "title_regex",
              "authority": "PyPI Recent Updates",
              "authority_url": "https://pypi.org",
              "evidence_url": "https://pypi.org/project/xpander-sdk/2.0.257/"
            }
          }
        },
        "source_payload": {
          "html": "xpander.ai Backend-as-a-service for AI Agents - SDK",
          "link": "https://pypi.org/project/xpander-sdk/2.0.257/",
          "published": "Sun, 15 Mar 2026 10:47:57 GMT",
          "published_parsed": [
            2026,
            3,
            15,
            10,
            47,
            57,
            6,
            74,
            0
          ],
          "updated": "Sun, 15 Mar 2026 10:47:57 GMT",
          "updated_parsed": [
            2026,
            3,
            15,
            10,
            47,
            57,
            6,
            74,
            0
          ],
          "guid": ""
        }
      },
      {
        "source": "pypi_recent_updates",
        "id": "8241d309b9a7f718f13ecb63194c45fe",
        "url": "https://pypi.org/project/agenthold/0.1.2/",
        "published_at": "2026-03-15T10:47:54Z",
        "updated_at": "2026-03-15T10:47:54Z",
        "headline": "agenthold 0.1.2",
        "content": {
          "excerpt_text": "Shared versioned state for multi-agent AI workflows",
          "lang": "en"
        },
        "provenance": {
          "fetched_at": "2026-03-15T10:54:41Z",
          "evidence_urls": [
            "https://pypi.org/project/agenthold/0.1.2/"
          ],
          "content_hash": "sha256:f802925dd8e9b001f3ce821c62aaacc7a35ccc0269d707034d4acd30d4419b48"
        },
        "signals": {
          "release": {
            "version": "0.1.2",
            "provenance": {
              "method": "title_regex",
              "authority": "PyPI Recent Updates",
              "authority_url": "https://pypi.org",
              "evidence_url": "https://pypi.org/project/agenthold/0.1.2/"
            }
          }
        },
        "source_payload": {
          "html": "Shared versioned state for multi-agent AI workflows",
          "link": "https://pypi.org/project/agenthold/0.1.2/",
          "published": "Sun, 15 Mar 2026 10:47:54 GMT",
          "published_parsed": [
            2026,
            3,
            15,
            10,
            47,
            54,
            6,
            74,
            0
          ],
          "updated": "Sun, 15 Mar 2026 10:47:54 GMT",
          "updated_parsed": [
            2026,
            3,
            15,
            10,
            47,
            54,
            6,
            74,
            0
          ],
          "guid": ""
        }
      },
      {
        "source": "pypi_recent_updates",
        "id": "9a162de9c3c13644b68cd150cf09b127",
        "url": "https://pypi.org/project/unisights/0.0.1b14/",
        "published_at": "2026-03-15T10:46:49Z",
        "updated_at": "2026-03-15T10:46:49Z",
        "headline": "unisights 0.0.1b14",
        "content": {
          "excerpt_text": "Unisights Python SDK provides a lightweight event collection endpoint for Python web frameworks.",
          "lang": "en"
        },
        "provenance": {
          "fetched_at": "2026-03-15T10:54:41Z",
          "evidence_urls": [
            "https://pypi.org/project/unisights/0.0.1b14/"
          ],
          "content_hash": "sha256:a50626162a92b35c023b3c0acf5f03da97ef5cda3fd2066be6c85ad6a490ccdf"
        },
        "signals": {
          "release": {
            "version": "0.0.1",
            "provenance": {
              "method": "title_regex",
              "authority": "PyPI Recent Updates",
              "authority_url": "https://pypi.org",
              "evidence_url": "https://pypi.org/project/unisights/0.0.1b14/"
            }
          }
        },
        "source_payload": {
          "html": "Unisights Python SDK provides a lightweight event collection endpoint for Python web frameworks.",
          "link": "https://pypi.org/project/unisights/0.0.1b14/",
          "published": "Sun, 15 Mar 2026 10:46:49 GMT",
          "published_parsed": [
            2026,
            3,
            15,
            10,
            46,
            49,
            6,
            74,
            0
          ],
          "updated": "Sun, 15 Mar 2026 10:46:49 GMT",
          "updated_parsed": [
            2026,
            3,
            15,
            10,
            46,
            49,
            6,
            74,
            0
          ],
          "guid": ""
        }
      },
      {
        "source": "pypi_recent_updates",
        "id": "0da4b2f664016b3520f5ce292daebb9e",
        "url": "https://pypi.org/project/maxwailab/1.0.2/",
        "published_at": "2026-03-15T10:46:43Z",
        "updated_at": "2026-03-15T10:46:43Z",
        "headline": "maxwailab 1.0.2",
        "content": {
          "excerpt_text": "Bootstrap-based model stability and supervised binning toolkit",
          "lang": "en"
        },
        "provenance": {
          "fetched_at": "2026-03-15T10:54:41Z",
          "evidence_urls": [
            "https://pypi.org/project/maxwailab/1.0.2/"
          ],
          "content_hash": "sha256:d15ccbabb843297bf34664ad9bcf6bd385043c7cbbcdc032613bc7f00eb57f66"
        },
        "signals": {
          "release": {
            "version": "1.0.2",
            "provenance": {
              "method": "title_regex",
              "authority": "PyPI Recent Updates",
              "authority_url": "https://pypi.org",
              "evidence_url": "https://pypi.org/project/maxwailab/1.0.2/"
            }
          }
        },
        "source_payload": {
          "html": "Bootstrap-based model stability and supervised binning toolkit",
          "link": "https://pypi.org/project/maxwailab/1.0.2/",
          "published": "Sun, 15 Mar 2026 10:46:43 GMT",
          "published_parsed": [
            2026,
            3,
            15,
            10,
            46,
            43,
            6,
            74,
            0
          ],
          "updated": "Sun, 15 Mar 2026 10:46:43 GMT",
          "updated_parsed": [
            2026,
            3,
            15,
            10,
            46,
            43,
            6,
            74,
            0
          ],
          "guid": ""
        }
      },
      {
        "source": "pypi_recent_updates",
        "id": "275f32b4506d8db5f5e4124e0f37eb57",
        "url": "https://pypi.org/project/ifchange/0.2.1/",
        "published_at": "2026-03-15T10:46:08Z",
        "updated_at": "2026-03-15T10:46:08Z",
        "headline": "ifchange 0.2.1",
        "content": {
          "excerpt_text": "A fast linter for enforcing conditional change directives in source code",
          "lang": "en"
        },
        "provenance": {
          "fetched_at": "2026-03-15T10:54:41Z",
          "evidence_urls": [
            "https://pypi.org/project/ifchange/0.2.1/"
          ],
          "content_hash": "sha256:acaca58ee422f36d19644e328ca938594e6c4c91776d16751e1890dbbe68b29f"
        },
        "signals": {
          "release": {
            "version": "0.2.1",
            "provenance": {
              "method": "title_regex",
              "authority": "PyPI Recent Updates",
              "authority_url": "https://pypi.org",
              "evidence_url": "https://pypi.org/project/ifchange/0.2.1/"
            }
          }
        },
        "source_payload": {
          "html": "A fast linter for enforcing conditional change directives in source code",
          "link": "https://pypi.org/project/ifchange/0.2.1/",
          "published": "Sun, 15 Mar 2026 10:46:08 GMT",
          "published_parsed": [
            2026,
            3,
            15,
            10,
            46,
            8,
            6,
            74,
            0
          ],
          "updated": "Sun, 15 Mar 2026 10:46:08 GMT",
          "updated_parsed": [
            2026,
            3,
            15,
            10,
            46,
            8,
            6,
            74,
            0
          ],
          "guid": ""
        }
      },
      {
        "source": "pypi_recent_updates",
        "id": "067918735b2f7cc46a4a2d965089f8eb",
        "url": "https://pypi.org/project/shekel/0.2.8/",
        "published_at": "2026-03-15T10:46:07Z",
        "updated_at": "2026-03-15T10:46:07Z",
        "headline": "shekel 0.2.8",
        "content": {
          "excerpt_text": "LLM budget enforcement and cost tracking. Zero config — with budget(max_usd=1.00): run_agent(). Works with LangGraph, CrewAI, raw OpenAI/Anthropic/Gemini.",
          "lang": "en"
        },
        "provenance": {
          "fetched_at": "2026-03-15T10:54:41Z",
          "evidence_urls": [
            "https://pypi.org/project/shekel/0.2.8/"
          ],
          "content_hash": "sha256:fc29d774282f427c849eff7548143dc61817d4dcc67efdccb97d45fc4a6c82e5"
        },
        "signals": {
          "release": {
            "version": "0.2.8",
            "provenance": {
              "method": "title_regex",
              "authority": "PyPI Recent Updates",
              "authority_url": "https://pypi.org",
              "evidence_url": "https://pypi.org/project/shekel/0.2.8/"
            }
          }
        },
        "source_payload": {
          "html": "LLM budget enforcement and cost tracking. Zero config — with budget(max_usd=1.00): run_agent(). Works with LangGraph, CrewAI, raw OpenAI/Anthropic/Gemini.",
          "link": "https://pypi.org/project/shekel/0.2.8/",
          "published": "Sun, 15 Mar 2026 10:46:07 GMT",
          "published_parsed": [
            2026,
            3,
            15,
            10,
            46,
            7,
            6,
            74,
            0
          ],
          "updated": "Sun, 15 Mar 2026 10:46:07 GMT",
          "updated_parsed": [
            2026,
            3,
            15,
            10,
            46,
            7,
            6,
            74,
            0
          ],
          "guid": ""
        }
      },
      {
        "source": "pypi_recent_updates",
        "id": "f64f87974d92f211c5ff853e11f58e58",
        "url": "https://pypi.org/project/ion-nn/0.2.6/",
        "published_at": "2026-03-15T10:45:54Z",
        "updated_at": "2026-03-15T10:45:54Z",
        "headline": "ion-nn 0.2.6",
        "content": {
          "excerpt_text": "A minimal neural network library for JAX.",
          "lang": "en"
        },
        "provenance": {
          "fetched_at": "2026-03-15T10:54:41Z",
          "evidence_urls": [
            "https://pypi.org/project/ion-nn/0.2.6/"
          ],
          "content_hash": "sha256:e7ff817251bb42d441484651d2c5dad3659639f12426b8011d728ba953ad4fd0"
        },
        "signals": {
          "release": {
            "version": "0.2.6",
            "provenance": {
              "method": "title_regex",
              "authority": "PyPI Recent Updates",
              "authority_url": "https://pypi.org",
              "evidence_url": "https://pypi.org/project/ion-nn/0.2.6/"
            }
          }
        },
        "source_payload": {
          "html": "A minimal neural network library for JAX.",
          "link": "https://pypi.org/project/ion-nn/0.2.6/",
          "published": "Sun, 15 Mar 2026 10:45:54 GMT",
          "published_parsed": [
            2026,
            3,
            15,
            10,
            45,
            54,
            6,
            74,
            0
          ],
          "updated": "Sun, 15 Mar 2026 10:45:54 GMT",
          "updated_parsed": [
            2026,
            3,
            15,
            10,
            45,
            54,
            6,
            74,
            0
          ],
          "guid": ""
        }
      },
      {
        "source": "pypi_recent_updates",
        "id": "bf9e5c0f2417850d76f5772a89288c68",
        "url": "https://pypi.org/project/apyds/0.0.20a1/",
        "published_at": "2026-03-15T10:45:52Z",
        "updated_at": "2026-03-15T10:45:52Z",
        "headline": "apyds 0.0.20a1",
        "content": {
          "excerpt_text": "A deductive system",
          "lang": "en"
        },
        "provenance": {
          "fetched_at": "2026-03-15T10:54:41Z",
          "evidence_urls": [
            "https://pypi.org/project/apyds/0.0.20a1/"
          ],
          "content_hash": "sha256:3789c49a71f731b2344de5a20b276ff3e9201ace2266f41b222d24bc92a241ce"
        },
        "signals": {
          "release": {
            "version": "0.0.20",
            "provenance": {
              "method": "title_regex",
              "authority": "PyPI Recent Updates",
              "authority_url": "https://pypi.org",
              "evidence_url": "https://pypi.org/project/apyds/0.0.20a1/"
            }
          }
        },
        "source_payload": {
          "html": "A deductive system",
          "link": "https://pypi.org/project/apyds/0.0.20a1/",
          "published": "Sun, 15 Mar 2026 10:45:52 GMT",
          "published_parsed": [
            2026,
            3,
            15,
            10,
            45,
            52,
            6,
            74,
            0
          ],
          "updated": "Sun, 15 Mar 2026 10:45:52 GMT",
          "updated_parsed": [
            2026,
            3,
            15,
            10,
            45,
            52,
            6,
            74,
            0
          ],
          "guid": ""
        }
      },
      {
        "source": "pypi_recent_updates",
        "id": "b0230526d96910db112b0f5376c0276b",
        "url": "https://pypi.org/project/skyvern-lite/1.0.3/",
        "published_at": "2026-03-15T10:45:51Z",
        "updated_at": "2026-03-15T10:45:51Z",
        "headline": "skyvern-lite 1.0.3",
        "content": {
          "excerpt_text": "Minimal cloud browser SDK for Skyvern — session lifecycle management via CDP.",
          "lang": "en"
        },
        "provenance": {
          "fetched_at": "2026-03-15T10:54:41Z",
          "evidence_urls": [
            "https://pypi.org/project/skyvern-lite/1.0.3/"
          ],
          "content_hash": "sha256:76921c34586946c89d06de62bdcdb65a3979a0a0c06ca42bf8fd883fbd44141e"
        },
        "signals": {
          "release": {
            "version": "1.0.3",
            "provenance": {
              "method": "title_regex",
              "authority": "PyPI Recent Updates",
              "authority_url": "https://pypi.org",
              "evidence_url": "https://pypi.org/project/skyvern-lite/1.0.3/"
            }
          }
        },
        "source_payload": {
          "html": "Minimal cloud browser SDK for Skyvern — session lifecycle management via CDP.",
          "link": "https://pypi.org/project/skyvern-lite/1.0.3/",
          "published": "Sun, 15 Mar 2026 10:45:51 GMT",
          "published_parsed": [
            2026,
            3,
            15,
            10,
            45,
            51,
            6,
            74,
            0
          ],
          "updated": "Sun, 15 Mar 2026 10:45:51 GMT",
          "updated_parsed": [
            2026,
            3,
            15,
            10,
            45,
            51,
            6,
            74,
            0
          ],
          "guid": ""
        }
      }
    ],
    "updated": [],
    "removed": []
  },
  "counts": {
    "items": 40,
    "updated": 0,
    "removed": 0
  },
  "integrity_reset": false
}
