{
  "cursor": "sha256:f861267e32e4b42297e42b982d775d39fc75dfd2e12e9339337fdd2b792e79cc",
  "prev_cursor": "sha256:bb1db3d541bbdf59134c89832c060ab7afd21b17982998b73659602ac9b2ac63",
  "changed": true,
  "generated_at": "2026-02-20T19:51:13Z",
  "ttl_sec": 3600,
  "latest_url": "/diff/apple_developer_releases/latest.json",
  "_protocol": {
    "standard": "ddv1",
    "spec": "/.well-known/diffdelta.json",
    "usage": "cursor SAME=no changes, STOP. counts.items>0→fetch latest_url. Schema guide in spec."
  },
  "counts": {
    "items": 48,
    "updated": 0,
    "removed": 0
  }
}
