{
  "cursor": "sha256:6effa11e35cc5028c185582310145b4a3af0cc681e52babc3b7a692459bbc65c",
  "prev_cursor": "sha256:6effa11e35cc5028c185582310145b4a3af0cc681e52babc3b7a692459bbc65c",
  "changed": false,
  "generated_at": "2026-03-04T11:04:01Z",
  "ttl_sec": 3600,
  "latest_url": "/diff/nvidia_press_releases/latest.json",
  "_protocol": {
    "standard": "ddv1",
    "spec": "/.well-known/diffdelta.json",
    "usage": "cursor SAME=no changes, STOP. counts.items>0→fetch latest_url. Schema guide in spec."
  },
  "counts": {
    "items": 20,
    "updated": 0,
    "removed": 0
  }
}
